Workbook

Sheet README
A1: SGR EXECUTIVE DASHBOARD | CONTROL CENTRE
A3: =HYPERLINK("#'HOME'!A1","HOME") -> HOME | B3: =HYPERLINK("#'FARMERS'!A1","FARMERS") -> FARMERS | C3: =HYPERLINK("#'SUBSCRIPTIONS'!A1","SUBSCRIPTIONS") -> SUBSCRIPTIONS | D3: =HYPERLINK("#'PRODUCTION'!A1","PRODUCTION") -> PRODUCTION | E3: =HYPERLINK("#'RECOVERY'!A1","RECOVERY") -> RECOVERY | F3: =HYPERLINK("#'DELIVERIES'!A1","DELIVERIES") -> DELIVERIES | G3: =HYPERLINK("#'FINANCE'!A1","FINANCE") -> FINANCE | H3: =HYPERLINK("#'REPORTS'!A1","REPORTS") -> REPORTS | I3: =HYPERLINK("#'SORGHUM BUDGET'!A1","SORGHUM BUDGET") -> SORGHUM BUDGET | J3: =HYPERLINK("#'MAIZE BUDGET'!A1","MAIZE BUDGET") -> MAIZE BUDGET

Sheet HOME
A1: STRATEGIC GRAIN RESERVE (SGR) 200 HA PLUS
A2: Executive Management Dashboard | Data snapshot through August 2026
A3: =HYPERLINK("#'HOME'!A1","HOME") -> HOME | B3: =HYPERLINK("#'FARMERS'!A1","FARMERS") -> FARMERS | C3: =HYPERLINK("#'SUBSCRIPTIONS'!A1","SUBSCRIPTIONS") -> SUBSCRIPTIONS | D3: =HYPERLINK("#'PRODUCTION'!A1","PRODUCTION") -> PRODUCTION | E3: =HYPERLINK("#'RECOVERY'!A1","RECOVERY") -> RECOVERY | F3: =HYPERLINK("#'DELIVERIES'!A1","DELIVERIES") -> DELIVERIES | G3: =HYPERLINK("#'FINANCE'!A1","FINANCE") -> FINANCE | H3: =HYPERLINK("#'REPORTS'!A1","REPORTS") -> REPORTS | J3: =HYPERLINK("#'MONTHLY SALARY'!A1","MONTHLY SALARY") -> MONTHLY SALARY | K3: =HYPERLINK("#'PROFIT & LOSS'!A1","PROFIT & LOSS") -> PROFIT & LOSS | L3: =HYPERLINK("#'BALANCE SHEET'!A1","BALANCE SHEET") -> BALANCE SHEET
A4: EXECUTIVE PERFORMANCE AT A GLANCE
A5: REGISTERED FARMERS | C5: PAID FARMERS | E5: PARTLY PAID FARMERS | G5: TOTAL SUBSCRIBED | I5: SUBSCRIPTION RATE | K5: SUBSCRIPTIONS RECEIVED
A6: =COUNTA(DATA_PIPELINE!$B$6:$B$601) -> 573 | C6: =COUNTIF(DATA_PIPELINE!$Y$6:$Y$601,"Paid") -> 18 | E6: =COUNTIF(DATA_PIPELINE!$Y$6:$Y$601,"Partly Paid") -> 38 | G6: =C6+E6 -> 56 | I6: =IFERROR(G6/A6,0) -> 0.097731239 | K6: =SUM(DATA_RECEIPTS!$E$6:$E$75) -> 17375
A7: TOTAL MEMBERS | C7: PAID | E7: PARTLY PAID | G7: PAID + PARTLY PAID | I7: REGISTERED | K7: TO DATE
A10: MAIZE TARGET | C10: MAIZE COMMITTED HA | E10: MAIZE VARIANCE | G10: SORGHUM TARGET | I10: SORGHUM COMMITTED HA | K10: SORGHUM VARIANCE
A11: 20000 | C11: =SUMIFS(DATA_PIPELINE!$M$6:$M$601,DATA_PIPELINE!$Y$6:$Y$601,"Paid")+SUMIFS(DATA_PIPELINE!$M$6:$M$601,DATA_PIPELINE!$Y$6:$Y$601,"Partly Paid") -> 1950 | E11: =C11-A11 -> -18050 | G11: 20000 | I11: =SUMIFS(DATA_PIPELINE!$N$6:$N$601,DATA_PIPELINE!$Y$6:$Y$601,"Paid")+SUMIFS(DATA_PIPELINE!$N$6:$N$601,DATA_PIPELINE!$Y$6:$Y$601,"Partly Paid") -> 5265 | K11: =I11-G11 -> -14735
A12: TARGET ACHIEVEMENT | C12: =IFERROR(C11/A11,0) -> 0.0975 | E12: TARGET GAP | G12: TARGET ACHIEVEMENT | I12: 0.195 | K12: TARGET GAP
A15: YTD RECEIPTS STATUS | C15: TOTAL RECEIPTS | E15: SEPTEMBER TOTAL RECEIPTS | G15: BANK BALANCE | I15: SUBSCRIPTION OUTSTANDING | K15: LAST DATA REFRESH
A16: =TODAY() -> 46295 | C16: =SUM(DATA_BANK!$C$6:$C$10) -> 17375 | E16: =SUMIFS(DATA_RECEIPTS!E:E, DATA_RECEIPTS!A:A, ">=2026-09-01", DATA_RECEIPTS!A:A, "<2026-10-01") -> 2725 | G16: =DATA_BANK!E10 -> 4125.12 | I16: =SUM(DATA_RECEIPTS!$F$6:$F$75) -> 14025 | K16: =TODAY() -> 46295
A20: Management navigation
A21: =HYPERLINK("#'FARMERS'!A1","Farmers") -> Farmers | C21: =HYPERLINK("#'SUBSCRIPTIONS'!A1","Subscriptions") -> Subscriptions | E21: =HYPERLINK("#'PRODUCTION'!A1","Production") -> Production | G21: =HYPERLINK("#'RECOVERY'!A1","Recovery Programme") -> Recovery Programme | I21: =HYPERLINK("#'DELIVERIES'!A1","Grain Deliveries") -> Grain Deliveries | K21: =HYPERLINK("#'FINANCE'!A1","Finance") -> Finance
A24: =HYPERLINK("#'REPORTS'!A1","Reports") -> Reports | C24: =HYPERLINK("#'DATA_PIPELINE'!A1","Data Pipeline") -> Data Pipeline | E24: =HYPERLINK("#'DATA_RECOVERY'!A1","Data Recovery") -> Data Recovery | G24: =HYPERLINK("#'DATA_RECEIPTS'!A1","Data Receipts") -> Data Receipts | I24: =HYPERLINK("#'DATA_EXPENSES'!A1","Data Expenses") -> Data Expenses | K24: =HYPERLINK("#'DATA_BANK'!A1","Data Bank") -> Data Bank
A27: SORGHUM 20,000 HA | PLANTING BUDGET CONTROL
A29: PAID MEMBERS | D29: PAID SORGHUM HA | G29: FUNDED HA | J29: 20,000 HA TARGET | M29: HA REMAINING
A30: =COUNTIF(DATA_PIPELINE!$Y$6:$Y$601,"Paid")+COUNTIF(DATA_PIPELINE!$Y$6:$Y$601,"Partly Paid") -> 56 | D30: =SUMIFS(DATA_PIPELINE!$N$6:$N$601,DATA_PIPELINE!$Y$6:$Y$601,"Paid")+SUMIFS(DATA_PIPELINE!$N$6:$N$601,DATA_PIPELINE!$Y$6:$Y$601,"Partly Paid") -> 5265 | G30: =MIN(D30,J30) -> 5265 | J30: =20000 -> 20000 | M30: =MAX(0,J30-G30) -> 14735
A32: COST / HA (HIRING) | D32: TOTAL COST | 20,000 HA | G32: BUDGET | FUNDED HA | J32: BUDGET REMAINING | M32: TARGET FUNDED %
A33: ='SORGHUM BUDGET'!I38 -> 873 | D33: =J30*A33 -> 17460000 | G33: =G30*A33 -> 4596345 | J33: =MAX(0,D33-G33) -> 12863655 | M33: =IFERROR(G30/J30,0) -> 0.26325
A35: BUDGET BREAKDOWN BY COST GROUP | G35: MANAGEMENT VIEW
A36: Cost Group | B36: Cost / Ha | C36: Cost @ 20,000 HA | D36: Cost @ Funded HA | E36: Share of Total
A37: Seed | B37: ='SORGHUM BUDGET'!I10+'SORGHUM BUDGET'!I11 -> 50 | C37: =B37*$J$30 -> 1000000 | D37: =B37*$G$30 -> 263250 | E37: =IFERROR(B37/$A$33,0) -> 0.057273769 | G37: Budget cost / ha | I37: ='SORGHUM BUDGET'!I38 -> 873
A38: Fertilisers | B38: ='SORGHUM BUDGET'!I14+'SORGHUM BUDGET'!I15 -> 268 | C38: =B38*$J$30 -> 5360000 | D38: =B38*$G$30 -> 1411020 | E38: =IFERROR(B38/$A$33,0) -> 0.3069874 | G38: Base source cost / ha | I38: ='SORGHUM BUDGET'!H38 -> 743
A39: Tillage | B39: ='SORGHUM BUDGET'!I18+'SORGHUM BUDGET'!I19+'SORGHUM BUDGET'!I20 -> 220 | C39: =B39*$J$30 -> 4400000 | D39: =B39*$G$30 -> 1158300 | E39: =IFERROR(B39/$A$33,0) -> 0.25200458 | G39: Paid members | I39: =COUNTIF(DATA_PIPELINE!$Y$6:$Y$601,"Paid")+COUNTIF(DATA_PIPELINE!$Y$6:$Y$601,"Partly Paid") -> 56
A40: Chemicals - Pre-emergence Herbicides | B40: ='SORGHUM BUDGET'!I24+'SORGHUM BUDGET'!I25+'SORGHUM BUDGET'!I26 -> 32 | C40: =B40*$J$30 -> 640000 | D40: =B40*$G$30 -> 168480 | E40: =IFERROR(B40/$A$33,0) -> 0.036655212 | G40: Paid sorghum hectares | I40: =SUMIFS(DATA_PIPELINE!$N$6:$N$601,DATA_PIPELINE!$Y$6:$Y$601,"Paid")+SUMIFS(DATA_PIPELINE!$N$6:$N$601,DATA_PIPELINE!$Y$6:$Y$601,"Partly Paid") -> 5265
A41: Chemicals - Post-emergence Herbicides | B41: ='SORGHUM BUDGET'!I28+'SORGHUM BUDGET'!I29 -> 15 | C41: =B41*$J$30 -> 300000 | D41: =B41*$G$30 -> 78975 | E41: =IFERROR(B41/$A$33,0) -> 0.017182131 | G41: Funded hectares (capped) | I41: =G30 -> 5265
A42: Chemicals - Insecticides / Fungicides | B42: ='SORGHUM BUDGET'!I31+'SORGHUM BUDGET'!I32+'SORGHUM BUDGET'!I33 -> 18 | C42: =B42*$J$30 -> 360000 | D42: =B42*$G$30 -> 94770 | E42: =IFERROR(B42/$A$33,0) -> 0.020618557 | G42: Funding gap to 20,000 HA | I42: =MAX(0,J30-G30) -> 14735
A43: Packaging | B43: ='SORGHUM BUDGET'!I34 -> 20 | C43: =B43*$J$30 -> 400000 | D43: =B43*$G$30 -> 105300 | E43: =IFERROR(B43/$A$33,0) -> 0.022909507 | G43: Budget for funded hectares | I43: =G33 -> 4596345
A44: Combine | B44: ='SORGHUM BUDGET'!I35 -> 90 | C44: =B44*$J$30 -> 1800000 | D44: =B44*$G$30 -> 473850 | E44: =IFERROR(B44/$A$33,0) -> 0.10309278 | G44: Budget for full 20,000 HA | I44: =D33 -> 17460000
A45: Labour | B45: ='SORGHUM BUDGET'!I36 -> 80 | C45: =B45*$J$30 -> 1600000 | D45: =B45*$G$30 -> 421200 | E45: =IFERROR(B45/$A$33,0) -> 0.09163803 | G45: Budget sheet
A46: Transport | B46: ='SORGHUM BUDGET'!I37 -> 80 | C46: =B46*$J$30 -> 1600000 | D46: =B46*$G$30 -> 421200 | E46: =IFERROR(B46/$A$33,0) -> 0.09163803
A47: TOTAL | B47: =SUM(B37:B46) -> 873 | C47: =SUM(C37:C46) -> 17460000 | D47: =SUM(D37:D46) -> 4596345 | E47: =SUM(E37:E46) -> 1
A50: MAIZE 20,000 HA | PLANTING BUDGET CONTROL
A52: PAID MEMBERS | D52: PAID MAIZE HA | G52: FUNDED HA | J52: 20,000 HA TARGET | M52: HA REMAINING
A53: =COUNTIF(DATA_PIPELINE!$Y$6:$Y$601,"Paid")+COUNTIF(DATA_PIPELINE!$Y$6:$Y$601,"Partly Paid") -> 56 | D53: =SUMIFS(DATA_PIPELINE!$M$6:$M$601,DATA_PIPELINE!$Y$6:$Y$601,"Paid")+SUMIFS(DATA_PIPELINE!$M$6:$M$601,DATA_PIPELINE!$Y$6:$Y$601,"Partly Paid") -> 1950 | G53: =MIN(D53,J53) -> 1950 | J53: =20000 -> 20000 | M53: =MAX(0,J53-G53) -> 18050
A55: COST / HA (HIRING) | D55: TOTAL COST | 20,000 HA | G55: BUDGET | FUNDED HA | J55: BUDGET REMAINING | M55: TARGET FUNDED %
A56: ='MAIZE BUDGET'!E49 -> 1119.825 | D56: =J53*A56 -> 22396500 | G56: =G53*A56 -> 2183658.8 | J56: =MAX(0,D56-G56) -> 20212841 | M56: =IFERROR(G53/J53,0) -> 0.0975
A58: BUDGET BREAKDOWN BY COST GROUP | G58: MANAGEMENT VIEW
A59: Cost Group | B59: Cost / Ha | C59: Cost @ 20,000 HA | D59: Cost @ Funded HA | E59: Share of Total | G59: Budget cost / ha | I59: ='MAIZE BUDGET'!E49 -> 1119.825
A60: Tillage & Farm Machinery | B60: ='MAIZE BUDGET'!E35+'MAIZE BUDGET'!E36+'MAIZE BUDGET'!E37 -> 310 | C60: =B60*$J$53 -> 6200000 | D60: =B60*$G$53 -> 604500 | E60: =IFERROR(B60/$A$56,0) -> 0.27682897 | G60: Base source cost / ha | I60: ='MAIZE BUDGET'!D30 -> 1066.5
A61: Seed & Fertilisers | B61: ='MAIZE BUDGET'!E38+'MAIZE BUDGET'!E39+'MAIZE BUDGET'!E40 -> 514.5 | C61: =B61*$J$53 -> 10290000 | D61: =B61*$G$53 -> 1003275 | E61: =IFERROR(B61/$A$56,0) -> 0.45944679 | G61: Paid members | I61: =COUNTIF(DATA_PIPELINE!$Y$6:$Y$601,"Paid")+COUNTIF(DATA_PIPELINE!$Y$6:$Y$601,"Partly Paid") -> 56
A62: Chemicals | B62: ='MAIZE BUDGET'!E41+'MAIZE BUDGET'!E42+'MAIZE BUDGET'!E43+'MAIZE BUDGET'!E44+'MAIZE BUDGET'!E45 -> 112 | C62: =B62*$J$53 -> 2240000 | D62: =B62*$G$53 -> 218400 | E62: =IFERROR(B62/$A$56,0) -> 0.10001563 | G62: Paid maize hectares | I62: =SUMIFS(DATA_PIPELINE!$M$6:$M$601,DATA_PIPELINE!$Y$6:$Y$601,"Paid")+SUMIFS(DATA_PIPELINE!$M$6:$M$601,DATA_PIPELINE!$Y$6:$Y$601,"Partly Paid") -> 1950
A63: Harvesting | B63: ='MAIZE BUDGET'!E46 -> 80 | C63: =B63*$J$53 -> 1600000 | D63: =B63*$G$53 -> 156000 | E63: =IFERROR(B63/$A$56,0) -> 0.071439734 | G63: Funded hectares (capped) | I63: =G53 -> 1950
A64: Labour | B64: ='MAIZE BUDGET'!E47 -> 50 | C64: =B64*$J$53 -> 1000000 | D64: =B64*$G$53 -> 97500 | E64: =IFERROR(B64/$A$56,0) -> 0.044649834 | G64: Funding gap to 20,000 HA | I64: =MAX(0,J53-G53) -> 18050
A65: Miscellaneous | B65: ='MAIZE BUDGET'!E48 -> 53.325 | C65: =B65*$J$53 -> 1066500 | D65: =B65*$G$53 -> 103983.75 | E65: =IFERROR(B65/$A$56,0) -> 0.047619048 | G65: Budget for funded hectares | I65: =G56 -> 2183658.8
A66: TOTAL | B66: =SUM(B60:B65) -> 1119.825 | C66: =SUM(C60:C65) -> 22396500 | D66: =SUM(D60:D65) -> 2183658.8 | E66: =SUM(E60:E65) -> 1 | G66: Budget for full 20,000 HA | I66: =D56 -> 22396500

Sheet SORGHUM BUDGET
A1: =HYPERLINK("#'HOME'!A1","HOME") -> HOME | B1: =HYPERLINK("#'SORGHUM BUDGET'!A1","SORGHUM BUDGET") -> SORGHUM BUDGET | C1: =HYPERLINK("#'PRODUCTION'!A1","PRODUCTION") -> PRODUCTION | D1: =HYPERLINK("#'SUBSCRIPTIONS'!A1","SUBSCRIPTIONS") -> SUBSCRIPTIONS
A2: SGR SORGHUM BUDGET 2026
A3: SORGHUM 20,000 HA | EXECUTIVE BUDGET MODEL
A5: SOURCE BUDGET INPUT (editable)
D9: Rate/Ha | E9: Unit | F9: Total Requirement | G9: Unit Cost | H9: Total Cost | I9: Total Cost Hiring
A10: Seed | B10: SCXH102/NS-5511 | D10: 10 | E10: Kg | F10: 1 | G10: 40 | H10: =F10*G10 -> 40 | I10: =H10 -> 40
B11: Seed Saffener | C11: Benoxacor | D11: 0.06 | E11: kg | F11: 1 | G11: 10 | H11: =F11*G11 -> 10 | I11: =H11 -> 10
I12: =H12 -> 0
A13: Fertilisers | I13: =H13 -> 0
B14: Basal fertiliser | D14: 200 | E14: kg | F14: =D14/50 -> 4 | G14: 32 | H14: =F14*G14 -> 128 | I14: =H14 -> 128
B15: Top Dressing | D15: 200 | E15: kg | F15: =D15/50 -> 4 | G15: 35 | H15: =F15*G15 -> 140 | I15: =H15 -> 140
I16: =H16 -> 0
A17: Tillage | I17: =H17 -> 0
A18: Discing | B18: Fuel | D18: 20 | E18: l | F18: 1 | G18: 2 | H18: 40 | I18: =50+40 -> 90
A19: Planting | B19: Fuel | D19: 15 | E19: l | F19: 1 | G19: 2 | H19: 30 | I19: =40+30 -> 70
A20: Spraying and fertilisation(7 times) | B20: Fuel | D20: 5 | E20: l | F20: 2 | G20: 2 | H20: 20 | I20: =20+40 -> 60
I21: =H21 -> 0
A22: Chemicals | I22: =H22 -> 0
A23: Pre-emergence Herbicides | C23: Weeds Controlled | I23: =H23 -> 0
B24: Glyphostae(granules) | C24: All | D24: 2 | E24: Kg | F24: 2 | G24: 6 | H24: 12 | I24: =H24 -> 12
B25: S-Metolachlor | C25: Broadleaf/grasses | D25: 1.2 | E25: L | F25: 1.2 | G25: 10 | H25: 12 | I25: =H25 -> 12
B26: Atrazine | C26: Annual Broadleaf | D26: 2 | E26: L | F26: 2 | G26: 4 | H26: 8 | I26: =H26 -> 8
A27: Post Emergence Herbicides | I27: =H27 -> 0
B28: Atrazine | C28: Broadleaf weeds | D28: 3 | E28: L | F28: 1 | G28: 4 | H28: 12 | I28: =H28 -> 12
B29: CP Wetter | C29: sticker / adjuvant | D29: 0.3 | E29: L | F29: 0.3 | G29: 3 | H29: 3 | I29: =H29 -> 3
A30: Insecticides | I30: =H30 -> 0
B31: Elegent Star | C31: Fall- armyworm | D31: 0.15 | E31: L | F31: 0.15 | G31: 8 | H31: 8 | I31: =H31 -> 8
B32: Dimethoate | C32: Aphids & leaf eaters | D32: 0.56 | E32: L | F32: 0.56 | G32: 8.9 | H32: 5 | I32: =H32 -> 5
B33: Tebiconazole | C33: Fungal Diseases | D33: 0.25 | E33: L | F33: 0.25 | G33: 5 | H33: 5 | I33: =H33 -> 5
A34: Packaging | C34: 4 tonnes per ha | D34: 80 | F34: 5 | G34: 4 | H34: 20 | I34: =H34 -> 20
A35: Combine | C35: dry rate | H35: 90 | I35: =H35 -> 90
A36: Labour days | C36: 20 labour days | D36: 5 | E36: days | F36: 4 | G36: 20 | H36: 80 | I36: =H36 -> 80
A37: Transport | C37: nearest gmb 0.15c/km /tonne | F37: 10 | G37: 8 | H37: 80 | I37: =H37 -> 80
A38: Total | H38: =SUM(H10:H37) -> 743 | I38: =SUM(I10:I37) -> 873
A46: EXECUTIVE COST GROUP DETAIL | HIRING RATES
A47: Group | B47: Item | C47: Rate/Ha | D47: Unit | E47: Cost/Ha | F47: Cost @20,000 HA | G47: Cost @ Funded HA | H47: Source Row
A48: Seed | B48: SCXH102/NS-5511 | C48: =D10 -> 10 | D48: =E10 -> Kg | E48: =I10 -> 40 | F48: =E48*20000 -> 800000 | G48: =E48*HOME!$G$30 -> 210600 | H48: 10
A49: Seed | B49: Seed Safener - Benoxacor | C49: =D11 -> 0.06 | D49: =E11 -> kg | E49: =I11 -> 10 | F49: =E49*20000 -> 200000 | G49: =E49*HOME!$G$30 -> 52650 | H49: 11
A50: Fertilisers | B50: Basal fertiliser | C50: =D14 -> 200 | D50: =E14 -> kg | E50: =I14 -> 128 | F50: =E50*20000 -> 2560000 | G50: =E50*HOME!$G$30 -> 673920 | H50: 14
A51: Fertilisers | B51: Top Dressing | C51: =D15 -> 200 | D51: =E15 -> kg | E51: =I15 -> 140 | F51: =E51*20000 -> 2800000 | G51: =E51*HOME!$G$30 -> 737100 | H51: 15
A52: Tillage | B52: Discing | C52: =D18 -> 20 | D52: =E18 -> l | E52: =I18 -> 90 | F52: =E52*20000 -> 1800000 | G52: =E52*HOME!$G$30 -> 473850 | H52: 18
A53: Tillage | B53: Planting | C53: =D19 -> 15 | D53: =E19 -> l | E53: =I19 -> 70 | F53: =E53*20000 -> 1400000 | G53: =E53*HOME!$G$30 -> 368550 | H53: 19
A54: Tillage | B54: Spraying and fertilisation (7 times) | C54: =D20 -> 5 | D54: =E20 -> l | E54: =I20 -> 60 | F54: =E54*20000 -> 1200000 | G54: =E54*HOME!$G$30 -> 315900 | H54: 20
A55: Chemicals - Pre-emergence Herbicides | B55: Glyphostae (granules) | C55: =D24 -> 2 | D55: =E24 -> Kg | E55: =I24 -> 12 | F55: =E55*20000 -> 240000 | G55: =E55*HOME!$G$30 -> 63180 | H55: 24
A56: Chemicals - Pre-emergence Herbicides | B56: S-Metolachlor | C56: =D25 -> 1.2 | D56: =E25 -> L | E56: =I25 -> 12 | F56: =E56*20000 -> 240000 | G56: =E56*HOME!$G$30 -> 63180 | H56: 25
A57: Chemicals - Pre-emergence Herbicides | B57: Atrazine | C57: =D26 -> 2 | D57: =E26 -> L | E57: =I26 -> 8 | F57: =E57*20000 -> 160000 | G57: =E57*HOME!$G$30 -> 42120 | H57: 26
A58: Chemicals - Post-emergence Herbicides | B58: Atrazine | C58: =D28 -> 3 | D58: =E28 -> L | E58: =I28 -> 12 | F58: =E58*20000 -> 240000 | G58: =E58*HOME!$G$30 -> 63180 | H58: 28
A59: Chemicals - Post-emergence Herbicides | B59: CP Wetter | C59: =D29 -> 0.3 | D59: =E29 -> L | E59: =I29 -> 3 | F59: =E59*20000 -> 60000 | G59: =E59*HOME!$G$30 -> 15795 | H59: 29
A60: Chemicals - Insecticides / Fungicides | B60: Elegent Star | C60: =D31 -> 0.15 | D60: =E31 -> L | E60: =I31 -> 8 | F60: =E60*20000 -> 160000 | G60: =E60*HOME!$G$30 -> 42120 | H60: 31
A61: Chemicals - Insecticides / Fungicides | B61: Dimethoate | C61: =D32 -> 0.56 | D61: =E32 -> L | E61: =I32 -> 5 | F61: =E61*20000 -> 100000 | G61: =E61*HOME!$G$30 -> 26325 | H61: 32
A62: Chemicals - Insecticides / Fungicides | B62: Tebiconazole | C62: =D33 -> 0.25 | D62: =E33 -> L | E62: =I33 -> 5 | F62: =E62*20000 -> 100000 | G62: =E62*HOME!$G$30 -> 26325 | H62: 33
A63: Packaging | B63: Packaging | C63: =D34 -> 80 | D63: =E34 -> 0 | E63: =I34 -> 20 | F63: =E63*20000 -> 400000 | G63: =E63*HOME!$G$30 -> 105300 | H63: 34
A64: Combine | B64: Combine | C64: =D35 -> 0 | D64: =E35 -> 0 | E64: =I35 -> 90 | F64: =E64*20000 -> 1800000 | G64: =E64*HOME!$G$30 -> 473850 | H64: 35
A65: Labour | B65: Labour days | C65: =D36 -> 5 | D65: =E36 -> days | E65: =I36 -> 80 | F65: =E65*20000 -> 1600000 | G65: =E65*HOME!$G$30 -> 421200 | H65: 36
A66: Transport | B66: Transport | C66: =D37 -> 0 | D66: =E37 -> 0 | E66: =I37 -> 80 | F66: =E66*20000 -> 1600000 | G66: =E66*HOME!$G$30 -> 421200 | H66: 37
A67: TOTAL | E67: =SUM(E48:E66) -> 873 | F67: =SUM(F48:F66) -> 17460000 | G67: =SUM(G48:G66) -> 4596345
A70: MODEL: Paid hectares come from DATA_PIPELINE SORGHUM (HA) for farmers with CALCULATED PAYMENT STATUS = Paid. Funded hectares are capped at the 20,000 HA target.

Sheet REPORTS
A1: MANAGEMENT REPORTS
A2: Print-ready A4 landscape report pages
A3: =HYPERLINK("#'HOME'!A1","HOME") -> HOME | B3: =HYPERLINK("#'FARMERS'!A1","FARMERS") -> FARMERS | C3: =HYPERLINK("#'SUBSCRIPTIONS'!A1","SUBSCRIPTIONS") -> SUBSCRIPTIONS | D3: =HYPERLINK("#'PRODUCTION'!A1","PRODUCTION") -> PRODUCTION | E3: =HYPERLINK("#'RECOVERY'!A1","RECOVERY") -> RECOVERY | F3: =HYPERLINK("#'DELIVERIES'!A1","DELIVERIES") -> DELIVERIES | G3: =HYPERLINK("#'FINANCE'!A1","FINANCE") -> FINANCE | H3: =HYPERLINK("#'REPORTS'!A1","REPORTS") -> REPORTS
A5: =HYPERLINK("#'HOME'!A1","Executive Summary Report") -> Executive Summary Report | D5: =HYPERLINK("#'FARMERS'!A1","Farmer Register") -> Farmer Register | G5: =HYPERLINK("#'SUBSCRIPTIONS'!A1","Subscription Report") -> Subscription Report | J5: =HYPERLINK("#'SORGHUM BUDGET'!A1","Sorghum 20,000 HA Budget") -> Sorghum 20,000 HA Budget
A8: =HYPERLINK("#'RECOVERY'!A1","Recovery Report") -> Recovery Report | D8: =HYPERLINK("#'DELIVERIES'!A1","Grain Delivery Report") -> Grain Delivery Report | G8: =HYPERLINK("#'FINANCE'!A1","Financial Report") -> Financial Report | J8: =HYPERLINK("#'FINANCE'!A1","Monthly Management Report") -> Monthly Management Report
J10: =HYPERLINK("#'MONTHLY SALARY'!A1","MONTHLY SALARY") -> MONTHLY SALARY
A11: =HYPERLINK("#'HOME'!A1","Annual Performance Report") -> Annual Performance Report | J11: =HYPERLINK("#'PROFIT & LOSS'!A1","PROFIT & LOSS") -> PROFIT & LOSS
J12: =HYPERLINK("#'BALANCE SHEET'!A1","BALANCE SHEET") -> BALANCE SHEET
A15: Printing setup
A16: All management dashboard sheets are configured for A4 landscape printing. Use File → Print → Print Active Sheets after selecting the desired dashboard/report.

Sheet DATA_PIPELINE
A1: DATA PIPELINE
A2: Imported source snapshot — update this table when source workbooks change.
A3: =HYPERLINK("#'HOME'!A1","HOME") -> HOME | B3: =HYPERLINK("#'FARMERS'!A1","FARMERS") -> FARMERS | C3: =HYPERLINK("#'SUBSCRIPTIONS'!A1","SUBSCRIPTIONS") -> SUBSCRIPTIONS | D3: =HYPERLINK("#'PRODUCTION'!A1","PRODUCTION") -> PRODUCTION | E3: =HYPERLINK("#'RECOVERY'!A1","RECOVERY") -> RECOVERY | F3: =HYPERLINK("#'DELIVERIES'!A1","DELIVERIES") -> DELIVERIES | G3: =HYPERLINK("#'FINANCE'!A1","FINANCE") -> FINANCE | H3: =HYPERLINK("#'REPORTS'!A1","REPORTS") -> REPORTS
A5: SEQ | B5: FARMER NAME | C5: FARM NAME | D5: CLUSTER | E5: ID NUMBER | F5: CONTACT | G5: DISTRCT | H5: PROVINCE | I5: WARD | J5: STATUS | K5: SUB PAID | L5: SUB BAL | M5: MAIZE (HA)-2026/27 | N5: SORGHUM (HA)-2026/27 | O5: TOTAL DEBT | P5: SORGHUM SOLD | Q5: SORGHUM VALUE | R5: BALANCE | S5: REPAYMENT (%) | T5: TOTAL CONTRACTED HA | U5: SUBSCRIPTION CATEGORY | V5: EXPECTED SUBSCRIPTION | W5: PAID AMOUNT | X5: OUTSTANDING | Y5: CALCULATED PAYMENT STATUS
A6: 1 | B6: BEHANE FLORENCE | C6: NK | D6: DANMORE MUDAVANHU | E6: 63-676409-M-39 | F6: 772816543 | G6: CHEGUTU | H6: MASHWEST | I6: 21 | J6: EXISTING | K6: 0 | L6: 0 | M6: 50 | N6: 50 | O6: 10273.28 | P6: 0 | Q6: 0 | R6: 10273.28 | S6: - | T6: 50 | U6: Category A | V6: 500 | W6: =DATA_PIPELINE!$K6 -> 0 | X6: =DATA_PIPELINE!$V6-DATA_PIPELINE!$W6 -> 500 | Y6: =IF(DATA_PIPELINE!$X6=0,"Paid",IF(DATA_PIPELINE!$W6=0,"Unpaid","Partly Paid")) -> Unpaid
A7: 2 | B7: ZINYOWERA DONALD | C7: UNIT 40 COBEN ESTATES | D7: DANMORE MUDAVANHU | E7: 63-259741-M-24 | F7: 774739609 | G7: CHEGUTU | H7: MASHWEST | J7: EXISTING | K7: 0 | L7: 0 | M7: 35 | N7: 50 | O7: 6466.9 | P7: 0 | Q7: 0 | R7: 6466.9 | S7: - | T7: 50 | U7: Category A | V7: 500 | W7: =DATA_PIPELINE!$K7 -> 0 | X7: =DATA_PIPELINE!$V7-DATA_PIPELINE!$W7 -> 500 | Y7: =IF(DATA_PIPELINE!$X7=0,"Paid",IF(DATA_PIPELINE!$W7=0,"Unpaid","Partly Paid")) -> Unpaid
A8: 3 | B8: MUNEMO MOSES | C8: AVOG 8 A COBURN ESTSTES | D8: DANMORE MUDAVANHU | E8: 63-431627-V-25 | F8: 771487499 | G8: CHEGUTU | H8: MASHWEST | J8: EXISTING | K8: 0 | L8: 0 | M8: 40 | N8: 40 | O8: 7596.28 | P8: 0 | Q8: 0 | R8: 7596.28 | S8: - | T8: 40 | U8: Category A | V8: 500 | W8: =DATA_PIPELINE!$K8 -> 0 | X8: =DATA_PIPELINE!$V8-DATA_PIPELINE!$W8 -> 500 | Y8: =IF(DATA_PIPELINE!$X8=0,"Paid",IF(DATA_PIPELINE!$W8=0,"Unpaid","Partly Paid")) -> Unpaid
A9: 4 | B9: GORORO HARROED | C9: COBEAN STATES | D9: DANMORE MUDAVANHU | E9: 63-202346-B-25 | F9: 773040703 | G9: CHEGUTU | H9: MASHWEST | I9: 29 | J9: EXISTING | K9: 0 | L9: 0 | M9: 30 | N9: 30 | O9: 6008.43 | P9: 0 | Q9: 0 | R9: 6008.43 | S9: - | T9: 30 | U9: Category A | V9: 500 | W9: =DATA_PIPELINE!$K9 -> 0 | X9: =DATA_PIPELINE!$V9-DATA_PIPELINE!$W9 -> 500 | Y9: =IF(DATA_PIPELINE!$X9=0,"Paid",IF(DATA_PIPELINE!$W9=0,"Unpaid","Partly Paid")) -> Unpaid
A10: 5 | B10: MATHUTHU FUNNY | C10: COBEAN ESTATE | D10: DANMORE MUDAVANHU | E10: 29-075854-N-21 | F10: 712521593 | G10: CHEGUTU | H10: MASHWEST | I10: 29 | J10: EXISTING | K10: 0 | L10: 0 | M10: 20 | N10: 20 | O10: 4415.12 | P10: 0 | Q10: 0 | R10: 4415.12 | S10: - | T10: 20 | U10: Category A | V10: 500 | W10: =DATA_PIPELINE!$K10 -> 0 | X10: =DATA_PIPELINE!$V10-DATA_PIPELINE!$W10 -> 500 | Y10: =IF(DATA_PIPELINE!$X10=0,"Paid",IF(DATA_PIPELINE!$W10=0,"Unpaid","Partly Paid")) -> Unpaid
A11: 6 | B11: MKWENA CAUL | C11: 43 COBEAN ESTATE | D11: DANMORE MUDAVANHU | E11: 70-2000429-T-04 | F11: 785980422 | G11: CHEGUTU | H11: MASHEAST | I11: 29 | J11: EXISTING | K11: 0 | L11: 0 | M11: 20 | N11: 20 | O11: 4415.12 | P11: 0 | Q11: 0 | R11: 4415.12 | S11: - | T11: 20 | U11: Category A | V11: 500 | W11: =DATA_PIPELINE!$K11 -> 0 | X11: =DATA_PIPELINE!$V11-DATA_PIPELINE!$W11 -> 500 | Y11: =IF(DATA_PIPELINE!$X11=0,"Paid",IF(DATA_PIPELINE!$W11=0,"Unpaid","Partly Paid")) -> Unpaid
A12: 7 | B12: JANDELES VALERIE | C12: CHIKAGO FARM | D12: DANMORE MUDAVANHU | E12: 63-708750-Q-00 | F12: 772216457 | G12: CHEGUTU | H12: MASHWEST | I12: 29 | J12: EXISTING | K12: 0 | L12: 0 | M12: 25 | N12: 25 | O12: 5316.94 | P12: 0 | Q12: 0 | R12: 5316.94 | S12: - | T12: 25 | U12: Category A | V12: 500 | W12: =DATA_PIPELINE!$K12 -> 0 | X12: =DATA_PIPELINE!$V12-DATA_PIPELINE!$W12 -> 500 | Y12: =IF(DATA_PIPELINE!$X12=0,"Paid",IF(DATA_PIPELINE!$W12=0,"Unpaid","Partly Paid")) -> Unpaid
A13: 8 | B13: MOYO CHARLES | C13: 25 COBEAN ESTATE | D13: DANMORE MUDAVANHU | E13: 29-062067-C-21 | F13: 718363313 | G13: CHEGUTU | H13: MASHWEST | I13: 29 | J13: EXISTING | K13: 0 | L13: 0 | M13: 20 | N13: 20 | O13: 4415.12 | P13: 0 | Q13: 0 | R13: 4415.12 | S13: - | T13: 20 | U13: Category A | V13: 500 | W13: =DATA_PIPELINE!$K13 -> 0 | X13: =DATA_PIPELINE!$V13-DATA_PIPELINE!$W13 -> 500 | Y13: =IF(DATA_PIPELINE!$X13=0,"Paid",IF(DATA_PIPELINE!$W13=0,"Unpaid","Partly Paid")) -> Unpaid
A14: 9 | B14: CHIKOMWE SHINE | C14: FAUN FARM PLOT 1 | D14: DANMORE MUDAVANHU | E14: 38-047571-E-38 | F14: 712730426 | G14: CHEGUTU | H14: MASHWEST | J14: EXISTING | K14: 0 | L14: 0 | M14: 80 | N14: 80 | O14: 12654.97 | P14: 0 | Q14: 0 | R14: 12654.97 | S14: - | T14: 80 | U14: Category A | V14: 500 | W14: =DATA_PIPELINE!$K14 -> 0 | X14: =DATA_PIPELINE!$V14-DATA_PIPELINE!$W14 -> 500 | Y14: =IF(DATA_PIPELINE!$X14=0,"Paid",IF(DATA_PIPELINE!$W14=0,"Unpaid","Partly Paid")) -> Unpaid
A15: 10 | B15: MUDAVANHU D | C15: MUDAVANHU FARM CHEGUTU | D15: DANMORE MUDAVANHU | E15: 27-165809-C-03 | F15: 772960915 | G15: CHEGUTU | H15: MASHWEST | J15: EXISTING | K15: 0 | L15: 0 | M15: 100 | N15: 100 | O15: 27964.77 | P15: 0 | Q15: 0 | R15: 27964.77 | S15: - | T15: 100 | U15: Category A | V15: 500 | W15: =DATA_PIPELINE!$K15 -> 0 | X15: =DATA_PIPELINE!$V15-DATA_PIPELINE!$W15 -> 500 | Y15: =IF(DATA_PIPELINE!$X15=0,"Paid",IF(DATA_PIPELINE!$W15=0,"Unpaid","Partly Paid")) -> Unpaid
A16: 11 | B16: GORA DOCAS | C16: PLOT 4 JAMAICA FARM | D16: DANMORE MUDAVANHU | E16: 32-188882-P-26 | F16: 773409156 | G16: CHEGUTU | H16: MASHWEST | J16: EXISTING | K16: 0 | L16: 0 | M16: 15 | N16: 15 | O16: 2807.94 | P16: 0 | Q16: 0 | R16: 2807.94 | S16: - | T16: 15 | U16: Category A | V16: 500 | W16: =DATA_PIPELINE!$K16 -> 0 | X16: =DATA_PIPELINE!$V16-DATA_PIPELINE!$W16 -> 500 | Y16: =IF(DATA_PIPELINE!$X16=0,"Paid",IF(DATA_PIPELINE!$W16=0,"Unpaid","Partly Paid")) -> Unpaid
A17: 12 | B17: MAVUNGA COMBOSI S | C17: HIPPOVALE FARM PLOT 5 | D17: DANMORE MUDAVANHU | E17: 08-285801-E-32 | F17: 715082150 | G17: CHEGUTU | H17: MASHWEST | J17: EXISTING | K17: 0 | L17: 0 | M17: 10 | N17: 10 | O17: 4433.03 | P17: 0 | Q17: 0 | R17: 4433.03 | S17: - | T17: 10 | U17: Category A | V17: 500 | W17: =DATA_PIPELINE!$K17 -> 0 | X17: =DATA_PIPELINE!$V17-DATA_PIPELINE!$W17 -> 500 | Y17: =IF(DATA_PIPELINE!$X17=0,"Paid",IF(DATA_PIPELINE!$W17=0,"Unpaid","Partly Paid")) -> Unpaid
A18: 13 | B18: MWAMLOWE OLIVIA | C18: 2 AQUARUS FARM GADZEMA | D18: DANMORE MUDAVANHU | E18: 24066249-Q-85 | F18: 772407927 | G18: CHEGUTU | H18: MASHWEST | J18: EXISTING | K18: 0 | L18: 0 | M18: 20 | N18: 20 | O18: 4743.76 | P18: 0 | Q18: 0 | R18: 4743.76 | S18: - | T18: 20 | U18: Category A | V18: 500 | W18: =DATA_PIPELINE!$K18 -> 0 | X18: =DATA_PIPELINE!$V18-DATA_PIPELINE!$W18 -> 500 | Y18: =IF(DATA_PIPELINE!$X18=0,"Paid",IF(DATA_PIPELINE!$W18=0,"Unpaid","Partly Paid")) -> Unpaid
A19: 14 | B19: KADZOMBE TRUST | C19: THE GROOVE FARM 1 | D19: DANMORE MUDAVANHU | E19: 32-123646-F-71 | F19: 783308067 | G19: CHEGUTU | H19: MASHWEST | J19: EXISTING | K19: 0 | L19: 0 | M19: 10 | N19: 10 | O19: 273 | P19: 0 | Q19: 0 | R19: 273 | S19: - | T19: 10 | U19: Category A | V19: 500 | W19: =DATA_PIPELINE!$K19 -> 0 | X19: =DATA_PIPELINE!$V19-DATA_PIPELINE!$W19 -> 500 | Y19: =IF(DATA_PIPELINE!$X19=0,"Paid",IF(DATA_PIPELINE!$W19=0,"Unpaid","Partly Paid")) -> Unpaid
A20: 15 | B20: MUBWANDARIKWA K | C20: COBUN ESTATE | D20: DANMORE MUDAVANHU | E20: 18-064080-T-27 | F20: 772590002 | G20: CHEGUTU | H20: MASHWEST | J20: EXISTING | K20: 0 | L20: 0 | M20: 30 | N20: 30 | O20: 7215.09 | P20: 0 | Q20: 0 | R20: 7215.09 | S20: - | T20: 30 | U20: Category A | V20: 500 | W20: =DATA_PIPELINE!$K20 -> 0 | X20: =DATA_PIPELINE!$V20-DATA_PIPELINE!$W20 -> 500 | Y20: =IF(DATA_PIPELINE!$X20=0,"Paid",IF(DATA_PIPELINE!$W20=0,"Unpaid","Partly Paid")) -> Unpaid
A21: 16 | B21: CHIWERA BLESSING | C21: ITAFA FARM , CTC | D21: DANMORE MUDAVANHU | E21: 18-088449-G-18 | F21: 772714503 | G21: KADOMA | H21: MASHWEST | I21: 4 | J21: EXISTING | K21: 0 | L21: 0 | M21: 60 | N21: 80 | O21: 20224.72 | P21: 0 | Q21: 0 | R21: 20224.72 | S21: - | T21: 80 | U21: Category A | V21: 500 | W21: =DATA_PIPELINE!$K21 -> 0 | X21: =DATA_PIPELINE!$V21-DATA_PIPELINE!$W21 -> 500 | Y21: =IF(DATA_PIPELINE!$X21=0,"Paid",IF(DATA_PIPELINE!$W21=0,"Unpaid","Partly Paid")) -> Unpaid
A22: 17 | B22: MACHIYA TAKUNDA | C22: PLOT 14 RAILWAY FARM | D22: DANMORE MUDAVANHU | E22: 24-181927-C22 | F22: 771525189 | G22: KADOMA | H22: MASHWEST | J22: EXISTING | K22: 0 | L22: 0 | M22: 25 | N22: 40 | O22: 6639.56 | P22: 0 | Q22: 0 | R22: 6639.56 | S22: - | T22: 40 | U22: Category A | V22: 500 | W22: =DATA_PIPELINE!$K22 -> 0 | X22: =DATA_PIPELINE!$V22-DATA_PIPELINE!$W22 -> 500 | Y22: =IF(DATA_PIPELINE!$X22=0,"Paid",IF(DATA_PIPELINE!$W22=0,"Unpaid","Partly Paid")) -> Unpaid
A23: 18 | B23: JAMELA BEATRICE | C23: COMBE FARM KADOMA | D23: DANMORE MUDAVANHU | E23: 24-097588-E-24 | F23: 772207146 | G23: KADOMA | H23: MASHWEST | J23: EXISTING | K23: 0 | L23: 0 | M23: 50 | N23: 50 | O23: 9777.72 | P23: 0 | Q23: 0 | R23: 9777.72 | S23: - | T23: 50 | U23: Category A | V23: 500 | W23: =DATA_PIPELINE!$K23 -> 0 | X23: =DATA_PIPELINE!$V23-DATA_PIPELINE!$W23 -> 500 | Y23: =IF(DATA_PIPELINE!$X23=0,"Paid",IF(DATA_PIPELINE!$W23=0,"Unpaid","Partly Paid")) -> Unpaid
A24: 19 | B24: KADOMA PRISSONS | C24: KADOMA PRISON FARM | D24: DANMORE MUDAVANHU | E24: 32-065804-J-26 | F24: 774383463 | G24: KADOMA | H24: MASHWEST | J24: EXISTING | K24: 0 | L24: 0 | M24: 20 | N24: 40 | O24: 2555.28 | P24: 0 | Q24: 0 | R24: 2555.28 | S24: - | T24: 40 | U24: Category A | V24: 500 | W24: =DATA_PIPELINE!$K24 -> 0 | X24: =DATA_PIPELINE!$V24-DATA_PIPELINE!$W24 -> 500 | Y24: =IF(DATA_PIPELINE!$X24=0,"Paid",IF(DATA_PIPELINE!$W24=0,"Unpaid","Partly Paid")) -> Unpaid
A25: 20 | B25: MARECHA MICHIEL | C25: NK | D25: DANMORE MUDAVANHU | E25: 22-026458-Z-04 | F25: 760572096 | G25: CHEGUTU | H25: MASHWEST | J25: EXISTING | K25: 0 | L25: 0 | M25: 20 | N25: 20 | O25: 2389.4 | P25: 0 | Q25: 0 | R25: 2389.4 | S25: - | T25: 20 | U25: Category A | V25: 500 | W25: =DATA_PIPELINE!$K25 -> 0 | X25: =DATA_PIPELINE!$V25-DATA_PIPELINE!$W25 -> 500 | Y25: =IF(DATA_PIPELINE!$X25=0,"Paid",IF(DATA_PIPELINE!$W25=0,"Unpaid","Partly Paid")) -> Unpaid
A26: 21 | B26: CHIMBETU COLLEN | C26: NK | D26: DANMORE MUDAVANHU | E26: 63-1138140-R-63 | G26: CHEGUTU | H26: MASHWEST | J26: EXISTING | K26: 0 | L26: 0 | M26: 25 | N26: 30 | O26: 5447.2 | P26: 0 | Q26: 0 | R26: 5447.2 | S26: - | T26: 30 | U26: Category A | V26: 500 | W26: =DATA_PIPELINE!$K26 -> 0 | X26: =DATA_PIPELINE!$V26-DATA_PIPELINE!$W26 -> 500 | Y26: =IF(DATA_PIPELINE!$X26=0,"Paid",IF(DATA_PIPELINE!$W26=0,"Unpaid","Partly Paid")) -> Unpaid
A27: 22 | B27: MASHOKO TINASHE | C27: PLOT 15 TORDAT FARM CHEGUTU | D27: DANMORE MUDAVANHU | E27: 32-191454-K-32 | F27: 777241382 | G27: CHEGUTU | H27: MASHWEST | J27: EXISTING | K27: 0 | L27: 0 | M27: 6 | N27: 20 | O27: 891.92 | P27: 0 | Q27: 0 | R27: 891.92 | S27: - | T27: 20 | U27: Category A | V27: 500 | W27: =DATA_PIPELINE!$K27 -> 0 | X27: =DATA_PIPELINE!$V27-DATA_PIPELINE!$W27 -> 500 | Y27: =IF(DATA_PIPELINE!$X27=0,"Paid",IF(DATA_PIPELINE!$W27=0,"Unpaid","Partly Paid")) -> Unpaid
A28: 23 | B28: IMPALAVALE FARM CHATIKOBO | C28: IMPALAVALE FARM | D28: DANMORE MUDAVANHU | E28: 63-900087-Q-26 | F28: 779729830 | G28: MHONDORO NGEZI | H28: MASHWEST | J28: EXISTING | K28: 0 | L28: 0 | M28: 80 | N28: 100 | O28: 11668.01 | P28: 0 | Q28: 0 | R28: 11668.01 | S28: - | T28: 100 | U28: Category A | V28: 500 | W28: =DATA_PIPELINE!$K28 -> 0 | X28: =DATA_PIPELINE!$V28-DATA_PIPELINE!$W28 -> 500 | Y28: =IF(DATA_PIPELINE!$X28=0,"Paid",IF(DATA_PIPELINE!$W28=0,"Unpaid","Partly Paid")) -> Unpaid
A29: 24 | B29: MAMINA IRRIGATION SCHEME | C29: MAMINA IRRIGATION SCHEME | D29: DANMORE MUDAVANHU | E29: 63-446623-V-24 | F29: 772354114 | G29: MHONDORO NGEZI | H29: MASHWEST | J29: EXISTING | K29: 0 | L29: 0 | M29: 145 | N29: 200 | O29: 17554.89 | P29: 0 | Q29: 0 | R29: 17554.89 | S29: - | T29: 200 | U29: Category B | V29: 1000 | W29: =DATA_PIPELINE!$K29 -> 0 | X29: =DATA_PIPELINE!$V29-DATA_PIPELINE!$W29 -> 1000 | Y29: =IF(DATA_PIPELINE!$X29=0,"Paid",IF(DATA_PIPELINE!$W29=0,"Unpaid","Partly Paid")) -> Unpaid
A30: 25 | B30: GAKA RODRICK | C30: 46 COBERN ESTATES CHEGUTU | D30: DANMORE MUDAVANHU | E30: 29-178061-H-12 | F30: 772251262 | G30: CHEGUTU | H30: MASHWEST | J30: EXISTING | K30: 0 | L30: 0 | M30: 50 | N30: 50 | O30: 8329.52 | P30: 0 | Q30: 0 | R30: 8329.52 | S30: - | T30: 50 | U30: Category A | V30: 500 | W30: =DATA_PIPELINE!$K30 -> 0 | X30: =DATA_PIPELINE!$V30-DATA_PIPELINE!$W30 -> 500 | Y30: =IF(DATA_PIPELINE!$X30=0,"Paid",IF(DATA_PIPELINE!$W30=0,"Unpaid","Partly Paid")) -> Unpaid
A31: 26 | B31: ZUNGUNDE BETTY | C31: KENT ESTATE | D31: BETTY ZUNGUNDE | E31: 32-122405-G-38 | F31: 773868322 | G31: CHEGUTU | H31: MASHWEST | I31: 14 | J31: EXISTING | K31: 50 | L31: 0 | M31: 0 | N31: 80 | O31: 18089.72 | P31: 3.04 | Q31: 1108.84 | R31: 16980.88 | S31: 6.13 | T31: 80 | U31: Category A | V31: 500 | W31: =DATA_PIPELINE!$K31 -> 50 | X31: =DATA_PIPELINE!$V31-DATA_PIPELINE!$W31 -> 450 | Y31: =IF(DATA_PIPELINE!$X31=0,"Paid",IF(DATA_PIPELINE!$W31=0,"Unpaid","Partly Paid")) -> Partly Paid
A32: 27 | B32: MARUFU DEPHINE | C32: KILWORTH FARM | D32: BETTY ZUNGUNDE | E32: 63-1541739-L-05 | F32: 774518500 | G32: CHEGUTU | H32: MASHWEST | J32: EXISTING | K32: 0 | L32: 0 | M32: 0 | N32: 40 | O32: 9236.5 | P32: 0 | Q32: 0 | R32: 9236.5 | S32: - | T32: 40 | U32: Category A | V32: 500 | W32: =DATA_PIPELINE!$K32 -> 0 | X32: =DATA_PIPELINE!$V32-DATA_PIPELINE!$W32 -> 500 | Y32: =IF(DATA_PIPELINE!$X32=0,"Paid",IF(DATA_PIPELINE!$W32=0,"Unpaid","Partly Paid")) -> Unpaid
A33: 28 | B33: MUTSVANGWA MONICA | C33: NK | D33: BETTY ZUNGUNDE | E33: 63-438218-B-70* | G33: CHEGUTU | H33: MASHWEST | J33: EXISTING | K33: 0 | L33: 0 | M33: 0 | N33: 40 | O33: 546 | P33: 0 | Q33: 0 | R33: 546 | S33: - | T33: 40 | U33: Category A | V33: 500 | W33: =DATA_PIPELINE!$K33 -> 0 | X33: =DATA_PIPELINE!$V33-DATA_PIPELINE!$W33 -> 500 | Y33: =IF(DATA_PIPELINE!$X33=0,"Paid",IF(DATA_PIPELINE!$W33=0,"Unpaid","Partly Paid")) -> Unpaid
A34: 29 | B34: NYENYAI ANGELINE | C34: NK | D34: BETTY ZUNGUNDE | E34: 70-459721-B-70* | G34: CHEGUTU | H34: MASHWEST | J34: EXISTING | K34: 0 | L34: 0 | M34: 0 | N34: 60 | O34: 11580.73 | P34: 0 | Q34: 0 | R34: 11580.73 | S34: - | T34: 60 | U34: Category A | V34: 500 | W34: =DATA_PIPELINE!$K34 -> 0 | X34: =DATA_PIPELINE!$V34-DATA_PIPELINE!$W34 -> 500 | Y34: =IF(DATA_PIPELINE!$X34=0,"Paid",IF(DATA_PIPELINE!$W34=0,"Unpaid","Partly Paid")) -> Unpaid
A35: 30 | B35: MUTSVANGWA MONICA | C35: MONCHRIS FARM | D35: BETTY ZUNGUNDE | E35: 63-905294-A-32 | F35: 772572470 | G35: CHEGUTU | H35: MASHWEST | J35: EXISTING | K35: 0 | L35: 0 | M35: 0 | N35: 0 | O35: 844.01 | P35: 0 | Q35: 0 | R35: 844.01 | S35: - | T35: 0 | U35: Category A | V35: 500 | W35: =DATA_PIPELINE!$K35 -> 0 | X35: =DATA_PIPELINE!$V35-DATA_PIPELINE!$W35 -> 500 | Y35: =IF(DATA_PIPELINE!$X35=0,"Paid",IF(DATA_PIPELINE!$W35=0,"Unpaid","Partly Paid")) -> Unpaid
A36: 31 | B36: MUTIWASEKWA ITAI | C36: PLOT 3 HUNYANI ETSTATE NORTON | D36: BETTY ZUNGUNDE | E36: 32088464-P-44 | F36: 715111991 | G36: CHEGUTU | H36: MASHWEST | J36: EXISTING | K36: 0 | L36: 0 | M36: 0 | N36: 40 | O36: 11005.69 | P36: 0 | Q36: 0 | R36: 11005.69 | S36: - | T36: 40 | U36: Category A | V36: 500 | W36: =DATA_PIPELINE!$K36 -> 0 | X36: =DATA_PIPELINE!$V36-DATA_PIPELINE!$W36 -> 500 | Y36: =IF(DATA_PIPELINE!$X36=0,"Paid",IF(DATA_PIPELINE!$W36=0,"Unpaid","Partly Paid")) -> Unpaid
A37: 32 | B37: MUJURU D | C37: SIVUNDAZI FAM | D37: BETTY ZUNGUNDE | E37: 63-948959-M-80 | F37: 718840612 | G37: CHEGUTU | H37: MASHWEST | I37: 26 | J37: EXISTING | K37: 0 | L37: 0 | M37: 0 | N37: 180 | O37: 27779.25 | P37: 0 | Q37: 0 | R37: 27779.25 | S37: - | T37: 180 | U37: Category A | V37: 500 | W37: =DATA_PIPELINE!$K37 -> 0 | X37: =DATA_PIPELINE!$V37-DATA_PIPELINE!$W37 -> 500 | Y37: =IF(DATA_PIPELINE!$X37=0,"Paid",IF(DATA_PIPELINE!$W37=0,"Unpaid","Partly Paid")) -> Unpaid
A38: 33 | B38: MANYAWU E.T | C38: DAIZY FARM | D38: BETTY ZUNGUNDE | E38: 63-817650-K-50 | F38: 773447211 | G38: CHEGUTU | H38: MASHWEST | I38: 15 | J38: EXISTING | K38: 0 | L38: 0 | M38: 0 | N38: 25 | O38: 4565.02 | P38: 0 | Q38: 0 | R38: 4565.02 | S38: - | T38: 25 | U38: Category A | V38: 500 | W38: =DATA_PIPELINE!$K38 -> 0 | X38: =DATA_PIPELINE!$V38-DATA_PIPELINE!$W38 -> 500 | Y38: =IF(DATA_PIPELINE!$X38=0,"Paid",IF(DATA_PIPELINE!$W38=0,"Unpaid","Partly Paid")) -> Unpaid
A39: 34 | B39: MUSWEHAURARI CHIPO | C39: BURNBANK FARM | D39: BETTY ZUNGUNDE | E39: 42-144968-X-42 | F39: 772816696 | G39: CHEGUTU | H39: MASHWEST | I39: 28 | J39: EXISTING | K39: 0 | L39: 0 | M39: 10 | N39: 50 | O39: 8300.95 | P39: 4.05 | Q39: 1477.24 | R39: 6823.71 | S39: 17.8 | T39: 60 | U39: Category A | V39: 500 | W39: =DATA_PIPELINE!$K39 -> 0 | X39: =DATA_PIPELINE!$V39-DATA_PIPELINE!$W39 -> 500 | Y39: =IF(DATA_PIPELINE!$X39=0,"Paid",IF(DATA_PIPELINE!$W39=0,"Unpaid","Partly Paid")) -> Unpaid
A40: 35 | B40: TAKAVADA KELVIN | C40: DAIZY FARM | D40: BETTY ZUNGUNDE | E40: 86-053962-P-22 | F40: 773084706 | G40: CHEGUTU | H40: MASHWEST | I40: 15 | J40: EXISTING | K40: 0 | L40: 0 | M40: 0 | N40: 40 | O40: 8629.59 | P40: 0 | Q40: 0 | R40: 8629.59 | S40: - | T40: 40 | U40: Category A | V40: 500 | W40: =DATA_PIPELINE!$K40 -> 0 | X40: =DATA_PIPELINE!$V40-DATA_PIPELINE!$W40 -> 500 | Y40: =IF(DATA_PIPELINE!$X40=0,"Paid",IF(DATA_PIPELINE!$W40=0,"Unpaid","Partly Paid")) -> Unpaid
A41: 36 | B41: MARTINDALE FARM LCBL | C41: MARTINDALE FARM | D41: BETTY ZUNGUNDE | E41: 63-709780-K-70 | F41: 775986483 | G41: CHEGUTU | H41: MASHWEST | J41: EXISTING | K41: 0 | L41: 0 | M41: 0 | N41: 20 | O41: 2447.07 | P41: 0 | Q41: 0 | R41: 2447.07 | S41: - | T41: 20 | U41: Category A | V41: 500 | W41: =DATA_PIPELINE!$K41 -> 0 | X41: =DATA_PIPELINE!$V41-DATA_PIPELINE!$W41 -> 500 | Y41: =IF(DATA_PIPELINE!$X41=0,"Paid",IF(DATA_PIPELINE!$W41=0,"Unpaid","Partly Paid")) -> Unpaid
A42: 37 | B42: CHAERUKA ANOLD | C42: PUMULA FARM MAGUNJE | D42: TAKUNDA NHEMA | E42: 75-157910-E-75 | F42: 772399882 | G42: HURUNGWE | H42: MASHWEST | J42: EXISTING | K42: 0 | L42: 0 | M42: 0 | N42: 600 | O42: 76796.41 | P42: 0 | Q42: 0 | R42: 76796.41 | S42: - | T42: 600 | U42: Category B | V42: 1000 | W42: =DATA_PIPELINE!$K42 -> 0 | X42: =DATA_PIPELINE!$V42-DATA_PIPELINE!$W42 -> 1000 | Y42: =IF(DATA_PIPELINE!$X42=0,"Paid",IF(DATA_PIPELINE!$W42=0,"Unpaid","Partly Paid")) -> Unpaid
A43: 38 | B43: KAROI PRISONS | C43: ZPCS FARM | D43: TAKUNDA NHEMA | E43: 71-051668-Y-71 | F43: 773944969 | G43: HURUNGWE | H43: MASHWEST | J43: EXISTING | K43: 0 | L43: 0 | M43: 0 | N43: 60 | O43: 15098.87 | P43: 0 | Q43: 0 | R43: 15098.87 | S43: - | T43: 60 | U43: Category A | V43: 500 | W43: =DATA_PIPELINE!$K43 -> 0 | X43: =DATA_PIPELINE!$V43-DATA_PIPELINE!$W43 -> 500 | Y43: =IF(DATA_PIPELINE!$X43=0,"Paid",IF(DATA_PIPELINE!$W43=0,"Unpaid","Partly Paid")) -> Unpaid
A44: 39 | B44: CHIREMBA S TAFADZWA | C44: SENCEGAL , TENGWE | D44: TAKUNDA NHEMA | E44: 63-1563144-C-07 | F44: 773965849 | G44: HURUNGWE | H44: MASHWEST | J44: EXISTING | K44: 0 | L44: 0 | M44: 0 | N44: 200 | O44: 31207.46 | P44: 0 | Q44: 0 | R44: 31207.46 | S44: - | T44: 200 | U44: Category B | V44: 1000 | W44: =DATA_PIPELINE!$K44 -> 0 | X44: =DATA_PIPELINE!$V44-DATA_PIPELINE!$W44 -> 1000 | Y44: =IF(DATA_PIPELINE!$X44=0,"Paid",IF(DATA_PIPELINE!$W44=0,"Unpaid","Partly Paid")) -> Unpaid
A45: 40 | B45: BURANDA MOSES | C45: COMSTON PLOT 5 KAROI | D45: TAKUNDA NHEMA | E45: 18045704B18 | G45: HURUNGWE | H45: MASHWEST | J45: EXISTING | K45: 0 | L45: 0 | M45: 0 | N45: 40 | O45: 4811.71 | P45: 0 | Q45: 0 | R45: 4811.71 | S45: - | T45: 40 | U45: Category A | V45: 500 | W45: =DATA_PIPELINE!$K45 -> 0 | X45: =DATA_PIPELINE!$V45-DATA_PIPELINE!$W45 -> 500 | Y45: =IF(DATA_PIPELINE!$X45=0,"Paid",IF(DATA_PIPELINE!$W45=0,"Unpaid","Partly Paid")) -> Unpaid
A46: 41 | B46: MWANDITANI PATRICIA | C46: Cornstone Farm Subdivision 5 | D46: TAKUNDA NHEMA | E46: 38140258B66 | G46: HURUNGWE | H46: MASHWEST | J46: EXISTING | K46: 0 | L46: 0 | M46: 0 | N46: 20 | O46: 4797.08 | P46: 0 | Q46: 0 | R46: 4797.08 | S46: - | T46: 20 | U46: Category A | V46: 500 | W46: =DATA_PIPELINE!$K46 -> 0 | X46: =DATA_PIPELINE!$V46-DATA_PIPELINE!$W46 -> 500 | Y46: =IF(DATA_PIPELINE!$X46=0,"Paid",IF(DATA_PIPELINE!$W46=0,"Unpaid","Partly Paid")) -> Unpaid
A47: 42 | B47: IMBAYAGO NYARADZO | C47: Naba Estate(A2) Plot 2 | D47: TAKUNDA NHEMA | E47: 24043532R12 | G47: HURUNGWE | H47: MASHWEST | I47: 5 | J47: EXISTING | K47: 0 | L47: 0 | M47: 0 | N47: 40 | O47: 12435.56 | P47: 0 | Q47: 0 | R47: 12435.56 | S47: - | T47: 40 | U47: Category A | V47: 500 | W47: =DATA_PIPELINE!$K47 -> 0 | X47: =DATA_PIPELINE!$V47-DATA_PIPELINE!$W47 -> 500 | Y47: =IF(DATA_PIPELINE!$X47=0,"Paid",IF(DATA_PIPELINE!$W47=0,"Unpaid","Partly Paid")) -> Unpaid
A48: 43 | B48: MILONDE ADAM | C48: Cornstone Farm Plot 7 Karoi | D48: TAKUNDA NHEMA | E48: 38-095779-E-38 | F48: 777051013 | G48: HURUNGWE | H48: MASHWEST | J48: EXISTING | K48: 0 | L48: 0 | M48: 0 | N48: 35 | O48: 7355.58 | P48: 0 | Q48: 0 | R48: 7355.58 | S48: - | T48: 35 | U48: Category A | V48: 500 | W48: =DATA_PIPELINE!$K48 -> 0 | X48: =DATA_PIPELINE!$V48-DATA_PIPELINE!$W48 -> 500 | Y48: =IF(DATA_PIPELINE!$X48=0,"Paid",IF(DATA_PIPELINE!$W48=0,"Unpaid","Partly Paid")) -> Unpaid
A49: 44 | B49: MASHORE LENON | C49: MYLERN FARM , Karoi | D49: TAKUNDA NHEMA | E49: 38-140239-F-70 | F49: 773275852 | G49: HURUNGWE | H49: MASHWEST | J49: EXISTING | K49: 0 | L49: 0 | M49: 0 | N49: 40 | O49: 10904.39 | P49: 0 | Q49: 0 | R49: 10904.39 | S49: - | T49: 40 | U49: Category A | V49: 500 | W49: =DATA_PIPELINE!$K49 -> 0 | X49: =DATA_PIPELINE!$V49-DATA_PIPELINE!$W49 -> 500 | Y49: =IF(DATA_PIPELINE!$X49=0,"Paid",IF(DATA_PIPELINE!$W49=0,"Unpaid","Partly Paid")) -> Unpaid
A50: 45 | B50: MUZEZEWA SHEPARD | C50: MYLERN FARM , Karoi | D50: TAKUNDA NHEMA | E50: 38-059005-H-38 | F50: 778141198 | G50: HURUNGWE | H50: MASHWEST | J50: EXISTING | K50: 0 | L50: 0 | M50: 0 | N50: 50 | O50: 14074.8 | P50: 0 | Q50: 0 | R50: 14074.8 | S50: - | T50: 50 | U50: Category A | V50: 500 | W50: =DATA_PIPELINE!$K50 -> 0 | X50: =DATA_PIPELINE!$V50-DATA_PIPELINE!$W50 -> 500 | Y50: =IF(DATA_PIPELINE!$X50=0,"Paid",IF(DATA_PIPELINE!$W50=0,"Unpaid","Partly Paid")) -> Unpaid
A51: 46 | B51: MARIMO DENNY TAPIWA | C51: MYLERN FARM , Karoi | D51: TAKUNDA NHEMA | E51: 38-175475-F-38 | F51: 782719229 | G51: HURUNGWE | H51: MASHWEST | J51: EXISTING | K51: 0 | L51: 0 | M51: 0 | N51: 50 | O51: 16983.94 | P51: 0 | Q51: 0 | R51: 16983.94 | S51: - | T51: 50 | U51: Category A | V51: 500 | W51: =DATA_PIPELINE!$K51 -> 0 | X51: =DATA_PIPELINE!$V51-DATA_PIPELINE!$W51 -> 500 | Y51: =IF(DATA_PIPELINE!$X51=0,"Paid",IF(DATA_PIPELINE!$W51=0,"Unpaid","Partly Paid")) -> Unpaid
A52: 47 | B52: MASENDA TAPIWA | C52: MAKOROKOTO | D52: TAKUNDA NHEMA | E52: 63-2080208-D-80 | F52: 716956544 | G52: HURUNGWE | H52: MASHWEST | J52: EXISTING | K52: 0 | L52: 0 | M52: 0 | N52: 60 | O52: 14815.12 | P52: 0 | Q52: 0 | R52: 14815.12 | S52: - | T52: 60 | U52: Category A | V52: 500 | W52: =DATA_PIPELINE!$K52 -> 0 | X52: =DATA_PIPELINE!$V52-DATA_PIPELINE!$W52 -> 500 | Y52: =IF(DATA_PIPELINE!$X52=0,"Paid",IF(DATA_PIPELINE!$W52=0,"Unpaid","Partly Paid")) -> Unpaid
A53: 48 | B53: NHEMA TAKUNDA | C53: NYAMANDA FARM, KAROI | D53: TAKUNDA NHEMA | E53: 29-198307-P-66 | F53: 772399882 | G53: HURUNGWE | H53: MASHWEST | I53: 50 | J53: EXISTING | K53: 1000 | L53: 0 | M53: 0 | N53: 700 | O53: 103060 | P53: 0 | Q53: 0 | R53: 103060 | S53: - | T53: 700 | U53: Category B | V53: 1000 | W53: =DATA_PIPELINE!$K53 -> 1000 | X53: =DATA_PIPELINE!$V53-DATA_PIPELINE!$W53 -> 0 | Y53: =IF(DATA_PIPELINE!$X53=0,"Paid",IF(DATA_PIPELINE!$W53=0,"Unpaid","Partly Paid")) -> Paid
A54: 49 | B54: MUDZVITI TECLA | C54: RAUUNMADE | D54: BRIAN CHIDAVAENZI | E54: 83-116229-B-83 | F54: 772488873 | G54: HURUNGWE | H54: MASHWEST | J54: EXISTING | K54: 0 | L54: 0 | M54: 0 | N54: 30 | O54: 8096.2 | P54: 0 | Q54: 0 | R54: 8096.2 | S54: - | T54: 30 | U54: Category A | V54: 500 | W54: =DATA_PIPELINE!$K54 -> 0 | X54: =DATA_PIPELINE!$V54-DATA_PIPELINE!$W54 -> 500 | Y54: =IF(DATA_PIPELINE!$X54=0,"Paid",IF(DATA_PIPELINE!$W54=0,"Unpaid","Partly Paid")) -> Unpaid
A55: 50 | B55: GOMBE TENDAI | C55: PELELE FARM PLOT 11 | D55: BRIAN CHIDAVAENZI | E55: 38-218039-W-70 | F55: 771775698 | G55: HURUNGWE | H55: MASHWEST | J55: EXISTING | K55: 0 | L55: 0 | M55: 0 | N55: 20 | O55: 7383.67 | P55: 0 | Q55: 0 | R55: 7383.67 | S55: - | T55: 20 | U55: Category A | V55: 500 | W55: =DATA_PIPELINE!$K55 -> 0 | X55: =DATA_PIPELINE!$V55-DATA_PIPELINE!$W55 -> 500 | Y55: =IF(DATA_PIPELINE!$X55=0,"Paid",IF(DATA_PIPELINE!$W55=0,"Unpaid","Partly Paid")) -> Unpaid
A56: 51 | B56: MUJENGE TONGAI | C56: CHOYAMBA | D56: BRIAN CHIDAVAENZI | E56: 71-072373-D-38 | F56: 773651499 | G56: HURUNGWE | H56: MASHWEST | J56: EXISTING | K56: 0 | L56: 0 | M56: 0 | N56: 50 | O56: 4850.23 | P56: 0 | Q56: 0 | R56: 4850.23 | S56: - | T56: 50 | U56: Category A | V56: 500 | W56: =DATA_PIPELINE!$K56 -> 0 | X56: =DATA_PIPELINE!$V56-DATA_PIPELINE!$W56 -> 500 | Y56: =IF(DATA_PIPELINE!$X56=0,"Paid",IF(DATA_PIPELINE!$W56=0,"Unpaid","Partly Paid")) -> Unpaid
A57: 52 | B57: GATSI MARIAN | C57: MARNI MULICHI | D57: BRIAN CHIDAVAENZI | E57: 66-025163-F-12 | F57: 779238902 | G57: HURUNGWE | H57: MASHWEST | J57: EXISTING | K57: 0 | L57: 0 | M57: 0 | N57: 10 | O57: 2806.8 | P57: 0 | Q57: 0 | R57: 2806.8 | S57: - | T57: 10 | U57: Category A | V57: 500 | W57: =DATA_PIPELINE!$K57 -> 0 | X57: =DATA_PIPELINE!$V57-DATA_PIPELINE!$W57 -> 500 | Y57: =IF(DATA_PIPELINE!$X57=0,"Paid",IF(DATA_PIPELINE!$W57=0,"Unpaid","Partly Paid")) -> Unpaid
A58: 53 | B58: NJOVANA TANAKA WONDER | C58: PLOT KIPPOCK FARM KAROI | D58: BRIAN CHIDAVAENZI | E58: 38-251446-H-66 | F58: 773534002 | G58: HURUNGWE | H58: MASHWEST | J58: EXISTING | K58: 0 | L58: 0 | M58: 0 | N58: 20 | O58: 3462 | P58: 0 | Q58: 0 | R58: 3462 | S58: - | T58: 20 | U58: Category A | V58: 500 | W58: =DATA_PIPELINE!$K58 -> 0 | X58: =DATA_PIPELINE!$V58-DATA_PIPELINE!$W58 -> 500 | Y58: =IF(DATA_PIPELINE!$X58=0,"Paid",IF(DATA_PIPELINE!$W58=0,"Unpaid","Partly Paid")) -> Unpaid
A59: 54 | B59: ISAH RABEEAH M | C59: NEBO FARM | D59: BRIAN CHIDAVAENZI | E59: 63-3216103-X-70 | F59: 717955922 | G59: HURUNGWE | H59: MASHWEST | J59: EXISTING | K59: 0 | L59: 0 | M59: 0 | N59: 20 | O59: 7611.71 | P59: 0 | Q59: 0 | R59: 7611.71 | S59: - | T59: 20 | U59: Category A | V59: 500 | W59: =DATA_PIPELINE!$K59 -> 0 | X59: =DATA_PIPELINE!$V59-DATA_PIPELINE!$W59 -> 500 | Y59: =IF(DATA_PIPELINE!$X59=0,"Paid",IF(DATA_PIPELINE!$W59=0,"Unpaid","Partly Paid")) -> Unpaid
A60: 55 | B60: MUSIIWA ALEXIS | C60: PLOT 1 RIDGES EASTER PARADE | D60: BRIAN CHIDAVAENZI | E60: 02-2000881-A-05 | F60: 775526270 | G60: HURUNGWE | H60: MASHWEST | J60: EXISTING | K60: 0 | L60: 0 | M60: 0 | N60: 20 | O60: 5199.4 | P60: 0 | Q60: 0 | R60: 5199.4 | S60: - | T60: 20 | U60: Category A | V60: 500 | W60: =DATA_PIPELINE!$K60 -> 0 | X60: =DATA_PIPELINE!$V60-DATA_PIPELINE!$W60 -> 500 | Y60: =IF(DATA_PIPELINE!$X60=0,"Paid",IF(DATA_PIPELINE!$W60=0,"Unpaid","Partly Paid")) -> Unpaid
A61: 56 | B61: HURUNGWE FARMERS ASSOCIA | C61: GOOD HOPE PLOT 27 | D61: BRIAN CHIDAVAENZI | E61: 38-115839-J-38 | F61: 775830916 | G61: HURUNGWE | H61: MASHWEST | I61: 18 | J61: EXISTING | K61: 0 | L61: 0 | M61: 0 | N61: 200 | O61: 30216.77 | P61: 0 | Q61: 0 | R61: 30216.77 | S61: - | T61: 200 | U61: Category B | V61: 1000 | W61: =DATA_PIPELINE!$K61 -> 0 | X61: =DATA_PIPELINE!$V61-DATA_PIPELINE!$W61 -> 1000 | Y61: =IF(DATA_PIPELINE!$X61=0,"Paid",IF(DATA_PIPELINE!$W61=0,"Unpaid","Partly Paid")) -> Unpaid
A62: 57 | B62: MLISWA THEMBA | C62: SPRING FARM | D62: BRIAN CHIDAVAENZI | E62: 63-821381-Q-66 | F62: 786904075 | G62: HURUNGWE | H62: MASHWEST | J62: EXISTING | K62: 0 | L62: 0 | M62: 0 | N62: 200 | O62: 31500.52 | P62: 19.7 | Q62: 7185.58 | R62: 24314.94 | S62: 22.81 | T62: 200 | U62: Category B | V62: 1000 | W62: =DATA_PIPELINE!$K62 -> 0 | X62: =DATA_PIPELINE!$V62-DATA_PIPELINE!$W62 -> 1000 | Y62: =IF(DATA_PIPELINE!$X62=0,"Paid",IF(DATA_PIPELINE!$W62=0,"Unpaid","Partly Paid")) -> Unpaid
A63: 58 | B63: ZENDANEMAKO JOSLIN MAUYA | C63: OMEGA FARM | D63: BRIAN CHIDAVAENZI | E63: 38-019983-S-38 | G63: HURUNGWE | H63: MASHWEST | J63: EXISTING | K63: 0 | L63: 0 | M63: 0 | N63: 150 | O63: 10122.84 | P63: 0 | Q63: 0 | R63: 10122.84 | S63: - | T63: 150 | U63: Category A | V63: 500 | W63: =DATA_PIPELINE!$K63 -> 0 | X63: =DATA_PIPELINE!$V63-DATA_PIPELINE!$W63 -> 500 | Y63: =IF(DATA_PIPELINE!$X63=0,"Paid",IF(DATA_PIPELINE!$W63=0,"Unpaid","Partly Paid")) -> Unpaid
A64: 59 | B64: CHIDAVAENZI BRIAN | C64: OMEGA FARM | D64: BRIAN CHIDAVAENZI | E64: 63-1032402 J 38 | F64: 774346142 | G64: HURUNGWE | H64: MASHWEST | J64: NEW | K64: 0 | L64: 0 | M64: 0 | N64: 200 | O64: 0 | P64: 0 | Q64: 0 | R64: 0 | T64: 200 | U64: Category B | V64: 1000 | W64: =DATA_PIPELINE!$K64 -> 0 | X64: =DATA_PIPELINE!$V64-DATA_PIPELINE!$W64 -> 1000 | Y64: =IF(DATA_PIPELINE!$X64=0,"Paid",IF(DATA_PIPELINE!$W64=0,"Unpaid","Partly Paid")) -> Unpaid
A65: 60 | B65: CHIDAVAENZI TAPIWA | C65: OMEGA FARM | D65: BRIAN CHIDAVAENZI | E65: 59-144446 Q 38 | G65: HURUNGWE | H65: MASHWEST | J65: NEW | K65: 0 | L65: 0 | M65: 0 | N65: 20 | O65: 0 | P65: 0 | Q65: 0 | R65: 0 | T65: 20 | U65: Category A | V65: 500 | W65: =DATA_PIPELINE!$K65 -> 0 | X65: =DATA_PIPELINE!$V65-DATA_PIPELINE!$W65 -> 500 | Y65: =IF(DATA_PIPELINE!$X65=0,"Paid",IF(DATA_PIPELINE!$W65=0,"Unpaid","Partly Paid")) -> Unpaid
A66: 61 | B66: KUYERUKANA CHIPO | C66: OMEGA FARM | D66: BRIAN CHIDAVAENZI | E66: 24-152796 N 38 | G66: HURUNGWE | H66: MASHWEST | J66: NEW | K66: 0 | L66: 0 | M66: 0 | N66: 20 | O66: 0 | P66: 0 | Q66: 0 | R66: 0 | T66: 20 | U66: Category A | V66: 500 | W66: =DATA_PIPELINE!$K66 -> 0 | X66: =DATA_PIPELINE!$V66-DATA_PIPELINE!$W66 -> 500 | Y66: =IF(DATA_PIPELINE!$X66=0,"Paid",IF(DATA_PIPELINE!$W66=0,"Unpaid","Partly Paid")) -> Unpaid
A67: 62 | B67: CHAWATAMA JONAH | C67: NK | D67: BRIAN CHIDAVAENZI | E67: 43-042960-A-43 | G67: HURUNGWE | H67: MASHWEST | J67: EXISTING | K67: 0 | L67: 0 | M67: 0 | N67: 50 | O67: 3840.08 | P67: 0 | Q67: 0 | R67: 3840.08 | S67: - | T67: 50 | U67: Category A | V67: 500 | W67: =DATA_PIPELINE!$K67 -> 0 | X67: =DATA_PIPELINE!$V67-DATA_PIPELINE!$W67 -> 500 | Y67: =IF(DATA_PIPELINE!$X67=0,"Paid",IF(DATA_PIPELINE!$W67=0,"Unpaid","Partly Paid")) -> Unpaid
A68: 63 | B68: MESO COLLEN | C68: NK | D68: COMMENT TONDERAYI MUTARA | E68: 26-17505252-S-26 | G68: HURUNGWE | H68: MASHWEST | J68: EXISTING | K68: 0 | L68: 0 | M68: 0 | N68: 20 | O68: 273 | P68: 0 | Q68: 0 | R68: 273 | S68: - | T68: 20 | U68: Category A | V68: 500 | W68: =DATA_PIPELINE!$K68 -> 0 | X68: =DATA_PIPELINE!$V68-DATA_PIPELINE!$W68 -> 500 | Y68: =IF(DATA_PIPELINE!$X68=0,"Paid",IF(DATA_PIPELINE!$W68=0,"Unpaid","Partly Paid")) -> Unpaid
A69: 64 | B69: MGUGU VELAPI | C69: NK | D69: BRIAN CHIDAVAENZI | E69: 63-531987-G-38 | G69: HURUNGWE | H69: MASHWEST | J69: EXISTING | K69: 0 | L69: 0 | M69: 0 | N69: 20 | O69: 2745.4 | P69: 0 | Q69: 0 | R69: 2745.4 | S69: - | T69: 20 | U69: Category A | V69: 500 | W69: =DATA_PIPELINE!$K69 -> 0 | X69: =DATA_PIPELINE!$V69-DATA_PIPELINE!$W69 -> 500 | Y69: =IF(DATA_PIPELINE!$X69=0,"Paid",IF(DATA_PIPELINE!$W69=0,"Unpaid","Partly Paid")) -> Unpaid
A70: 65 | B70: BIKA FARAYI WILFRED | C70: RUDOLPHIA | D70: PHIBEON MUTIBURA | E70: 63-701839-D-25 | F70: 772667052 | G70: GOROMONZI | H70: MASHCENTRAL | J70: EXISTING | K70: 0 | L70: 0 | M70: 0 | N70: 70 | O70: 7265.24 | P70: 0 | Q70: 0 | R70: 7265.24 | S70: - | T70: 70 | U70: Category A | V70: 500 | W70: =DATA_PIPELINE!$K70 -> 0 | X70: =DATA_PIPELINE!$V70-DATA_PIPELINE!$W70 -> 500 | Y70: =IF(DATA_PIPELINE!$X70=0,"Paid",IF(DATA_PIPELINE!$W70=0,"Unpaid","Partly Paid")) -> Unpaid
A71: 66 | B71: CHIKOMO UNICO | C71: SPRINGS FARM | D71: PHIBEON MUTIBURA | E71: 63-1438243-Q-75 | F71: 779466560 | G71: GOROMONZI | H71: MASHCENTRAL | J71: EXISTING | K71: 0 | L71: 0 | M71: 0 | N71: 100 | O71: 8947.96 | P71: 0 | Q71: 0 | R71: 8947.96 | S71: - | T71: 100 | U71: Category A | V71: 500 | W71: =DATA_PIPELINE!$K71 -> 0 | X71: =DATA_PIPELINE!$V71-DATA_PIPELINE!$W71 -> 500 | Y71: =IF(DATA_PIPELINE!$X71=0,"Paid",IF(DATA_PIPELINE!$W71=0,"Unpaid","Partly Paid")) -> Unpaid
A72: 67 | B72: KANETA NACY | C72: DOUNE FARM, Marondera | D72: PHIBEON MUTIBURA | E72: 58-057835-R-44 | F72: 772357624 | G72: MARONDERA | H72: MASHCENTRAL | J72: EXISTING | K72: 0 | L72: 0 | M72: 0 | N72: 30 | O72: 2522.03 | P72: 0 | Q72: 0 | R72: 2522.03 | S72: - | T72: 30 | U72: Category A | V72: 500 | W72: =DATA_PIPELINE!$K72 -> 0 | X72: =DATA_PIPELINE!$V72-DATA_PIPELINE!$W72 -> 500 | Y72: =IF(DATA_PIPELINE!$X72=0,"Paid",IF(DATA_PIPELINE!$W72=0,"Unpaid","Partly Paid")) -> Unpaid
A73: 68 | B73: MANGASHENA DOREEN | C73: CHIDANGU FARM , IGAVA | D73: PHIBEON MUTIBURA | E73: 58-037974-D-61 | F73: 773380304 | G73: MARONDERA | H73: MASHCENTRAL | J73: EXISTING | K73: 0 | L73: 0 | M73: 0 | N73: 40 | O73: 5038.6 | P73: 0 | Q73: 0 | R73: 5038.6 | S73: - | T73: 40 | U73: Category A | V73: 500 | W73: =DATA_PIPELINE!$K73 -> 0 | X73: =DATA_PIPELINE!$V73-DATA_PIPELINE!$W73 -> 500 | Y73: =IF(DATA_PIPELINE!$X73=0,"Paid",IF(DATA_PIPELINE!$W73=0,"Unpaid","Partly Paid")) -> Unpaid
A74: 69 | B74: CHIHOTA SPENCER | C74: GOREJENA PLOT 1 | D74: PHIBEON MUTIBURA | E74: 63-976550-C-43 | F74: 774838715 | G74: MARONDERA | H74: MASHCENTRAL | J74: EXISTING | K74: 0 | L74: 0 | M74: 0 | N74: 50 | O74: 11485.88 | P74: 0 | Q74: 0 | R74: 11485.88 | S74: - | T74: 50 | U74: Category A | V74: 500 | W74: =DATA_PIPELINE!$K74 -> 0 | X74: =DATA_PIPELINE!$V74-DATA_PIPELINE!$W74 -> 500 | Y74: =IF(DATA_PIPELINE!$X74=0,"Paid",IF(DATA_PIPELINE!$W74=0,"Unpaid","Partly Paid")) -> Unpaid
A75: 70 | B75: MUTIBURA PHIBEON | C75: BERWICK FARM | D75: PHIBEON MUTIBURA | E75: 63-893739-Q-07 | F75: 788360239 | G75: MAZOWE | H75: MASHCENTRAL | J75: EXISTING | K75: 1000 | L75: 0 | M75: 0 | N75: 600 | O75: 173036.14 | P75: 0 | Q75: 0 | R75: 173036.14 | S75: - | T75: 600 | U75: Category B | V75: 1000 | W75: =DATA_PIPELINE!$K75 -> 1000 | X75: =DATA_PIPELINE!$V75-DATA_PIPELINE!$W75 -> 0 | Y75: =IF(DATA_PIPELINE!$X75=0,"Paid",IF(DATA_PIPELINE!$W75=0,"Unpaid","Partly Paid")) -> Paid
A76: 71 | B76: MADZURA WENDY | C76: WENJI FARM , CONCESSION | D76: PHIBEON MUTIBURA | E76: 29-2008578-C-70 | F76: 773270080 | G76: MAZOWE | H76: MASHCENTRAL | J76: EXISTING | K76: 500 | L76: 0 | M76: 0 | N76: 100 | O76: 11922.2 | P76: 19.64 | Q76: 7163.69 | R76: 4758.51 | S76: 60.09 | T76: 100 | U76: Category A | V76: 500 | W76: =DATA_PIPELINE!$K76 -> 500 | X76: =DATA_PIPELINE!$V76-DATA_PIPELINE!$W76 -> 0 | Y76: =IF(DATA_PIPELINE!$X76=0,"Paid",IF(DATA_PIPELINE!$W76=0,"Unpaid","Partly Paid")) -> Paid
A77: 72 | B77: GWATIMBA MN | C77: TIZORO FARM | D77: PHIBEON MUTIBURA | E77: 63-2030938-Z-26 | F77: 775222627 | G77: MUZARABANI | H77: MASHCENTRAL | J77: EXISTING | K77: 0 | L77: 0 | M77: 0 | N77: 50 | O77: 11654.07 | P77: 0 | Q77: 0 | R77: 11654.07 | S77: - | T77: 50 | U77: Category A | V77: 500 | W77: =DATA_PIPELINE!$K77 -> 0 | X77: =DATA_PIPELINE!$V77-DATA_PIPELINE!$W77 -> 500 | Y77: =IF(DATA_PIPELINE!$X77=0,"Paid",IF(DATA_PIPELINE!$W77=0,"Unpaid","Partly Paid")) -> Unpaid
A78: 73 | B78: KAPENDE TAFADZWA | C78: NK | D78: PHIBEON MUTIBURA | E78: 48-083283-M-48 | G78: BEATRICE | H78: MASHCENTRAL | J78: EXISTING | K78: 0 | L78: 0 | M78: 0 | N78: 20 | O78: 3799.67 | P78: 0 | Q78: 0 | R78: 3799.67 | S78: - | T78: 20 | U78: Category A | V78: 500 | W78: =DATA_PIPELINE!$K78 -> 0 | X78: =DATA_PIPELINE!$V78-DATA_PIPELINE!$W78 -> 500 | Y78: =IF(DATA_PIPELINE!$X78=0,"Paid",IF(DATA_PIPELINE!$W78=0,"Unpaid","Partly Paid")) -> Unpaid
A79: 74 | B79: JAJI TAKUNDIWA J | C79: ATHLONE FARM BINDURA | D79: PHIBEON MUTIBURA | E79: 15-070888-Z-45 | F79: 772762241 | G79: BINDURA | H79: MASHCENTRAL | J79: EXISTING | K79: 0 | L79: 0 | M79: 0 | N79: 100 | O79: 4466.28 | P79: 0 | Q79: 0 | R79: 4466.28 | S79: - | T79: 100 | U79: Category A | V79: 500 | W79: =DATA_PIPELINE!$K79 -> 0 | X79: =DATA_PIPELINE!$V79-DATA_PIPELINE!$W79 -> 500 | Y79: =IF(DATA_PIPELINE!$X79=0,"Paid",IF(DATA_PIPELINE!$W79=0,"Unpaid","Partly Paid")) -> Unpaid
A80: 75 | B80: DUBE SHINGIRAI | C80: NK | D80: PHIBEON MUTIBURA | E80: 47-183323 V 13 | G80: MACHEKE | H80: MASHCENTRAL | J80: EXISTING | K80: 0 | L80: 0 | M80: 0 | N80: 40 | O80: 4167.02 | P80: 0 | Q80: 0 | R80: 4167.02 | S80: - | T80: 40 | U80: Category A | V80: 500 | W80: =DATA_PIPELINE!$K80 -> 0 | X80: =DATA_PIPELINE!$V80-DATA_PIPELINE!$W80 -> 500 | Y80: =IF(DATA_PIPELINE!$X80=0,"Paid",IF(DATA_PIPELINE!$W80=0,"Unpaid","Partly Paid")) -> Unpaid
A81: 76 | B81: SEWERA PHILIP | C81: CRIEY LEA FARM | D81: PHIBEON MUTIBURA | E81: 68-010914-J-42 | F81: 782009397 | G81: MARONDERA | H81: MASHCENTRAL | J81: EXISTING | K81: 0 | L81: 0 | M81: 0 | N81: 40 | O81: 3727.25 | P81: 0 | Q81: 0 | R81: 3727.25 | S81: - | T81: 40 | U81: Category A | V81: 500 | W81: =DATA_PIPELINE!$K81 -> 0 | X81: =DATA_PIPELINE!$V81-DATA_PIPELINE!$W81 -> 500 | Y81: =IF(DATA_PIPELINE!$X81=0,"Paid",IF(DATA_PIPELINE!$W81=0,"Unpaid","Partly Paid")) -> Unpaid
A82: 77 | B82: ZVINAVASHE TARIRO | C82: R/E OF VICTORY FARM | D82: PHIBEON MUTIBURA | E82: 63-2375901-J-27 | F82: 772370590 | G82: SEKE | H82: MASHCENTRAL | J82: EXISTING | K82: 0 | L82: 0 | M82: 0 | N82: 40 | O82: 2285.67 | P82: 0 | Q82: 0 | R82: 2285.67 | S82: - | T82: 40 | U82: Category A | V82: 500 | W82: =DATA_PIPELINE!$K82 -> 0 | X82: =DATA_PIPELINE!$V82-DATA_PIPELINE!$W82 -> 500 | Y82: =IF(DATA_PIPELINE!$X82=0,"Paid",IF(DATA_PIPELINE!$W82=0,"Unpaid","Partly Paid")) -> Unpaid
A83: 78 | B83: MHARAPARA ISIAH | C83: BENWELL FARM PLOT 4 | D83: PHIBEON MUTIBURA | E83: 14-013178-P-80 | F83: 774735015 | G83: BINDURA | H83: MASHCENTRAL | J83: EXISTING | K83: 0 | L83: 0 | M83: 0 | N83: 40 | O83: 2703.64 | P83: 0 | Q83: 0 | R83: 2703.64 | S83: - | T83: 40 | U83: Category A | V83: 500 | W83: =DATA_PIPELINE!$K83 -> 0 | X83: =DATA_PIPELINE!$V83-DATA_PIPELINE!$W83 -> 500 | Y83: =IF(DATA_PIPELINE!$X83=0,"Paid",IF(DATA_PIPELINE!$W83=0,"Unpaid","Partly Paid")) -> Unpaid
A84: 79 | B84: MAVETERA TATENDA | C84: NK | D84: PHIBEON MUTIBURA | E84: 27-2000247R27 | G84: BINDURA | H84: MASHCENTRAL | J84: EXISTING | K84: 0 | L84: 0 | M84: 0 | N84: 40 | O84: 5798.01 | P84: 0 | Q84: 0 | R84: 5798.01 | S84: - | T84: 40 | U84: Category A | V84: 500 | W84: =DATA_PIPELINE!$K84 -> 0 | X84: =DATA_PIPELINE!$V84-DATA_PIPELINE!$W84 -> 500 | Y84: =IF(DATA_PIPELINE!$X84=0,"Paid",IF(DATA_PIPELINE!$W84=0,"Unpaid","Partly Paid")) -> Unpaid
A85: 80 | B85: ZIYAMBI ZIYAMBI | C85: LONGWOOD FARM , DARWENDALE | D85: COMMENT TONDERAYI MUTARA | E85: 32-084159-K-70 | F85: 719119461 | G85: ZVIMBA | H85: MASHWEST | J85: EXISTING | K85: 0 | L85: 0 | M85: 0 | N85: 20 | O85: 7128.8 | P85: 0 | Q85: 0 | R85: 7128.8 | S85: - | T85: 80 | U85: Category A | V85: 500 | W85: =DATA_PIPELINE!$K85 -> 0 | X85: =DATA_PIPELINE!$V85-DATA_PIPELINE!$W85 -> 500 | Y85: =IF(DATA_PIPELINE!$X85=0,"Paid",IF(DATA_PIPELINE!$W85=0,"Unpaid","Partly Paid")) -> Unpaid
A86: 81 | B86: JINYA JEFFREY | C86: PLOT 10 BALLANEETTY FARM NYABIRA | D86: WALTER MASHINGAIDZE | E86: 70-135325-Y-71 | F86: 771008716 | G86: ZVIMBA | H86: MASHWEST | J86: EXISTING | K86: 0 | L86: 0 | M86: 0 | N86: 10 | O86: 2381.6 | P86: 0 | Q86: 0 | R86: 2381.6 | S86: - | T86: 10 | U86: Category A | V86: 500 | W86: =DATA_PIPELINE!$K86 -> 0 | X86: =DATA_PIPELINE!$V86-DATA_PIPELINE!$W86 -> 500 | Y86: =IF(DATA_PIPELINE!$X86=0,"Paid",IF(DATA_PIPELINE!$W86=0,"Unpaid","Partly Paid")) -> Unpaid
A87: 82 | B87: NYANDIMA TAMUKA | C87: NK | D87: WALTER MASHINGAIDZE | E87: 34-111439A34 | G87: ZVIMBA | H87: MASHWEST | J87: EXISTING | K87: 0 | L87: 0 | M87: 0 | N87: 20 | O87: 5540.49 | P87: 0 | Q87: 0 | R87: 5540.49 | S87: - | T87: 20 | U87: Category A | V87: 500 | W87: =DATA_PIPELINE!$K87 -> 0 | X87: =DATA_PIPELINE!$V87-DATA_PIPELINE!$W87 -> 500 | Y87: =IF(DATA_PIPELINE!$X87=0,"Paid",IF(DATA_PIPELINE!$W87=0,"Unpaid","Partly Paid")) -> Unpaid
A88: 83 | B88: KASUSU GODKNOWS | C88: NK | D88: WALTER MASHINGAIDZE | E88: 86-043996-G-45 | G88: ZVIMBA | H88: MASHWEST | J88: EXISTING | K88: 0 | L88: 0 | M88: 0 | N88: 0 | O88: 4778.11 | P88: 0 | Q88: 0 | R88: 4778.11 | S88: - | T88: 0 | U88: Category A | V88: 500 | W88: =DATA_PIPELINE!$K88 -> 0 | X88: =DATA_PIPELINE!$V88-DATA_PIPELINE!$W88 -> 500 | Y88: =IF(DATA_PIPELINE!$X88=0,"Paid",IF(DATA_PIPELINE!$W88=0,"Unpaid","Partly Paid")) -> Unpaid
A89: 84 | B89: NYAMUFANA GIFT | C89: NK | D89: WALTER MASHINGAIDZE | E89: 86-071829-K-71 | G89: ZVIMBA | H89: MASHWEST | J89: EXISTING | K89: 0 | L89: 0 | M89: 0 | N89: 0 | O89: 5766.34 | P89: 0 | Q89: 0 | R89: 5766.34 | S89: - | T89: 0 | U89: Category A | V89: 500 | W89: =DATA_PIPELINE!$K89 -> 0 | X89: =DATA_PIPELINE!$V89-DATA_PIPELINE!$W89 -> 500 | Y89: =IF(DATA_PIPELINE!$X89=0,"Paid",IF(DATA_PIPELINE!$W89=0,"Unpaid","Partly Paid")) -> Unpaid
A90: 85 | B90: MANKANYA RONALD | C90: HUMMON HALL | D90: WALTER MASHINGAIDZE | E90: 67-110504-Z-67 | F90: 775696973 | G90: ZVIMBA | H90: MASHWEST | J90: EXISTING | K90: 200 | L90: 300 | M90: 0 | N90: 100 | O90: 12155.47 | P90: 0 | Q90: 0 | R90: 12155.47 | S90: - | T90: 100 | U90: Category A | V90: 500 | W90: =DATA_PIPELINE!$K90 -> 200 | X90: =DATA_PIPELINE!$V90-DATA_PIPELINE!$W90 -> 300 | Y90: =IF(DATA_PIPELINE!$X90=0,"Paid",IF(DATA_PIPELINE!$W90=0,"Unpaid","Partly Paid")) -> Partly Paid
A91: 86 | B91: MAPFOCHE TICHAONA | C91: COWLEY FARM | D91: WALTER MASHINGAIDZE | E91: 63-1164413-Z-18 | F91: 772425952 | G91: ZVIMBA | H91: MASHWEST | J91: EXISTING | K91: 1000 | L91: 0 | M91: 800 | N91: 500 | O91: 119757.66 | P91: 0 | Q91: 0 | R91: 119757.66 | S91: - | T91: 1300 | U91: Category B | V91: 1000 | W91: =DATA_PIPELINE!$K91 -> 1000 | X91: =DATA_PIPELINE!$V91-DATA_PIPELINE!$W91 -> 0 | Y91: =IF(DATA_PIPELINE!$X91=0,"Paid",IF(DATA_PIPELINE!$W91=0,"Unpaid","Partly Paid")) -> Paid
A92: 87 | B92: MASHINGAIDZE WALTER | C92: NEWLANDS FARM | D92: WALTER MASHINGAIDZE | E92: 63-1144169-V-11 | F92: 772333363 | G92: ZVIMBA | H92: MASHWEST | J92: EXISTING | K92: 200 | L92: 300 | M92: 160 | N92: 200 | O92: 68952.23 | P92: 0 | Q92: 0 | R92: 68952.23 | S92: - | T92: 360 | U92: Category A | V92: 500 | W92: =DATA_PIPELINE!$K92 -> 200 | X92: =DATA_PIPELINE!$V92-DATA_PIPELINE!$W92 -> 300 | Y92: =IF(DATA_PIPELINE!$X92=0,"Paid",IF(DATA_PIPELINE!$W92=0,"Unpaid","Partly Paid")) -> Partly Paid
A93: 88 | B93: MAGAYA BATSIRAI | C93: NIDDERDALE PLOT 1 | D93: WALTER MASHINGAIDZE | E93: 86-047930-H-86 | F93: 774798096 | G93: ZVIMBA | H93: MASHWEST | J93: EXISTING | K93: 0 | L93: 0 | M93: 90 | N93: 200 | O93: 56426.42 | P93: 0 | Q93: 0 | R93: 56426.42 | S93: - | T93: 290 | U93: Category B | V93: 1000 | W93: =DATA_PIPELINE!$K93 -> 0 | X93: =DATA_PIPELINE!$V93-DATA_PIPELINE!$W93 -> 1000 | Y93: =IF(DATA_PIPELINE!$X93=0,"Paid",IF(DATA_PIPELINE!$W93=0,"Unpaid","Partly Paid")) -> Unpaid
A94: 89 | B94: TSOKA AQUILIA | C94: PLOT 14,15,16 MVOU | D94: WALTER MASHINGAIDZE | E94: 63-212834-B-42 | F94: 783438892 | G94: ZVIMBA | H94: MASHWEST | J94: EXISTING | K94: 0 | L94: 0 | M94: 0 | N94: 15 | O94: 2086.41 | P94: 0 | Q94: 0 | R94: 2086.41 | S94: - | T94: 15 | U94: Category A | V94: 500 | W94: =DATA_PIPELINE!$K94 -> 0 | X94: =DATA_PIPELINE!$V94-DATA_PIPELINE!$W94 -> 500 | Y94: =IF(DATA_PIPELINE!$X94=0,"Paid",IF(DATA_PIPELINE!$W94=0,"Unpaid","Partly Paid")) -> Unpaid
A95: 90 | B95: MPESWE DARLINGTON | C95: CHIKOMOCHEMUNGA PLOT 2 | D95: WALTER MASHINGAIDZE | E95: 70-094996-M-70 | F95: 773919140 | G95: ZVIMBA | H95: MASHWEST | J95: EXISTING | K95: 0 | L95: 0 | M95: 0 | N95: 0 | O95: 9275.19 | P95: 0 | Q95: 0 | R95: 9275.19 | S95: - | T95: 0 | U95: Category A | V95: 500 | W95: =DATA_PIPELINE!$K95 -> 0 | X95: =DATA_PIPELINE!$V95-DATA_PIPELINE!$W95 -> 500 | Y95: =IF(DATA_PIPELINE!$X95=0,"Paid",IF(DATA_PIPELINE!$W95=0,"Unpaid","Partly Paid")) -> Unpaid
A96: 91 | B96: MUPAKO KNIGHT | C96: INYATI FARM, Banket | D96: WALTER MASHINGAIDZE | E96: 15-103673-K-15 | F96: 772556781 | G96: ZVIMBA | H96: MASHWEST | J96: EXISTING | K96: 0 | L96: 0 | M96: 0 | N96: 50 | O96: 10849.44 | P96: 0 | Q96: 0 | R96: 10849.44 | S96: - | T96: 50 | U96: Category A | V96: 500 | W96: =DATA_PIPELINE!$K96 -> 0 | X96: =DATA_PIPELINE!$V96-DATA_PIPELINE!$W96 -> 500 | Y96: =IF(DATA_PIPELINE!$X96=0,"Paid",IF(DATA_PIPELINE!$W96=0,"Unpaid","Partly Paid")) -> Unpaid
A97: 92 | B97: MUTANGARA LENIN | C97: HIGHDON FARM | D97: WALTER MASHINGAIDZE | E97: 70-220175-B-07 | F97: 772461379 | G97: ZVIMBA | H97: MASHWEST | J97: EXISTING | K97: 1000 | L97: 0 | M97: 600 | N97: 600 | O97: 85122.68 | P97: 0 | Q97: 0 | R97: 85122.68 | S97: - | T97: 1200 | U97: Category B | V97: 1000 | W97: =DATA_PIPELINE!$K97 -> 1000 | X97: =DATA_PIPELINE!$V97-DATA_PIPELINE!$W97 -> 0 | Y97: =IF(DATA_PIPELINE!$X97=0,"Paid",IF(DATA_PIPELINE!$W97=0,"Unpaid","Partly Paid")) -> Paid
A98: 93 | B98: TAGWASHA CHAKA LENGTON | C98: ILSHAM FARM, TRELAWNEY | D98: WALTER MASHINGAIDZE | E98: 63-2039405-C-34 | F98: 772972291 | G98: ZVIMBA | H98: MASHWEST | J98: EXISTING | K98: 0 | L98: 0 | M98: 0 | N98: 60 | O98: 9603.94 | P98: 0 | Q98: 0 | R98: 9603.94 | S98: - | T98: 60 | U98: Category A | V98: 500 | W98: =DATA_PIPELINE!$K98 -> 0 | X98: =DATA_PIPELINE!$V98-DATA_PIPELINE!$W98 -> 500 | Y98: =IF(DATA_PIPELINE!$X98=0,"Paid",IF(DATA_PIPELINE!$W98=0,"Unpaid","Partly Paid")) -> Unpaid
A99: 94 | B99: MHUNGU EDWIN | C99: CHITOMBORWIZI 60 FARM | D99: WALTER MASHINGAIDZE | E99: 85-038428-Y-85 | F99: 772645431 | G99: ZVIMBA | H99: MASHWEST | I99: 9 | J99: EXISTING | K99: 0 | L99: 0 | M99: 0 | N99: 20 | O99: 2745.4 | P99: 0 | Q99: 0 | R99: 2745.4 | S99: - | T99: 20 | U99: Category A | V99: 500 | W99: =DATA_PIPELINE!$K99 -> 0 | X99: =DATA_PIPELINE!$V99-DATA_PIPELINE!$W99 -> 500 | Y99: =IF(DATA_PIPELINE!$X99=0,"Paid",IF(DATA_PIPELINE!$W99=0,"Unpaid","Partly Paid")) -> Unpaid
A100: 95 | B100: MADZINGO CLEMENCE | C100: CHINOMWE ESTATE RAFINGORA | D100: WALTER MASHINGAIDZE | E100: 22-062363-D-83 | F100: 772923617 | G100: ZVIMBA | H100: MASHWEST | J100: EXISTING | K100: 0 | L100: 0 | M100: 0 | N100: 20 | O100: 5820.47 | P100: 0 | Q100: 0 | R100: 5820.47 | S100: - | T100: 20 | U100: Category A | V100: 500 | W100: =DATA_PIPELINE!$K100 -> 0 | X100: =DATA_PIPELINE!$V100-DATA_PIPELINE!$W100 -> 500 | Y100: =IF(DATA_PIPELINE!$X100=0,"Paid",IF(DATA_PIPELINE!$W100=0,"Unpaid","Partly Paid")) -> Unpaid
A101: 96 | B101: GARAKARA FREDDY | C101: COMBE FARM , Banket | D101: WALTER MASHINGAIDZE | E101: 63-767066-C-70 | F101: 774422844 | G101: ZVIMBA | H101: MASHWEST | J101: EXISTING | K101: 0 | L101: 0 | M101: 20 | N101: 40 | O101: 7314.44 | P101: 0 | Q101: 0 | R101: 7314.44 | S101: - | T101: 60 | U101: Category A | V101: 500 | W101: =DATA_PIPELINE!$K101 -> 0 | X101: =DATA_PIPELINE!$V101-DATA_PIPELINE!$W101 -> 500 | Y101: =IF(DATA_PIPELINE!$X101=0,"Paid",IF(DATA_PIPELINE!$W101=0,"Unpaid","Partly Paid")) -> Unpaid
...

Sheet DATA_RECEIPTS
A1: DATA RECEIPTS
A2: Imported source snapshot — update this table when source workbooks change.
A3: =HYPERLINK("#'HOME'!A1","HOME") -> HOME | B3: =HYPERLINK("#'FARMERS'!A1","FARMERS") -> FARMERS | C3: =HYPERLINK("#'SUBSCRIPTIONS'!A1","SUBSCRIPTIONS") -> SUBSCRIPTIONS | D3: =HYPERLINK("#'PRODUCTION'!A1","PRODUCTION") -> PRODUCTION | E3: =HYPERLINK("#'RECOVERY'!A1","RECOVERY") -> RECOVERY | F3: =HYPERLINK("#'DELIVERIES'!A1","DELIVERIES") -> DELIVERIES | G3: =HYPERLINK("#'FINANCE'!A1","FINANCE") -> FINANCE
A5: MONTH | B5: DATE | C5: FARMER NAME | D5: AMOUNT DUE | E5: AMOUNT PAID | F5: BALANCE | G5: TYPE
A6: 45962 | B6: 45986 | C6: LENIN MUTANGARA | D6: 1000 | E6: 1000 | F6: =DATA_RECEIPTS!$D6-DATA_RECEIPTS!$E6 -> 0 | G6: Cash
A7: 45962 | B7: 45984 | C7: ISAIAH DAVISON FARAI CHAKUCHICHI | D7: 1000 | E7: 1000 | F7: =DATA_RECEIPTS!$D7-DATA_RECEIPTS!$E7 -> 0 | G7: Cash
A8: 45962 | B8: 45984 | C8: TICHAONA MAPFOCHE | D8: 1000 | E8: 1000 | F8: =DATA_RECEIPTS!$D8-DATA_RECEIPTS!$E8 -> 0 | G8: Cash
A9: 45962 | B9: 45984 | C9: FUNGAI MAKONI | D9: 1000 | E9: 1000 | F9: =DATA_RECEIPTS!$D9-DATA_RECEIPTS!$E9 -> 0 | G9: Cash
A10: 45962 | B10: 45987 | C10: MUTIBURA PHEBEON | D10: 1000 | E10: 1000 | F10: =DATA_RECEIPTS!$D10-DATA_RECEIPTS!$E10 -> 0 | G10: Cash
A11: 45962 | B11: 45987 | C11: WENDEY MADZURA | D11: 500 | E11: 500 | F11: =DATA_RECEIPTS!$D11-DATA_RECEIPTS!$E11 -> 0 | G11: Cash
A12: 45962 | B12: 45987 | C12: NHEMA TAKUNDA | D12: 1000 | E12: 1000 | F12: =DATA_RECEIPTS!$D12-DATA_RECEIPTS!$E12 -> 0 | G12: Cash
A13: 45962 | B13: 45987 | C13: MASHURA LIBERTY | D13: 1000 | E13: 1000 | F13: =DATA_RECEIPTS!$D13-DATA_RECEIPTS!$E13 -> 0 | G13: Cash
A14: 46174 | B14: 46184 | C14: ABIGAIL ZARANYIKA | D14: 500 | E14: 500 | F14: =DATA_RECEIPTS!$D14-DATA_RECEIPTS!$E14 -> 0 | G14: Cash
A15: 46174 | B15: 46198 | C15: NATSAI NHEMACHENA | D15: 500 | E15: 200 | F15: =DATA_RECEIPTS!$D15-DATA_RECEIPTS!$E15 -> 300 | G15: Cash
A16: 46204 | B16: 46206 | C16: TENDAI BARE | D16: 300 | E16: 300 | F16: =DATA_RECEIPTS!$D16-DATA_RECEIPTS!$E16 -> 0
A17: 46204 | B17: 46219 | C17: DAVISON MADHIGI | D17: 500 | E17: 500 | F17: =DATA_RECEIPTS!$D17-DATA_RECEIPTS!$E17 -> 0 | G17: Bank
A18: 46204 | B18: 46227 | C18: MALTINA MASHAVA | D18: 500 | E18: 500 | F18: =DATA_RECEIPTS!$D18-DATA_RECEIPTS!$E18 -> 0
A19: 46204 | B19: 46227 | C19: TAZVIVINGA FOROMA | D19: 500 | E19: 100 | F19: =DATA_RECEIPTS!$D19-DATA_RECEIPTS!$E19 -> 400
A20: 46204 | B20: 46227 | C20: WALTER MASHINGAIDZE | D20: 500 | E20: 200 | F20: =DATA_RECEIPTS!$D20-DATA_RECEIPTS!$E20 -> 300
A21: 46235 | B21: 46237 | C21: GURAMATUNHU OBEY | D21: 500 | E21: 200 | F21: =DATA_RECEIPTS!$D21-DATA_RECEIPTS!$E21 -> 300
A22: 46235 | B22: 46237 | C22: TAPFUMANEYI RUTH | D22: 500 | E22: 100 | F22: =DATA_RECEIPTS!$D22-DATA_RECEIPTS!$E22 -> 400 | G22: Bank
A23: 46235 | B23: 46237 | C23: CHAFAUSIPO CLIFFORD | D23: 500 | E23: 100 | F23: =DATA_RECEIPTS!$D23-DATA_RECEIPTS!$E23 -> 400 | G23: Bank
A24: 46235 | B24: 46238 | C24: MAZONDE FARAI | D24: 500 | E24: 100 | F24: =DATA_RECEIPTS!$D24-DATA_RECEIPTS!$E24 -> 400 | G24: Bank
A25: 46235 | B25: 46237 | C25: PAUCHENI MASANGO | D25: 500 | E25: 500 | F25: =DATA_RECEIPTS!$D25-DATA_RECEIPTS!$E25 -> 0 | G25: Bank
A26: 46235 | B26: 46237 | C26: MAMBO MUSONA | D26: 500 | E26: 200 | F26: =DATA_RECEIPTS!$D26-DATA_RECEIPTS!$E26 -> 300 | G26: Bank
A27: 46235 | B27: 46240 | C27: DORREEN NYARADZAI | D27: 500 | E27: 100 | F27: =DATA_RECEIPTS!$D27-DATA_RECEIPTS!$E27 -> 400 | G27: Bank
A28: 46246 | B28: 46241 | C28: PATIENCE MUTANGADURA | D28: 500 | E28: 500 | F28: =DATA_RECEIPTS!$D28-DATA_RECEIPTS!$E28 -> 0 | G28: Bank
A29: 46235 | B29: 46243 | C29: TSORAI EDNA | D29: 500 | E29: 100 | F29: =DATA_RECEIPTS!$D29-DATA_RECEIPTS!$E29 -> 400 | G29: Bank
A30: 46260 | B30: 46246 | C30: MASHAVAVE SIMBARASHE | D30: 500 | E30: 100 | F30: =DATA_RECEIPTS!$D30-DATA_RECEIPTS!$E30 -> 400 | G30: bank
A31: 46248 | B31: 46248 | C31: NYACHOWE LEO | D31: 500 | E31: 100 | F31: =DATA_RECEIPTS!$D31-DATA_RECEIPTS!$E31 -> 400 | G31: Bank
A32: 46248 | B32: 46248 | C32: ZUNGUNDE BETTY | D32: 500 | E32: 50 | F32: =DATA_RECEIPTS!$D32-DATA_RECEIPTS!$E32 -> 450 | G32: Bank
A33: 46248 | B33: 46248 | C33: RETIWA REGIS | D33: 500 | E33: 200 | F33: =DATA_RECEIPTS!$D33-DATA_RECEIPTS!$E33 -> 300 | G33: Bank
A34: 46251 | B34: 46251 | C34: MATIYENGA MUNYARADZI | D34: 500 | E34: 100 | F34: =DATA_RECEIPTS!$D34-DATA_RECEIPTS!$E34 -> 400 | G34: Bank
A35: 46252 | B35: 46252 | C35: MELLODY N CHITIYO | D35: 500 | E35: 100 | F35: 400 | G35: Bank
A36: 46255 | B36: 46255 | C36: GAMUCHIRAI CHIDARIKIRE | D36: 500 | E36: 200 | F36: =DATA_RECEIPTS!$D36-DATA_RECEIPTS!$E36 -> 300 | G36: Bank
A37: 46255 | B37: 46255 | C37: PETER MATARUSE | D37: 500 | E37: 200 | F37: 200 | G37: Bank
A38: 46258 | B38: 46258 | C38: MUTARA COMMENT | D38: 500 | E38: 100 | F38: =DATA_RECEIPTS!$D38-DATA_RECEIPTS!$E38 -> 400 | G38: Bank
A39: 46254 | B39: 46254 | C39: CLIVE CHOTO | D39: 500 | E39: 100 | F39: =DATA_RECEIPTS!$D39-DATA_RECEIPTS!$E39 -> 400 | G39: Bank
A40: 46258 | B40: 46258 | C40: FUNNY MUNYONGA | D40: 500 | E40: 50 | F40: =DATA_RECEIPTS!$D40-DATA_RECEIPTS!$E40 -> 450 | G40: Bank
A41: 46259 | B41: 46259 | C41: ERNERST KAPUYA | D41: 500 | E41: 250 | F41: =DATA_RECEIPTS!$D41-DATA_RECEIPTS!$E41 -> 250 | G41: Bank
A42: 46262 | B42: 46262 | C42: PARADZWANWA MISHECK | D42: 500 | E42: 50 | F42: =DATA_RECEIPTS!$D42-DATA_RECEIPTS!$E42 -> 450 | G42: Bank
A43: 46262 | B43: 46262 | C43: MICHAEL MUGUVAZA | D43: 500 | E43: 500 | F43: =DATA_RECEIPTS!$D43-DATA_RECEIPTS!$E43 -> 0 | G43: Bank
A44: 46263 | B44: 46263 | C44: FARAI JONGORO | D44: 500 | E44: 100 | F44: =DATA_RECEIPTS!$D44-DATA_RECEIPTS!$E44 -> 400 | G44: Bank
A45: 46263 | B45: 46263 | C45: CHIKARO TIONOS | D45: 500 | E45: 50 | F45: =DATA_RECEIPTS!$D45-DATA_RECEIPTS!$E45 -> 450 | G45: Bank
A46: 46265 | B46: 46265 | C46: MASANGO JAMES | D46: 500 | E46: 500 | F46: =DATA_RECEIPTS!$D46-DATA_RECEIPTS!$E46 -> 0 | G46: Bank
A47: 46265 | B47: 46265 | C47: ROSEMARY KULEYA | D47: 500 | E47: 200 | F47: =DATA_RECEIPTS!$D47-DATA_RECEIPTS!$E47 -> 300 | G47: Bank
A48: 46266 | B48: 46266 | C48: RONALD MANKANYA | D48: 500 | E48: 200 | F48: =DATA_RECEIPTS!$D48-DATA_RECEIPTS!$E48 -> 300 | G48: Bank
A49: 46266 | B49: 46266 | C49: MUNYARADZI MATIYENGA | D49: 500 | E49: 100 | F49: =DATA_RECEIPTS!$D49-DATA_RECEIPTS!$E49 -> 400 | G49: Bank
... A62: 46273 | B62: 46273 | C62: HOVE ZIVAI | D62: 500 | E62: 500 | F62: =DATA_RECEIPTS!$D62-DATA_RECEIPTS!$E62 -> 0 | G62: Bank
D63: 0 | E63: 0 | F63: =DATA_RECEIPTS!$D63-DATA_RECEIPTS!$E63 -> 0
D64: 0 | E64: 0 | F64: =DATA_RECEIPTS!$D64-DATA_RECEIPTS!$E64 -> 0
D65: 0 | E65: 0 | F65: =DATA_RECEIPTS!$D65-DATA_RECEIPTS!$E65 -> 0
D66: 0 | E66: 0 | F66: =DATA_RECEIPTS!$D66-DATA_RECEIPTS!$E66 -> 0
D67: 0 | E67: 0 | F67: =DATA_RECEIPTS!$D67-DATA_RECEIPTS!$E67 -> 0
D68: 0 | E68: 0 | F68: =DATA_RECEIPTS!$D68-DATA_RECEIPTS!$E68 -> 0
D69: 0 | E69: 0 | F69: =DATA_RECEIPTS!$D69-DATA_RECEIPTS!$E69 -> 0
D70: 0 | E70: 0 | F70: =DATA_RECEIPTS!$D70-DATA_RECEIPTS!$E70 -> 0
D71: 0 | E71: 0 | F71: =DATA_RECEIPTS!$D71-DATA_RECEIPTS!$E71 -> 0
D72: 0 | E72: 0 | F72: =DATA_RECEIPTS!$D72-DATA_RECEIPTS!$E72 -> 0
D73: 0 | E73: 0 | F73: =DATA_RECEIPTS!$D73-DATA_RECEIPTS!$E73 -> 0
E74: 0 | F74: =DATA_RECEIPTS!$D74-DATA_RECEIPTS!$E74 -> 0
E75: 0 | F75: =DATA_RECEIPTS!$D75-DATA_RECEIPTS!$E75 -> 0
C77: TOTAL RECEIPTS | D77: =SUM(D6:D75) -> 31500 | E77: =SUM(E6:E75) -> 17375 | F77: =SUM(F6:F75) -> 14025

Sheet SGR ASSET REGISTER
A1: SGR ASSET REGISTER & DEPRECIATION SCHEDULE
A2: Fixed asset register with straight-line depreciation, accumulated depreciation and closing net book value.
A4: =HYPERLINK("#'HOME'!A1","HOME") -> HOME | B4: =HYPERLINK("#'FINANCE'!A1","FINANCE") -> FINANCE | C4: =HYPERLINK("#'REPORTS'!A1","REPORTS") -> REPORTS | D4: =HYPERLINK("#'PRODUCTION'!A1","PRODUCTION") -> PRODUCTION | E4: =HYPERLINK("#'SORGHUM BUDGET'!A1","SORGHUM BUDGET") -> SORGHUM BUDGET | F4: =HYPERLINK("#'MAIZE BUDGET'!A1","MAIZE BUDGET") -> MAIZE BUDGET
A6: Asset ID | B6: Asset Description | C6: Category | D6: Purchase Date | E6: Cost (USD) | F6: Residual Value (USD) | G6: Useful Life (Years) | H6: Annual Depreciation (USD) | I6: Accumulated Depreciation (USD) | J6: Closing NBV (USD)
A7: COM1 | B7: HP-ELITEBOOK 840 CORE i7 | C7: Laptop | D7: 46265 | E7: 390 | F7: 80 | G7: 2 | H7: =IF(OR(E7="",F7="",G7=""),"",MAX(0,(E7-F7)/G7)) -> 155 | I7: =IF(OR(H7="",D7=""),"",MIN(E7-F7,H7*MAX(0,YEARFRAC(D7,DATE(2027,8,31))))) -> 155 | J7: =IF(E7="","",MAX(F7,E7-IF(I7="",0,I7))) -> 235
A8: CH01 | B8: MESH VISITORS CHAIRS | C8: Office Equipment | D8: 46265 | E8: 380 | F8: 16 | G8: 1 | H8: =IF(OR(E8="",F8="",G8=""),"",MAX(0,(E8-F8)/G8)) -> 364 | I8: =IF(OR(H8="",D8=""),"",MIN(E8-F8,H8*MAX(0,YEARFRAC(D8,DATE(2027,8,31))))) -> 364 | J8: =IF(E8="","",MAX(F8,E8-IF(I8="",0,I8))) -> 16
H9: =IF(OR(E9="",F9="",G9=""),"",MAX(0,(E9-F9)/G9)) | I9: =IF(OR(H9="",D9=""),"",MIN(E9-F9,H9*MAX(0,YEARFRAC(D9,DATE(2027,8,31))))) | J9: =IF(E9="","",MAX(F9,E9-IF(I9="",0,I9)))
H10: =IF(OR(E10="",F10="",G10=""),"",MAX(0,(E10-F10)/G10)) | I10: =IF(OR(H10="",D10=""),"",MIN(E10-F10,H10*MAX(0,YEARFRAC(D10,DATE(2027,8,31))))) | J10: =IF(E10="","",MAX(F10,E10-IF(I10="",0,I10)))
H11: =IF(OR(E11="",F11="",G11=""),"",MAX(0,(E11-F11)/G11)) | I11: =IF(OR(H11="",D11=""),"",MIN(E11-F11,H11*MAX(0,YEARFRAC(D11,DATE(2027,8,31))))) | J11: =IF(E11="","",MAX(F11,E11-IF(I11="",0,I11)))
H12: =IF(OR(E12="",F12="",G12=""),"",MAX(0,(E12-F12)/G12)) | I12: =IF(OR(H12="",D12=""),"",MIN(E12-F12,H12*MAX(0,YEARFRAC(D12,DATE(2027,8,31))))) | J12: =IF(E12="","",MAX(F12,E12-IF(I12="",0,I12)))
H13: =IF(OR(E13="",F13="",G13=""),"",MAX(0,(E13-F13)/G13)) | I13: =IF(OR(H13="",D13=""),"",MIN(E13-F13,H13*MAX(0,YEARFRAC(D13,DATE(2027,8,31))))) | J13: =IF(E13="","",MAX(F13,E13-IF(I13="",0,I13)))
H14: =IF(OR(E14="",F14="",G14=""),"",MAX(0,(E14-F14)/G14)) | I14: =IF(OR(H14="",D14=""),"",MIN(E14-F14,H14*MAX(0,YEARFRAC(D14,DATE(2027,8,31))))) | J14: =IF(E14="","",MAX(F14,E14-IF(I14="",0,I14)))
H15: =IF(OR(E15="",F15="",G15=""),"",MAX(0,(E15-F15)/G15)) | I15: =IF(OR(H15="",D15=""),"",MIN(E15-F15,H15*MAX(0,YEARFRAC(D15,DATE(2027,8,31))))) | J15: =IF(E15="","",MAX(F15,E15-IF(I15="",0,I15)))
H16: =IF(OR(E16="",F16="",G16=""),"",MAX(0,(E16-F16)/G16)) | I16: =IF(OR(H16="",D16=""),"",MIN(E16-F16,H16*MAX(0,YEARFRAC(D16,DATE(2027,8,31))))) | J16: =IF(E16="","",MAX(F16,E16-IF(I16="",0,I16)))
H17: =IF(OR(E17="",F17="",G17=""),"",MAX(0,(E17-F17)/G17)) | I17: =IF(OR(H17="",D17=""),"",MIN(E17-F17,H17*MAX(0,YEARFRAC(D17,DATE(2027,8,31))))) | J17: =IF(E17="","",MAX(F17,E17-IF(I17="",0,I17)))
H18: =IF(OR(E18="",F18="",G18=""),"",MAX(0,(E18-F18)/G18)) | I18: =IF(OR(H18="",D18=""),"",MIN(E18-F18,H18*MAX(0,YEARFRAC(D18,DATE(2027,8,31))))) | J18: =IF(E18="","",MAX(F18,E18-IF(I18="",0,I18)))
H19: =IF(OR(E19="",F19="",G19=""),"",MAX(0,(E19-F19)/G19)) | I19: =IF(OR(H19="",D19=""),"",MIN(E19-F19,H19*MAX(0,YEARFRAC(D19,DATE(2027,8,31))))) | J19: =IF(E19="","",MAX(F19,E19-IF(I19="",0,I19)))
H20: =IF(OR(E20="",F20="",G20=""),"",MAX(0,(E20-F20)/G20)) | I20: =IF(OR(H20="",D20=""),"",MIN(E20-F20,H20*MAX(0,YEARFRAC(D20,DATE(2027,8,31))))) | J20: =IF(E20="","",MAX(F20,E20-IF(I20="",0,I20)))
... H26: =IF(OR(E26="",F26="",G26=""),"",MAX(0,(E26-F26)/G26)) | I26: =IF(OR(H26="",D26=""),"",MIN(E26-F26,H26*MAX(0,YEARFRAC(D26,DATE(2027,8,31))))) | J26: =IF(E26="","",MAX(F26,E26-IF(I26="",0,I26)))
B27: TOTAL ASSET REGISTER | E27: =SUM(E7:E26) -> 770 | F27: =SUM(F7:F26) -> 96 | H27: =SUM(H7:H26) -> 519 | I27: =SUM(I7:I26) -> 519 | J27: =SUM(J7:J26) -> 251
A29: Depreciation method | B29: Straight-line
A30: Depreciation period | B30: 2026/27 reporting year to 31-Aug-2027
A31: Formula | B31: (Cost − Residual Value) ÷ Useful Life

Sheet CLUSTER PIPELINE PROJECTION
A1: SGR | SUMMER 2026/27 PIPELINE PROJECTION
A2: Executive high-level view of farmer participation and hectares scheduled for 2026/27 summer season, compared with 2025/26
A3: HOME | B3: CLUSTER FARMERS | C3: PIPELINE PROJECTION | D3: DATA PIPELINE | E3: PRODUCTION | F3: SUBSCRIPTIONS | G3: RECOVERY | H3: REPORTS
A5: REGISTERED FARMERS-2025/26 | C5: 2025/26 FARMERS (UNIQUE) | E5: FARMER PIPELINE GROWTH
A6: 429 | C6: 567 | E6: =(C6-A6)/A6 -> 0.32167832
A9: SORGHUM -2025/26 SUMMER HA | C9: 2026/27 SORGHUM HA | E9: HA PIPELINE GROWTH
A10: 16492 | C10: 20526 | E10: =(C10-A10)/A10 -> 0.24460344
A12: 2025/26 MAIZE HA | C12: 2026/27 MAIZE HA | E12: HA PIPELINE GROWTH
A13: 7144 | C13: 7144 | E13: =(C13-A13)/A13 -> 0
A18: SEASON COMPARISON
A19: METRIC | B19: 2025/26 | C19: 2026/27 | D19: CHANGE | E19: CHANGE % | F19: MANAGEMENT VIEW
A20: Farmers | B20: 429 | C20: =C6 -> 567 | D20: =C20-B20 -> 138 | E20: =E6 -> 0.32167832 | F20: More farmers scheduled
A21: Total hectares | B21: 16492 | C21: 27670 | D21: 11178 | E21: 0.678 | F21: Larger production pipeline
A22: Maize hectares | B22: 0 | C22: 7144 | D22: 7144 | F22: New maize component
A23: Sorghum hectares | B23: 16492 | C23: 20526 | D23: 4034 | E23: 0.245 | F23: Sorghum remains core crop
A25: 2026/27 TARGET CHECK
A26: CROP | B26: TARGET HA | C26: SCHEDULED HA | D26: GAP/(SURPLUS) | E26: ACHIEVEMENT | F26: STATUS
A27: MAIZE | B27: 20000 | C27: 7144 | D27: 12856 | E27: 0.357 | F27: GAP TO CLOSE
A28: SORGHUM | B28: 20000 | C28: 20526 | D28: -526 | E28: 1.026 | F28: ON / ABOVE TARGET
A29: COMBINED | B29: 40000 | C29: 27670 | D29: 12330 | E29: 0.692 | F29: GAP TO CLOSE
A32: CLUSTER PIPELINE PROJECTION
A33: CLUSTER | B33: REGISTERED-2026/27 | C33: 2025/26 FARMERS | D33: 26/27 FARMERS | E33: MAIZE HA-2025/26 | F33: MAIZE HA-2026/27 | G33: SORGHUM -2025/26 HA | H33: SORGHUM HA-2026/27 | I33: 26/27 TOTAL HA | J33: SHARE OF 26/27 HA
A34: UNKNOWN | B34: 282 | C34: 190 | D34: 236 | E34: 0 | F34: 6591 | G34: 7460 | H34: 8287 | I34: 14878 | J34: 0.538
A35: TAKUNDA NHEMA | B35: 13 | C35: 12 | D35: 12 | E35: 0 | F35: 0 | G35: 1305 | H35: 1895 | I35: 1895 | J35: 0.068 | K35: MOLEEN TO SENT
A36: MOFFAT SEFU | B36: 49 | C36: 32 | D36: 37 | E36: 0 | F36: 56 | G36: 1110 | H36: 1575 | I36: 1631 | J36: 0.059
A37: PHIBEON MUTIBURA | B37: 18 | C37: 18 | D37: 18 | E37: 0 | F37: 0 | G37: 825 | H37: 1470 | I37: 1470 | J37: 0.053
A38: BATSIRAYI MAGAYA | B38: 43 | C38: 43 | D38: 41 | E38: 0 | F38: 300 | G38: 1000 | H38: 1050 | I38: 1350 | J38: 0.049
A39: RICHARD JENAMI | B39: 26 | C39: 25 | D39: 23 | E39: 0 | F39: 0 | G39: 985 | H39: 1265 | I39: 1265 | J39: 0.046
A40: DANMORE MUDAVANHU | B40: 25 | C40: 25 | D40: 25 | E40: 0 | F40: 0 | G40: 986 | H40: 1150 | I40: 1150 | J40: 0.042 | K40: MOLLEN SHOKO
A41: COMMENT TONDERAYI MUTARA | B41: 14 | C41: 13 | D41: 12 | E41: 0 | F41: 7 | G41: 920 | H41: 1140 | I41: 1147 | J41: 0.041
A42: BRIAN CHIDAVAENZI | B42: 16 | C42: 13 | D42: 16 | E42: 0 | F42: 0 | G42: 462 | H42: 1050 | I42: 1050 | J42: 0.038
A43: UNASSIGNED / NO CLUSTER | B43: 21 | C43: 19 | D43: 20 | E43: 0 | F43: 120 | G43: 473 | H43: 544 | I43: 664 | J43: 0.024
A44: BETTY ZUNGUNDE | B44: 11 | C44: 11 | D44: 10 | E44: 0 | F44: 10 | G44: 452 | H44: 575 | I44: 585 | J44: 0.021
A45: TINASHE CHIKONDOWA | B45: 26 | C45: 23 | D45: 25 | E45: 0 | F45: 0 | G45: 369 | H45: 335 | I45: 335 | J45: 0.012
A46: WALTER MASHINGAIDZE | B46: 5 | C46: 2 | D46: 3 | E46: 0 | F46: 20 | G46: 35 | H46: 90 | I46: 110 | J46: 0.004
A47: MICHEK PARADZANWA | B47: 7 | C47: 1 | D47: 1 | E47: 0 | F47: 40 | G47: 10 | H47: 20 | I47: 60 | J47: 0.002
A48: THEMBEKILE GATA | B48: 1 | C48: 0 | D48: 1 | E48: 0 | F48: 0 | G48: 0 | H48: 50 | I48: 50 | J48: 0.002
A49: NL | B49: 1 | C49: 0 | D49: 1 | E49: 0 | F49: 0 | G49: 0 | H49: 30 | I49: 30 | J49: 0.001
A50: JAMES MASANGO | B50: 1 | C50: 1 | D50: 0 | E50: 0 | F50: 0 | G50: 100 | H50: 0 | I50: 0 | J50: 0
A51: BLESSING CHIWERA | B51: 7 | C51: 0 | D51: 0 | E51: 0 | F51: 0 | G51: 0 | H51: 0 | I51: 0 | J51: 0
A52: MUMANIKWA MUTIMBA
A53: FUNGAYI MAKONI
A54: TAFADZWA NHUNDU
A55: WILSON MUGANDA
A56: TAFADZWA MUSIWA
A57: STANFORD MASHINGAIDZE

Sheet SUBSCRIPTIONS
A1: FARMER SUBSCRIPTION DASHBOARD
A2: Subscription collections, category analysis and monthly performance
A3: =HYPERLINK("#'HOME'!A1","HOME") -> HOME | B3: =HYPERLINK("#'FARMERS'!A1","FARMERS") -> FARMERS | C3: =HYPERLINK("#'SUBSCRIPTIONS'!A1","SUBSCRIPTIONS") -> SUBSCRIPTIONS | D3: =HYPERLINK("#'PRODUCTION'!A1","PRODUCTION") -> PRODUCTION | E3: =HYPERLINK("#'RECOVERY'!A1","RECOVERY") -> RECOVERY | F3: =HYPERLINK("#'DELIVERIES'!A1","DELIVERIES") -> DELIVERIES | G3: =HYPERLINK("#'FINANCE'!A1","FINANCE") -> FINANCE | H3: =HYPERLINK("#'REPORTS'!A1","REPORTS") -> REPORTS
A5: TOTAL REGISTERED | C5: CATEGORY A (<200 HA) | E5: CATEGORY B (>=200 HA) | G5: EXPECTED INCOME | I5: INCOME RECEIVED | K5: OUTSTANDING
A6: =COUNTA(DATA_PIPELINE!$B$6:$B$601) -> 573 | C6: =COUNTIF(DATA_PIPELINE!$U$6:$U$601,"Category A") -> 515 | E6: =COUNTIF(DATA_PIPELINE!$U$6:$U$601,"Category B") -> 24 | G6: =SUM(DATA_PIPELINE!$V$6:$V$601) -> 597000 | I6: =SUM(DATA_RECEIPTS!$E$6:$E$75) -> 17375 | K6: =SUM(DATA_RECEIPTS!$F$6:$F$75) -> 14025
A9: Category | B9: Farmers | C9: Expected Income | D9: Rate | E9: Paid | I9: Hac Size | J9: Sorgum Hac | K9: Maize Ha | L9: % Contribution
A10: Category A | B10: =COUNTIF(DATA_PIPELINE!$U$6:$U$601,"Category A") -> 515 | C10: =B10*500 -> 257500 | D10: 500 | E10: 23 | I10: =SUMIFS(DATA_PIPELINE!$N$6:$N$601, DATA_PIPELINE!$U$6:$U$601, "Category A") + SUMIFS(DATA_PIPELINE!$M$6:$M$601, DATA_PIPELINE!$U$6:$U$601, "Category A") -> 19791 | J10: =SUMIFS(DATA_PIPELINE!$N$6:$N$601, DATA_PIPELINE!$U$6:$U$601, "Category A") -> 14556 | K10: =SUMIFS(DATA_PIPELINE!$M$6:$M$601, DATA_PIPELINE!$U$6:$U$601, "Category A") -> 5235 | L10: =I10/I12 -> 0.64098329
A11: Category B | B11: =COUNTIF(DATA_PIPELINE!$U$6:$U$601,"Category B") -> 24 | C11: =B11*1000 -> 24000 | D11: 1000 | E11: 7 | I11: =SUMIFS(DATA_PIPELINE!$N$6:$N$601, DATA_PIPELINE!$U$6:$U$601, "Category B") + SUMIFS(DATA_PIPELINE!$M$6:$M$601, DATA_PIPELINE!$U$6:$U$601, "Category B") -> 11085 | J11: =SUMIFS(DATA_PIPELINE!$N$6:$N$601, DATA_PIPELINE!$U$6:$U$601, "Category B") -> 5900 | K11: =SUMIFS(DATA_PIPELINE!$M$6:$M$601, DATA_PIPELINE!$U$6:$U$601, "Category B") -> 5185 | L11: =I11/I12 -> 0.35901671
H12: Total | I12: =I10+I11 -> 30876 | J12: =J10+J11 -> 20456 | K12: =K10+K11 -> 10420 | L12: =L10+L11 -> 1
A14: Monthly collections
A15: Month | B15: Collections | C15: Outstanding | D15: Transactions
A16: 45962 | B16: =SUMIF(DATA_RECEIPTS!$A$6:$A$75,A16,DATA_RECEIPTS!$E$6:$E$75) -> 7500 | C16: =SUMIF(DATA_RECEIPTS!$A$6:$A$75,A16,DATA_RECEIPTS!$F$6:$F$75) -> 0 | D16: =COUNTIF(DATA_RECEIPTS!$A$6:$A$75,A16) -> 8
A17: 46174 | B17: =SUMIF(DATA_RECEIPTS!$A$6:$A$75,A17,DATA_RECEIPTS!$E$6:$E$75) -> 700 | C17: =SUMIF(DATA_RECEIPTS!$A$6:$A$75,A17,DATA_RECEIPTS!$F$6:$F$75) -> 300 | D17: =COUNTIF(DATA_RECEIPTS!$A$6:$A$75,A17) -> 2
A18: 46204 | B18: =SUMIF(DATA_RECEIPTS!$A$6:$A$75,A18,DATA_RECEIPTS!$E$6:$E$75) -> 1600 | C18: =SUMIF(DATA_RECEIPTS!$A$6:$A$75,A18,DATA_RECEIPTS!$F$6:$F$75) -> 700 | D18: =COUNTIF(DATA_RECEIPTS!$A$6:$A$75,A18) -> 5
A19: 46235 | B19: =SUMIFS(DATA_RECEIPTS!E:E, DATA_RECEIPTS!A:A, ">=2026-08-01", DATA_RECEIPTS!A:A, "<2026-09-01") -> 4850 | C19: =SUMIF(DATA_RECEIPTS!$A$6:$A$75,A19,DATA_RECEIPTS!$F$6:$F$75) -> 2600 | D19: =COUNTIF(DATA_RECEIPTS!$A$6:$A$75,A19) -> 8
A20: 46266 | B20: =SUMIFS(DATA_RECEIPTS!E:E, DATA_RECEIPTS!A:A, ">=2026-09-01", DATA_RECEIPTS!A:A, "<2026-10-01") -> 2725 | C20: =SUMIF(DATA_RECEIPTS!$A$6:$A$75,A20,DATA_RECEIPTS!$F$6:$F$75) -> 2075 | D20: =COUNTIF(DATA_RECEIPTS!$A$6:$A$75,A20) -> 5

Sheet FINANCE
A1: FINANCE DASHBOARD
A2: Receipt book + expense book + bank reconciliation
A3: =HYPERLINK("#'HOME'!A1","HOME") -> HOME | B3: =HYPERLINK("#'FARMERS'!A1","FARMERS") -> FARMERS | C3: =HYPERLINK("#'SUBSCRIPTIONS'!A1","SUBSCRIPTIONS") -> SUBSCRIPTIONS | D3: =HYPERLINK("#'PRODUCTION'!A1","PRODUCTION") -> PRODUCTION | E3: =HYPERLINK("#'RECOVERY'!A1","RECOVERY") -> RECOVERY | F3: =HYPERLINK("#'DELIVERIES'!A1","DELIVERIES") -> DELIVERIES | G3: =HYPERLINK("#'FINANCE'!A1","FINANCE") -> FINANCE | H3: =HYPERLINK("#'REPORTS'!A1","REPORTS") -> REPORTS
A5: AUGUST TOTAL BANK RECEIPTS | C5: TOTAL BANK EXPENSES(YTD) | E5: CLOSING BANK BALANCE | G5: RECEIPT BOOK COLLECTIONS (YTD) | I5: SUBSCRIPTION OUTSTANDING | K5: RECONCILIATION STATUS
A6: =C14 -> 4850 | C6: =SUM(DATA_BANK!$D$6:$D$10) -> 13249.88 | E6: =E15 -> 4125.12 | G6: =SUM(DATA_RECEIPTS!$E$6:$E$75) -> 17375 | I6: =SUM(DATA_RECEIPTS!$F$6:$F$75) -> 14025 | K6: =COUNTIF(DATA_BANK!$H$6:$H$10,"RECONCILED") -> 5
A9: Monthly cash flow
A10: Month | B10: Opening | C10: Receipts | D10: Expenses | E10: Closing
A11: November 2025 | B11: =SUMIF(DATA_BANK!$A$6:$A$10,A11,DATA_BANK!$B$6:$B$10) -> 0 | C11: =SUMIF(DATA_BANK!$A$6:$A$10,A11,DATA_BANK!$C$6:$C$10) -> 7500 | D11: =SUMIF(DATA_BANK!$A$6:$A$10,A11,DATA_BANK!$D$6:$D$10) -> 7159.5 | E11: =SUMIF(DATA_BANK!$A$6:$A$10,A11,DATA_BANK!$E$6:$E$10) -> 340.5
A12: June 2026 | B12: =SUMIF(DATA_BANK!$A$6:$A$10,A12,DATA_BANK!$B$6:$B$10) -> 340.5 | C12: =SUMIF(DATA_BANK!$A$6:$A$10,A12,DATA_BANK!$C$6:$C$10) -> 700 | D12: =SUMIF(DATA_BANK!$A$6:$A$10,A12,DATA_BANK!$D$6:$D$10) -> 1300 | E12: =SUMIF(DATA_BANK!$A$6:$A$10,A12,DATA_BANK!$E$6:$E$10) -> -259.5
A13: July 2026 | B13: =SUMIF(DATA_BANK!$A$6:$A$10,A13,DATA_BANK!$B$6:$B$10) -> -259.5 | C13: =SUMIF(DATA_BANK!$A$6:$A$10,A13,DATA_BANK!$C$6:$C$10) -> 1600 | D13: =SUMIF(DATA_BANK!$A$6:$A$10,A13,DATA_BANK!$D$6:$D$10) -> 1832.98 | E13: =SUMIF(DATA_BANK!$A$6:$A$10,A13,DATA_BANK!$E$6:$E$10) -> -492.48
A14: August 2026 | B14: =SUMIF(DATA_BANK!$A$6:$A$10,A14,DATA_BANK!$B$6:$B$10) -> -492.48 | C14: =SUMIF(DATA_BANK!$A$6:$A$10,A14,DATA_BANK!$C$6:$C$10) -> 4850 | D14: =SUMIF(DATA_BANK!$A$6:$A$10,A14,DATA_BANK!$D$6:$D$10) -> 2491.31 | E14: =SUMIF(DATA_BANK!$A$6:$A$10,A14,DATA_BANK!$E$6:$E$10) -> 1866.21
A15: 46266 | B15: =E14 -> 1866.21 | C15: =DATA_BANK!C10 -> 2725 | D15: =DATA_BANK!D10 -> 466.09 | E15: =B15+C15-D15 -> 4125.12
A23: NEW MANAGEMENT ACCOUNTS | E23: Expense summary
A24: =HYPERLINK("#'MONTHLY SALARY'!A1","Monthly Salary") -> Monthly Salary | B24: Amount Paid | C24: =HYPERLINK("#'PROFIT & LOSS'!A1","Profit & Loss") -> Profit & Loss | E24: =HYPERLINK("#'BALANCE SHEET'!A1","Balance Sheet") -> Balance Sheet | F24: Expense
A25: Bank | B25: =SUMIF(DATA_RECEIPTS!$G$6:$G$75,A25,DATA_RECEIPTS!$E$6:$E$75) -> 3650 | E25: November 2025 | F25: =SUMIF(DATA_BANK!$A$6:$A$10,E25,DATA_BANK!$D$6:$D$10) -> 7159.5
A26: Cash | B26: =SUMIF(DATA_RECEIPTS!$G$6:$G$75,A26,DATA_RECEIPTS!$E$6:$E$75) -> 8400 | E26: June 2026 | F26: =SUMIF(DATA_BANK!$A$6:$A$10,E26,DATA_BANK!$D$6:$D$10) -> 1300
E27: July 2026 | F27: =SUMIF(DATA_BANK!$A$6:$A$10,E27,DATA_BANK!$D$6:$D$10) -> 1832.98
E28: August 2026 | F28: =SUMIF(DATA_BANK!$A$6:$A$10,E28,DATA_BANK!$D$6:$D$10) -> 2491.31
E29: 46266 | F29: =D15 -> 466.09

Sheet CLUSTER PERFORMANCE
A1: SGR 200HA+ CLUB | CLUSTER PERFORMANCE | N1: =HYPERLINK("#'DATA_PIPELINE'!A1","↗ DATA PIPELINE") -> ↗ DATA PIPELINE
A2: Live management view linked directly to DATA_PIPELINE. Update DATA_PIPELINE and recalculate Excel to refresh the performance figures.
A4: TOTAL CLUSTERS | D4: TOTAL FARMERS | G4: TOTAL PIPELINE HA | J4: PAID FARMERS
A5: =COUNTA(A9:A196) -> 20 | D5: =SUM(B9:B196) -> 553 | G5: =SUM(E9:E196) -> 30096 | J5: =SUM(F9:F196) -> 55
A8: CLUSTER NAME | B8: FARMERS MANAGED | C8: MAIZE HA 2026/27 | D8: SORGHUM HA 2026/27 | E8: TOTAL PIPELINE HA | F8: PAID FARMERS | G8: UNPAID | H8: PAYMENT % | I8: PROVINCE | J8: DISTRICT | K8: CLUSTER CONTACT | L8: CONTACT DETAILS | M8: EXPECTED SUBSCRIPTIONS | N8: AMOUNT PAID
A9: BATSIRAYI MAGAYA | B9: =COUNTIF(DATA_PIPELINE!$D$5:$D$603,A9) -> 29 | C9: =SUMIF(DATA_PIPELINE!$D$5:$D$603,A9,DATA_PIPELINE!$M$5:$M$603) -> 70 | D9: =SUMIF(DATA_PIPELINE!$D$5:$D$603,A9,DATA_PIPELINE!$N$5:$N$603) -> 610 | E9: =C9+D9 -> 680 | F9: {=SUM(COUNTIFS(DATA_PIPELINE!$D$5:$D$603,A9,DATA_PIPELINE!$Y$5:$Y$603,{"Paid","Partly Paid"}))} -> 3 | G9: =B9-F9 -> 26 | H9: =IFERROR(F9/B9,0) -> 0.10344828 | I9: =IFERROR(_xlfn.single(_xlfn.xlookup(A9, DATA_PIPELINE!$D$5:$D$603, DATA_PIPELINE!$H$5:$H$603, "")), "") -> MASHWEST | J9: =IFERROR(_xlfn.single(_xlfn.xlookup(A9, DATA_PIPELINE!$D$5:$D$603, DATA_PIPELINE!$G$5:$G$603, "")), "") -> MAKONDE | K9: ='CLUSTER PERFORMANCE'!$A9 -> BATSIRAYI MAGAYA | L9: 0774798096 | M9: =SUMIF(DATA_PIPELINE!$D$5:$D$603,A9,DATA_PIPELINE!$V$5:$V$603) -> 14500 | N9: =SUMIF(DATA_PIPELINE!$D$5:$D$603,A9,DATA_PIPELINE!$W$5:$W$603) -> 650
A10: BETTY ZUNGUNDE | B10: =COUNTIF(DATA_PIPELINE!$D$5:$D$603,A10) -> 15 | C10: =SUMIF(DATA_PIPELINE!$D$5:$D$603,A10,DATA_PIPELINE!$M$5:$M$603) -> 10 | D10: =SUMIF(DATA_PIPELINE!$D$5:$D$603,A10,DATA_PIPELINE!$N$5:$N$603) -> 575 | E10: =C10+D10 -> 585 | F10: {=SUM(COUNTIFS(DATA_PIPELINE!$D$5:$D$603,A10,DATA_PIPELINE!$Y$5:$Y$603,{"Paid","Partly Paid"}))} -> 1 | G10: =B10-F10 -> 14 | H10: =IFERROR(F10/B10,0) -> 0.066666667 | I10: =IFERROR(_xlfn.single(_xlfn.xlookup(A10, DATA_PIPELINE!$D$5:$D$603, DATA_PIPELINE!$H$5:$H$603, "")), "") -> MASHWEST | J10: =IFERROR(_xlfn.single(_xlfn.xlookup(A10, DATA_PIPELINE!$D$5:$D$603, DATA_PIPELINE!$G$5:$G$603, "")), "") -> CHEGUTU | K10: ='CLUSTER PERFORMANCE'!$A10 -> BETTY ZUNGUNDE | L10: 0773868322 | M10: =SUMIF(DATA_PIPELINE!$D$5:$D$603,A10,DATA_PIPELINE!$V$5:$V$603) -> 7500 | N10: =SUMIF(DATA_PIPELINE!$D$5:$D$603,A10,DATA_PIPELINE!$W$5:$W$603) -> 50
A11: BLESSING CHIWERA | B11: =COUNTIF(DATA_PIPELINE!$D$5:$D$603,A11) -> 11 | C11: =SUMIF(DATA_PIPELINE!$D$5:$D$603,A11,DATA_PIPELINE!$M$5:$M$603) -> 2605 | D11: =SUMIF(DATA_PIPELINE!$D$5:$D$603,A11,DATA_PIPELINE!$N$5:$N$603) -> 0 | E11: =C11+D11 -> 2605 | F11: {=SUM(COUNTIFS(DATA_PIPELINE!$D$5:$D$603,A11,DATA_PIPELINE!$Y$5:$Y$603,{"Paid","Partly Paid"}))} -> 0 | G11: =B11-F11 -> 11 | H11: =IFERROR(F11/B11,0) -> 0 | I11: =IFERROR(_xlfn.single(_xlfn.xlookup(A11, DATA_PIPELINE!$D$5:$D$603, DATA_PIPELINE!$H$5:$H$603, "")), "") -> MASHWEST | J11: =IFERROR(_xlfn.single(_xlfn.xlookup(A11, DATA_PIPELINE!$D$5:$D$603, DATA_PIPELINE!$G$5:$G$603, "")), "") -> NK | K11: ='CLUSTER PERFORMANCE'!$A11 -> BLESSING CHIWERA | L11: 0772714503 | M11: =SUMIF(DATA_PIPELINE!$D$5:$D$603,A11,DATA_PIPELINE!$V$5:$V$603) -> 6500 | N11: =SUMIF(DATA_PIPELINE!$D$5:$D$603,A11,DATA_PIPELINE!$W$5:$W$603) -> 0
A12: BRIAN CHIDAVAENZI | B12: =COUNTIF(DATA_PIPELINE!$D$5:$D$603,A12) -> 18 | C12: =SUMIF(DATA_PIPELINE!$D$5:$D$603,A12,DATA_PIPELINE!$M$5:$M$603) -> 10 | D12: =SUMIF(DATA_PIPELINE!$D$5:$D$603,A12,DATA_PIPELINE!$N$5:$N$603) -> 1070 | E12: =C12+D12 -> 1080 | F12: {=SUM(COUNTIFS(DATA_PIPELINE!$D$5:$D$603,A12,DATA_PIPELINE!$Y$5:$Y$603,{"Paid","Partly Paid"}))} -> 0 | G12: =B12-F12 -> 18 | H12: =IFERROR(F12/B12,0) -> 0 | I12: =IFERROR(_xlfn.single(_xlfn.xlookup(A12, DATA_PIPELINE!$D$5:$D$603, DATA_PIPELINE!$H$5:$H$603, "")), "") -> MASHWEST | J12: =IFERROR(_xlfn.single(_xlfn.xlookup(A12, DATA_PIPELINE!$D$5:$D$603, DATA_PIPELINE!$G$5:$G$603, "")), "") -> HURUNGWE | K12: ='CLUSTER PERFORMANCE'!$A12 -> BRIAN CHIDAVAENZI | L12: 0774346142 | M12: =SUMIF(DATA_PIPELINE!$D$5:$D$603,A12,DATA_PIPELINE!$V$5:$V$603) -> 10500 | N12: =SUMIF(DATA_PIPELINE!$D$5:$D$603,A12,DATA_PIPELINE!$W$5:$W$603) -> 0
A13: COMMENT TONDERAYI MUTARA | B13: =COUNTIF(DATA_PIPELINE!$D$5:$D$603,A13) -> 64 | C13: =SUMIF(DATA_PIPELINE!$D$5:$D$603,A13,DATA_PIPELINE!$M$5:$M$603) -> 252 | D13: =SUMIF(DATA_PIPELINE!$D$5:$D$603,A13,DATA_PIPELINE!$N$5:$N$603) -> 2549 | E13: =C13+D13 -> 2801 | F13: {=SUM(COUNTIFS(DATA_PIPELINE!$D$5:$D$603,A13,DATA_PIPELINE!$Y$5:$Y$603,{"Paid","Partly Paid"}))} -> 8 | G13: =B13-F13 -> 56 | H13: =IFERROR(F13/B13,0) -> 0.125 | I13: =IFERROR(_xlfn.single(_xlfn.xlookup(A13, DATA_PIPELINE!$D$5:$D$603, DATA_PIPELINE!$H$5:$H$603, "")), "") -> MASHWEST | J13: =IFERROR(_xlfn.single(_xlfn.xlookup(A13, DATA_PIPELINE!$D$5:$D$603, DATA_PIPELINE!$G$5:$G$603, "")), "") -> HURUNGWE | K13: ='CLUSTER PERFORMANCE'!$A13 -> COMMENT TONDERAYI MUTARA | L13: 0774117214 | M13: =SUMIF(DATA_PIPELINE!$D$5:$D$603,A13,DATA_PIPELINE!$V$5:$V$603) -> 32500 | N13: =SUMIF(DATA_PIPELINE!$D$5:$D$603,A13,DATA_PIPELINE!$W$5:$W$603) -> 2800
A14: DANMORE MUDAVANHU | B14: =COUNTIF(DATA_PIPELINE!$D$5:$D$603,A14) -> 35 | C14: =SUMIF(DATA_PIPELINE!$D$5:$D$603,A14,DATA_PIPELINE!$M$5:$M$603) -> 1086 | D14: =SUMIF(DATA_PIPELINE!$D$5:$D$603,A14,DATA_PIPELINE!$N$5:$N$603) -> 1213 | E14: =C14+D14 -> 2299 | F14: {=SUM(COUNTIFS(DATA_PIPELINE!$D$5:$D$603,A14,DATA_PIPELINE!$Y$5:$Y$603,{"Paid","Partly Paid"}))} -> 1 | G14: =B14-F14 -> 34 | H14: =IFERROR(F14/B14,0) -> 0.028571429 | I14: =IFERROR(_xlfn.single(_xlfn.xlookup(A14, DATA_PIPELINE!$D$5:$D$603, DATA_PIPELINE!$H$5:$H$603, "")), "") -> MASHWEST | J14: =IFERROR(_xlfn.single(_xlfn.xlookup(A14, DATA_PIPELINE!$D$5:$D$603, DATA_PIPELINE!$G$5:$G$603, "")), "") -> CHEGUTU | K14: ='CLUSTER PERFORMANCE'!$A14 -> DANMORE MUDAVANHU | L14: 0772960915 | M14: =SUMIF(DATA_PIPELINE!$D$5:$D$603,A14,DATA_PIPELINE!$V$5:$V$603) -> 18000 | N14: =SUMIF(DATA_PIPELINE!$D$5:$D$603,A14,DATA_PIPELINE!$W$5:$W$603) -> 100
A15: JAMES MASANGO | B15: =COUNTIF(DATA_PIPELINE!$D$5:$D$603,A15) -> 4 | C15: =SUMIF(DATA_PIPELINE!$D$5:$D$603,A15,DATA_PIPELINE!$M$5:$M$603) -> 0 | D15: =SUMIF(DATA_PIPELINE!$D$5:$D$603,A15,DATA_PIPELINE!$N$5:$N$603) -> 95 | E15: =C15+D15 -> 95 | F15: {=SUM(COUNTIFS(DATA_PIPELINE!$D$5:$D$603,A15,DATA_PIPELINE!$Y$5:$Y$603,{"Paid","Partly Paid"}))} -> 1 | G15: =B15-F15 -> 3 | H15: =IFERROR(F15/B15,0) -> 0.25 | I15: =IFERROR(_xlfn.single(_xlfn.xlookup(A15, DATA_PIPELINE!$D$5:$D$603, DATA_PIPELINE!$H$5:$H$603, "")), "") -> MASHWEST | J15: =IFERROR(_xlfn.single(_xlfn.xlookup(A15, DATA_PIPELINE!$D$5:$D$603, DATA_PIPELINE!$G$5:$G$603, "")), "") -> MAKONDE | K15: ='CLUSTER PERFORMANCE'!$A15 -> JAMES MASANGO | L15: 0772854734 | M15: =SUMIF(DATA_PIPELINE!$D$5:$D$603,A15,DATA_PIPELINE!$V$5:$V$603) -> 2000 | N15: =SUMIF(DATA_PIPELINE!$D$5:$D$603,A15,DATA_PIPELINE!$W$5:$W$603) -> 50
A16: LIBERTY MASHURA | B16: =COUNTIF(DATA_PIPELINE!$D$5:$D$603,A16) -> 1 | C16: =SUMIF(DATA_PIPELINE!$D$5:$D$603,A16,DATA_PIPELINE!$M$5:$M$603) -> 50 | D16: =SUMIF(DATA_PIPELINE!$D$5:$D$603,A16,DATA_PIPELINE!$N$5:$N$603) -> 0 | E16: =C16+D16 -> 50 | F16: {=SUM(COUNTIFS(DATA_PIPELINE!$D$5:$D$603,A16,DATA_PIPELINE!$Y$5:$Y$603,{"Paid","Partly Paid"}))} -> 0 | G16: =B16-F16 -> 1 | H16: =IFERROR(F16/B16,0) -> 0 | I16: =IFERROR(_xlfn.single(_xlfn.xlookup(A16, DATA_PIPELINE!$D$5:$D$603, DATA_PIPELINE!$H$5:$H$603, "")), "") -> MIDLADS | J16: =IFERROR(_xlfn.single(_xlfn.xlookup(A16, DATA_PIPELINE!$D$5:$D$603, DATA_PIPELINE!$G$5:$G$603, "")), "") | K16: ='CLUSTER PERFORMANCE'!$A16 -> LIBERTY MASHURA | L16: 0773650650 | M16: =SUMIF(DATA_PIPELINE!$D$5:$D$603,A16,DATA_PIPELINE!$V$5:$V$603) -> 500 | N16: =SUMIF(DATA_PIPELINE!$D$5:$D$603,A16,DATA_PIPELINE!$W$5:$W$603) -> 0
A17: MISHECK PARADZANWA | B17: =COUNTIF(DATA_PIPELINE!$D$5:$D$603,A17) -> 23 | C17: =SUMIF(DATA_PIPELINE!$D$5:$D$603,A17,DATA_PIPELINE!$M$5:$M$603) -> 420 | D17: =SUMIF(DATA_PIPELINE!$D$5:$D$603,A17,DATA_PIPELINE!$N$5:$N$603) -> 790 | E17: =C17+D17 -> 1210 | F17: {=SUM(COUNTIFS(DATA_PIPELINE!$D$5:$D$603,A17,DATA_PIPELINE!$Y$5:$Y$603,{"Paid","Partly Paid"}))} -> 5 | G17: =B17-F17 -> 18 | H17: =IFERROR(F17/B17,0) -> 0.2173913 | I17: =IFERROR(_xlfn.single(_xlfn.xlookup(A17, DATA_PIPELINE!$D$5:$D$603, DATA_PIPELINE!$H$5:$H$603, "")), "") -> MASHWEST | J17: =IFERROR(_xlfn.single(_xlfn.xlookup(A17, DATA_PIPELINE!$D$5:$D$603, DATA_PIPELINE!$G$5:$G$603, "")), "") -> MAKONDE | K17: ='CLUSTER PERFORMANCE'!$A17 -> MISHECK PARADZANWA | L17: 0772587456 | M17: =SUMIF(DATA_PIPELINE!$D$5:$D$603,A17,DATA_PIPELINE!$V$5:$V$603) -> 12500 | N17: =SUMIF(DATA_PIPELINE!$D$5:$D$603,A17,DATA_PIPELINE!$W$5:$W$603) -> 350
A18: MOFFAT SEFU | B18: =COUNTIF(DATA_PIPELINE!$D$5:$D$603,A18) -> 77 | C18: =SUMIF(DATA_PIPELINE!$D$5:$D$603,A18,DATA_PIPELINE!$M$5:$M$603) -> 281 | D18: =SUMIF(DATA_PIPELINE!$D$5:$D$603,A18,DATA_PIPELINE!$N$5:$N$603) -> 1875 | E18: =C18+D18 -> 2156 | F18: {=SUM(COUNTIFS(DATA_PIPELINE!$D$5:$D$603,A18,DATA_PIPELINE!$Y$5:$Y$603,{"Paid","Partly Paid"}))} -> 14 | G18: =B18-F18 -> 63 | H18: =IFERROR(F18/B18,0) -> 0.18181818 | I18: =IFERROR(_xlfn.single(_xlfn.xlookup(A18, DATA_PIPELINE!$D$5:$D$603, DATA_PIPELINE!$H$5:$H$603, "")), "") -> MASHWEST | J18: =IFERROR(_xlfn.single(_xlfn.xlookup(A18, DATA_PIPELINE!$D$5:$D$603, DATA_PIPELINE!$G$5:$G$603, "")), "") -> MAKONDE | K18: ='CLUSTER PERFORMANCE'!$A18 -> MOFFAT SEFU | L18: 0772927647 | M18: =SUMIF(DATA_PIPELINE!$D$5:$D$603,A18,DATA_PIPELINE!$V$5:$V$603) -> 39000 | N18: =SUMIF(DATA_PIPELINE!$D$5:$D$603,A18,DATA_PIPELINE!$W$5:$W$603) -> 2175
A19: MOHADI | B19: =COUNTIF(DATA_PIPELINE!$D$5:$D$603,A19) -> 2 | C19: =SUMIF(DATA_PIPELINE!$D$5:$D$603,A19,DATA_PIPELINE!$M$5:$M$603) -> 400 | D19: =SUMIF(DATA_PIPELINE!$D$5:$D$603,A19,DATA_PIPELINE!$N$5:$N$603) -> 0 | E19: =C19+D19 -> 400 | F19: {=SUM(COUNTIFS(DATA_PIPELINE!$D$5:$D$603,A19,DATA_PIPELINE!$Y$5:$Y$603,{"Paid","Partly Paid"}))} -> 0 | G19: =B19-F19 -> 2 | H19: =IFERROR(F19/B19,0) -> 0 | I19: =IFERROR(_xlfn.single(_xlfn.xlookup(A19, DATA_PIPELINE!$D$5:$D$603, DATA_PIPELINE!$H$5:$H$603, "")), "") -> MATABELELAND SOUTH | J19: =IFERROR(_xlfn.single(_xlfn.xlookup(A19, DATA_PIPELINE!$D$5:$D$603, DATA_PIPELINE!$G$5:$G$603, "")), "") | K19: ='CLUSTER PERFORMANCE'!$A19 -> MOHADI | M19: =SUMIF(DATA_PIPELINE!$D$5:$D$603,A19,DATA_PIPELINE!$V$5:$V$603) -> 2000 | N19: =SUMIF(DATA_PIPELINE!$D$5:$D$603,A19,DATA_PIPELINE!$W$5:$W$603) -> 0
A20: TAFADZWA MUSIIWA | B20: =COUNTIF(DATA_PIPELINE!$D$5:$D$603,A20) -> 12 | C20: =SUMIF(DATA_PIPELINE!$D$5:$D$603,A20,DATA_PIPELINE!$M$5:$M$603) -> 100 | D20: =SUMIF(DATA_PIPELINE!$D$5:$D$603,A20,DATA_PIPELINE!$N$5:$N$603) -> 230 | E20: =C20+D20 -> 330 | F20: {=SUM(COUNTIFS(DATA_PIPELINE!$D$5:$D$603,A20,DATA_PIPELINE!$Y$5:$Y$603,{"Paid","Partly Paid"}))} -> 0 | G20: =B20-F20 -> 12 | H20: =IFERROR(F20/B20,0) -> 0 | I20: =IFERROR(_xlfn.single(_xlfn.xlookup(A20, DATA_PIPELINE!$D$5:$D$603, DATA_PIPELINE!$H$5:$H$603, "")), "") -> MASHWEST | J20: =IFERROR(_xlfn.single(_xlfn.xlookup(A20, DATA_PIPELINE!$D$5:$D$603, DATA_PIPELINE!$G$5:$G$603, "")), "") -> MAKONDE | K20: ='CLUSTER PERFORMANCE'!$A20 -> TAFADZWA MUSIIWA | L20: 0776511877 | M20: =SUMIF(DATA_PIPELINE!$D$5:$D$603,A20,DATA_PIPELINE!$V$5:$V$603) -> 6000 | N20: =SUMIF(DATA_PIPELINE!$D$5:$D$603,A20,DATA_PIPELINE!$W$5:$W$603) -> 0
A21: PHIBEON MUTIBURA | B21: =COUNTIF(DATA_PIPELINE!$D$5:$D$603,A21) -> 20 | C21: =SUMIF(DATA_PIPELINE!$D$5:$D$603,A21,DATA_PIPELINE!$M$5:$M$603) -> 280 | D21: =SUMIF(DATA_PIPELINE!$D$5:$D$603,A21,DATA_PIPELINE!$N$5:$N$603) -> 1360 | E21: =C21+D21 -> 1640 | F21: {=SUM(COUNTIFS(DATA_PIPELINE!$D$5:$D$603,A21,DATA_PIPELINE!$Y$5:$Y$603,{"Paid","Partly Paid"}))} -> 2 | G21: =B21-F21 -> 18 | H21: =IFERROR(F21/B21,0) -> 0.1 | I21: =IFERROR(_xlfn.single(_xlfn.xlookup(A21, DATA_PIPELINE!$D$5:$D$603, DATA_PIPELINE!$H$5:$H$603, "")), "") -> MASHCENTRAL | J21: =IFERROR(_xlfn.single(_xlfn.xlookup(A21, DATA_PIPELINE!$D$5:$D$603, DATA_PIPELINE!$G$5:$G$603, "")), "") -> GOROMONZI | K21: ='CLUSTER PERFORMANCE'!$A21 -> PHIBEON MUTIBURA | L21: 0788360239 | M21: =SUMIF(DATA_PIPELINE!$D$5:$D$603,A21,DATA_PIPELINE!$V$5:$V$603) -> 10500 | N21: =SUMIF(DATA_PIPELINE!$D$5:$D$603,A21,DATA_PIPELINE!$W$5:$W$603) -> 1500
A22: RICHARD JENAMI | B22: =COUNTIF(DATA_PIPELINE!$D$5:$D$603,A22) -> 31 | C22: =SUMIF(DATA_PIPELINE!$D$5:$D$603,A22,DATA_PIPELINE!$M$5:$M$603) -> 2050 | D22: =SUMIF(DATA_PIPELINE!$D$5:$D$603,A22,DATA_PIPELINE!$N$5:$N$603) -> 1325 | E22: =C22+D22 -> 3375 | F22: {=SUM(COUNTIFS(DATA_PIPELINE!$D$5:$D$603,A22,DATA_PIPELINE!$Y$5:$Y$603,{"Paid","Partly Paid"}))} -> 2 | G22: =B22-F22 -> 29 | H22: =IFERROR(F22/B22,0) -> 0.064516129 | I22: =IFERROR(_xlfn.single(_xlfn.xlookup(A22, DATA_PIPELINE!$D$5:$D$603, DATA_PIPELINE!$H$5:$H$603, "")), "") -> MASHWEST | J22: =IFERROR(_xlfn.single(_xlfn.xlookup(A22, DATA_PIPELINE!$D$5:$D$603, DATA_PIPELINE!$G$5:$G$603, "")), "") -> MAKONDE | K22: ='CLUSTER PERFORMANCE'!$A22 -> RICHARD JENAMI | L22: 0771528938 | M22: =SUMIF(DATA_PIPELINE!$D$5:$D$603,A22,DATA_PIPELINE!$V$5:$V$603) -> 16000 | N22: =SUMIF(DATA_PIPELINE!$D$5:$D$603,A22,DATA_PIPELINE!$W$5:$W$603) -> 700
A23: TAFADZWA NHUNDU | B23: =COUNTIF(DATA_PIPELINE!$D$5:$D$603,A23) -> 4 | C23: =SUMIF(DATA_PIPELINE!$D$5:$D$603,A23,DATA_PIPELINE!$M$5:$M$603) -> 130 | D23: =SUMIF(DATA_PIPELINE!$D$5:$D$603,A23,DATA_PIPELINE!$N$5:$N$603) -> 30 | E23: =C23+D23 -> 160 | F23: {=SUM(COUNTIFS(DATA_PIPELINE!$D$5:$D$603,A23,DATA_PIPELINE!$Y$5:$Y$603,{"Paid","Partly Paid"}))} -> 1 | G23: =B23-F23 -> 3 | H23: =IFERROR(F23/B23,0) -> 0.25 | I23: =IFERROR(_xlfn.single(_xlfn.xlookup(A23, DATA_PIPELINE!$D$5:$D$603, DATA_PIPELINE!$H$5:$H$603, "")), "") -> MASHEAST | J23: =IFERROR(_xlfn.single(_xlfn.xlookup(A23, DATA_PIPELINE!$D$5:$D$603, DATA_PIPELINE!$G$5:$G$603, "")), "") | K23: ='CLUSTER PERFORMANCE'!$A23 -> TAFADZWA NHUNDU | L23: 0717589019 | M23: =SUMIF(DATA_PIPELINE!$D$5:$D$603,A23,DATA_PIPELINE!$V$5:$V$603) -> 2000 | N23: =SUMIF(DATA_PIPELINE!$D$5:$D$603,A23,DATA_PIPELINE!$W$5:$W$603) -> 500
A24: TAKUNDA NHEMA | B24: =COUNTIF(DATA_PIPELINE!$D$5:$D$603,A24) -> 15 | C24: =SUMIF(DATA_PIPELINE!$D$5:$D$603,A24,DATA_PIPELINE!$M$5:$M$603) -> 100 | D24: =SUMIF(DATA_PIPELINE!$D$5:$D$603,A24,DATA_PIPELINE!$N$5:$N$603) -> 1895 | E24: =C24+D24 -> 1995 | F24: {=SUM(COUNTIFS(DATA_PIPELINE!$D$5:$D$603,A24,DATA_PIPELINE!$Y$5:$Y$603,{"Paid","Partly Paid"}))} -> 2 | G24: =B24-F24 -> 13 | H24: =IFERROR(F24/B24,0) -> 0.13333333 | I24: =IFERROR(_xlfn.single(_xlfn.xlookup(A24, DATA_PIPELINE!$D$5:$D$603, DATA_PIPELINE!$H$5:$H$603, "")), "") -> MASHWEST | J24: =IFERROR(_xlfn.single(_xlfn.xlookup(A24, DATA_PIPELINE!$D$5:$D$603, DATA_PIPELINE!$G$5:$G$603, "")), "") -> HURUNGWE | K24: ='CLUSTER PERFORMANCE'!$A24 -> TAKUNDA NHEMA | L24: 0772399882 | M24: =SUMIF(DATA_PIPELINE!$D$5:$D$603,A24,DATA_PIPELINE!$V$5:$V$603) -> 9000 | N24: =SUMIF(DATA_PIPELINE!$D$5:$D$603,A24,DATA_PIPELINE!$W$5:$W$603) -> 1200
A25: THEMBEKILE GATA | B25: =COUNTIF(DATA_PIPELINE!$D$5:$D$603,A25) -> 17 | C25: =SUMIF(DATA_PIPELINE!$D$5:$D$603,A25,DATA_PIPELINE!$M$5:$M$603) -> 66 | D25: =SUMIF(DATA_PIPELINE!$D$5:$D$603,A25,DATA_PIPELINE!$N$5:$N$603) -> 380 | E25: =C25+D25 -> 446 | F25: {=SUM(COUNTIFS(DATA_PIPELINE!$D$5:$D$603,A25,DATA_PIPELINE!$Y$5:$Y$603,{"Paid","Partly Paid"}))} -> 1 | G25: =B25-F25 -> 16 | H25: =IFERROR(F25/B25,0) -> 0.058823529 | I25: =IFERROR(_xlfn.single(_xlfn.xlookup(A25, DATA_PIPELINE!$D$5:$D$603, DATA_PIPELINE!$H$5:$H$603, "")), "") -> MASHWEST | J25: =IFERROR(_xlfn.single(_xlfn.xlookup(A25, DATA_PIPELINE!$D$5:$D$603, DATA_PIPELINE!$G$5:$G$603, "")), "") -> MAKONDE | K25: ='CLUSTER PERFORMANCE'!$A25 -> THEMBEKILE GATA | L25: 0776607775 | M25: =SUMIF(DATA_PIPELINE!$D$5:$D$603,A25,DATA_PIPELINE!$V$5:$V$603) -> 8500 | N25: =SUMIF(DATA_PIPELINE!$D$5:$D$603,A25,DATA_PIPELINE!$W$5:$W$603) -> 100
A26: TINASHE CHIKONDOWA | B26: =COUNTIF(DATA_PIPELINE!$D$5:$D$603,A26) -> 34 | C26: =SUMIF(DATA_PIPELINE!$D$5:$D$603,A26,DATA_PIPELINE!$M$5:$M$603) -> 0 | D26: =SUMIF(DATA_PIPELINE!$D$5:$D$603,A26,DATA_PIPELINE!$N$5:$N$603) -> 396 | E26: =C26+D26 -> 396 | F26: {=SUM(COUNTIFS(DATA_PIPELINE!$D$5:$D$603,A26,DATA_PIPELINE!$Y$5:$Y$603,{"Paid","Partly Paid"}))} -> 1 | G26: =B26-F26 -> 33 | H26: =IFERROR(F26/B26,0) -> 0.029411765 | I26: =IFERROR(_xlfn.single(_xlfn.xlookup(A26, DATA_PIPELINE!$D$5:$D$603, DATA_PIPELINE!$H$5:$H$603, "")), "") -> MASHWEST | J26: =IFERROR(_xlfn.single(_xlfn.xlookup(A26, DATA_PIPELINE!$D$5:$D$603, DATA_PIPELINE!$G$5:$G$603, "")), "") -> MAKONDE | K26: ='CLUSTER PERFORMANCE'!$A26 -> TINASHE CHIKONDOWA | L26: 0719976172 | M26: =SUMIF(DATA_PIPELINE!$D$5:$D$603,A26,DATA_PIPELINE!$V$5:$V$603) -> 17000 | N26: =SUMIF(DATA_PIPELINE!$D$5:$D$603,A26,DATA_PIPELINE!$W$5:$W$603) -> 500
A27: WALTER MASHINGAIDZE | B27: =COUNTIF(DATA_PIPELINE!$D$5:$D$603,A27) -> 139 | C27: =SUMIF(DATA_PIPELINE!$D$5:$D$603,A27,DATA_PIPELINE!$M$5:$M$603) -> 2080 | D27: =SUMIF(DATA_PIPELINE!$D$5:$D$603,A27,DATA_PIPELINE!$N$5:$N$603) -> 5613 | E27: =C27+D27 -> 7693 | F27: {=SUM(COUNTIFS(DATA_PIPELINE!$D$5:$D$603,A27,DATA_PIPELINE!$Y$5:$Y$603,{"Paid","Partly Paid"}))} -> 12 | G27: =B27-F27 -> 127 | H27: =IFERROR(F27/B27,0) -> 0.086330935 | I27: =IFERROR(_xlfn.single(_xlfn.xlookup(A27, DATA_PIPELINE!$D$5:$D$603, DATA_PIPELINE!$H$5:$H$603, "")), "") -> MASHWEST | J27: =IFERROR(_xlfn.single(_xlfn.xlookup(A27, DATA_PIPELINE!$D$5:$D$603, DATA_PIPELINE!$G$5:$G$603, "")), "") -> ZVIMBA | K27: ='CLUSTER PERFORMANCE'!$A27 -> WALTER MASHINGAIDZE | L27: 0772333363 | M27: =SUMIF(DATA_PIPELINE!$D$5:$D$603,A27,DATA_PIPELINE!$V$5:$V$603) -> 72000 | N27: =SUMIF(DATA_PIPELINE!$D$5:$D$603,A27,DATA_PIPELINE!$W$5:$W$603) -> 5500
A28: WILSON MUGANDA | B28: =COUNTIF(DATA_PIPELINE!$D$5:$D$603,A28) -> 2 | C28: =SUMIF(DATA_PIPELINE!$D$5:$D$603,A28,DATA_PIPELINE!$M$5:$M$603) -> 100 | D28: =SUMIF(DATA_PIPELINE!$D$5:$D$603,A28,DATA_PIPELINE!$N$5:$N$603) -> 0 | E28: =C28+D28 -> 100 | F28: {=SUM(COUNTIFS(DATA_PIPELINE!$D$5:$D$603,A28,DATA_PIPELINE!$Y$5:$Y$603,{"Paid","Partly Paid"}))} -> 1 | G28: =B28-F28 -> 1 | H28: =IFERROR(F28/B28,0) -> 0.5 | I28: =IFERROR(_xlfn.single(_xlfn.xlookup(A28, DATA_PIPELINE!$D$5:$D$603, DATA_PIPELINE!$H$5:$H$603, "")), "") -> MANICALAND | J28: =IFERROR(_xlfn.single(_xlfn.xlookup(A28, DATA_PIPELINE!$D$5:$D$603, DATA_PIPELINE!$G$5:$G$603, "")), "") | K28: ='CLUSTER PERFORMANCE'!$A28 -> WILSON MUGANDA | L28: 0772690124 | M28: =SUMIF(DATA_PIPELINE!$D$5:$D$603,A28,DATA_PIPELINE!$V$5:$V$603) -> 1500 | N28: =SUMIF(DATA_PIPELINE!$D$5:$D$603,A28,DATA_PIPELINE!$W$5:$W$603) -> 1000

Sheet DATA_BANK
A1: DATA BANK
A2: Imported source snapshot — update this table when source workbooks change.
A3: =HYPERLINK("#'HOME'!A1","HOME") -> HOME | B3: =HYPERLINK("#'FARMERS'!A1","FARMERS") -> FARMERS | C3: =HYPERLINK("#'SUBSCRIPTIONS'!A1","SUBSCRIPTIONS") -> SUBSCRIPTIONS | D3: =HYPERLINK("#'PRODUCTION'!A1","PRODUCTION") -> PRODUCTION | E3: =HYPERLINK("#'RECOVERY'!A1","RECOVERY") -> RECOVERY | F3: =HYPERLINK("#'DELIVERIES'!A1","DELIVERIES") -> DELIVERIES | G3: =HYPERLINK("#'FINANCE'!A1","FINANCE") -> FINANCE | H3: =HYPERLINK("#'REPORTS'!A1","REPORTS") -> REPORTS
A5: MONTH | B5: OPENING BALANCE | C5: RECEIPTS / BANK DEPOSITS | D5: EXPENSES / PAYMENTS | E5: CLOSING BALANCE | F5: SOURCE / CHECK | G5: DIFFERENCE | H5: STATUS
A6: November 2025 | B6: 0 | C6: =SUMIFS(DATA_RECEIPTS!E:E, DATA_RECEIPTS!A:A, ">=2025-11-01", DATA_RECEIPTS!A:A, "<2025-12-01") -> 7500 | D6: =SUMIFS(DATA_EXPENSES!E:E, DATA_EXPENSES!A:A, ">=2025-11-01", DATA_EXPENSES!A:A, "<2025-12-01") -> 7159.5 | E6: =DATA_BANK!$C6-DATA_BANK!$D6 -> 340.5 | F6: Source expense book closing balance | G6: 0 | H6: RECONCILED
A7: June 2026 | B7: =E6 -> 340.5 | C7: =SUMIFS(DATA_RECEIPTS!E:E, DATA_RECEIPTS!A:A, ">=2026-06-01", DATA_RECEIPTS!A:A, "<2026-07-01") -> 700 | D7: =SUMIFS(DATA_EXPENSES!E:E, DATA_EXPENSES!A:A, ">=2026-06-01", DATA_EXPENSES!A:A, "<2026-07-01") -> 1300 | E7: =DATA_BANK!$B7+DATA_BANK!$C7-DATA_BANK!$D7 -> -259.5 | F7: Source expense book bank balance | G7: 0 | H7: RECONCILED
A8: July 2026 | B8: =E7 -> -259.5 | C8: =SUMIFS(DATA_RECEIPTS!E:E, DATA_RECEIPTS!A:A, ">=2026-07-01", DATA_RECEIPTS!A:A, "<2026-08-01") -> 1600 | D8: =SUMIFS(DATA_EXPENSES!E:E, DATA_EXPENSES!A:A, ">=2026-07-01", DATA_EXPENSES!A:A, "<2026-08-01") -> 1832.98 | E8: =DATA_BANK!$B8+DATA_BANK!$C8-DATA_BANK!$D8 -> -492.48 | F8: Source expense book bank balance | G8: 0 | H8: RECONCILED
A9: August 2026 | B9: =E8 -> -492.48 | C9: =SUMIFS(DATA_RECEIPTS!E:E, DATA_RECEIPTS!A:A, ">=2026-08-01", DATA_RECEIPTS!A:A, "<2026-09-01") -> 4850 | D9: =SUMIFS(DATA_EXPENSES!E:E, DATA_EXPENSES!A:A, ">=2026-08-01", DATA_EXPENSES!A:A, "<2026-09-01") -> 2491.31 | E9: =DATA_BANK!$B9+DATA_BANK!$C9-DATA_BANK!$D9 -> 1866.21 | F9: Source expense book bank balance | G9: 0 | H9: RECONCILED
A10: September | B10: =E9 -> 1866.21 | C10: =SUMIFS(DATA_RECEIPTS!E:E, DATA_RECEIPTS!A:A, ">=2026-09-01", DATA_RECEIPTS!A:A, "<2026-10-01") -> 2725 | D10: =SUMIFS(DATA_EXPENSES!E:E, DATA_EXPENSES!A:A, ">=2026-09-01", DATA_EXPENSES!A:A, "<2026-10-01") -> 466.09 | E10: =DATA_BANK!$B10+DATA_BANK!$C10-DATA_BANK!$D10 -> 4125.12 | F10: Source expense book bank balance | G10: 0 | H10: RECONCILED

Sheet SALARY SCHEDULE
A1: SGR SALARY & ALLOWANCES SCHEDULE
A2: Employee payroll planning schedule covering monthly salary, allowances and annual employment cost.
A4: =HYPERLINK("#'HOME'!A1","HOME") -> HOME | B4: =HYPERLINK("#'FINANCE'!A1","FINANCE") -> FINANCE | C4: =HYPERLINK("#'REPORTS'!A1","REPORTS") -> REPORTS | D4: =HYPERLINK("#'PRODUCTION'!A1","PRODUCTION") -> PRODUCTION | E4: =HYPERLINK("#'SORGHUM BUDGET'!A1","SORGHUM BUDGET") -> SORGHUM BUDGET | F4: =HYPERLINK("#'MAIZE BUDGET'!A1","MAIZE BUDGET") -> MAIZE BUDGET
A6: Employee ID | B6: Employee / Position | C6: Department | D6: Basic Salary / Month (USD) | E6: Housing Allowance / Month | F6: Transport Allowance / Month | G6: Other Allowance / Month | H6: Total Monthly Cost (USD) | I6: Annual Salary Cost (USD) | J6: Annual Total Employment Cost (USD)
A7: ADMIN01 | B7: SENIOR ADMINSTRATOR | C7: FINANCE | D7: 850 | G7: 0 | H7: =IF(D7="","",SUM(D7:G7)) -> 850 | I7: =IF(D7="","",D7*12) -> 10200 | J7: =IF(H7="","",H7*12) -> 10200
A8: AT01 | B8: INTERN | C8: FINANCE | D8: 100 | H8: =IF(D8="","",SUM(D8:G8)) -> 100 | I8: =IF(D8="","",D8*12) -> 1200 | J8: =IF(H8="","",H8*12) -> 1200
H9: =IF(D9="","",SUM(D9:G9)) | I9: =IF(D9="","",D9*12) | J9: =IF(H9="","",H9*12)
H10: =IF(D10="","",SUM(D10:G10)) | I10: =IF(D10="","",D10*12) | J10: =IF(H10="","",H10*12)
H11: =IF(D11="","",SUM(D11:G11)) | I11: =IF(D11="","",D11*12) | J11: =IF(H11="","",H11*12)
H12: =IF(D12="","",SUM(D12:G12)) | I12: =IF(D12="","",D12*12) | J12: =IF(H12="","",H12*12)
H13: =IF(D13="","",SUM(D13:G13)) | I13: =IF(D13="","",D13*12) | J13: =IF(H13="","",H13*12)
H14: =IF(D14="","",SUM(D14:G14)) | I14: =IF(D14="","",D14*12) | J14: =IF(H14="","",H14*12)
H15: =IF(D15="","",SUM(D15:G15)) | I15: =IF(D15="","",D15*12) | J15: =IF(H15="","",H15*12)
H16: =IF(D16="","",SUM(D16:G16)) | I16: =IF(D16="","",D16*12) | J16: =IF(H16="","",H16*12)
H17: =IF(D17="","",SUM(D17:G17)) | I17: =IF(D17="","",D17*12) | J17: =IF(H17="","",H17*12)
H18: =IF(D18="","",SUM(D18:G18)) | I18: =IF(D18="","",D18*12) | J18: =IF(H18="","",H18*12)
H19: =IF(D19="","",SUM(D19:G19)) | I19: =IF(D19="","",D19*12) | J19: =IF(H19="","",H19*12)
H20: =IF(D20="","",SUM(D20:G20)) | I20: =IF(D20="","",D20*12) | J20: =IF(H20="","",H20*12)
... H26: =IF(D26="","",SUM(D26:G26)) | I26: =IF(D26="","",D26*12) | J26: =IF(H26="","",H26*12)
B27: TOTAL PAYROLL | D27: =SUM(D7:D26) -> 950 | E27: =SUM(E7:E26) -> 0 | F27: =SUM(F7:F26) -> 0 | G27: =SUM(G7:G26) -> 0 | H27: =SUM(H7:H26) -> 950 | I27: =SUM(I7:I26) -> 11400 | J27: =SUM(J7:J26) -> 11400
A29: PAYROLL SUMMARY
A30: Total Basic Salary / Month | B30: =D27 -> 950
A31: Total Allowances / Month | B31: =SUM(E27:G27) -> 0
A32: Total Monthly Employment Cost | B32: =H27 -> 950
A33: Total Annual Basic Salary | B33: =I27 -> 11400
A34: Total Annual Employment Cost | B34: =J27 -> 11400

Sheet DATA_EXPENSES
A1: DATA EXPENSES
A2: Imported source snapshot — update this table when source workbooks change.
A3: =HYPERLINK("#'HOME'!A1","HOME") -> HOME | B3: =HYPERLINK("#'FARMERS'!A1","FARMERS") -> FARMERS | C3: =HYPERLINK("#'SUBSCRIPTIONS'!A1","SUBSCRIPTIONS") -> SUBSCRIPTIONS | D3: =HYPERLINK("#'PRODUCTION'!A1","PRODUCTION") -> PRODUCTION | E3: =HYPERLINK("#'RECOVERY'!A1","RECOVERY") -> RECOVERY | F3: =HYPERLINK("#'DELIVERIES'!A1","DELIVERIES") -> DELIVERIES | G3: =HYPERLINK("#'FINANCE'!A1","FINANCE") -> FINANCE | H3: =HYPERLINK("#'REPORTS'!A1","REPORTS") -> REPORTS
A5: DATE | B5: EXPENSE / PARTICULARS | C5: AMOUNT DR | D5: CREDIT / REIMBURSEMENT | E5: NET EXPENSE
A6: 45962 | B6: 5 cows | C6: 4020 | D6: 0 | E6: =DATA_EXPENSES!$C6 - DATA_EXPENSES!$D6 -> 4020
A7: 45962 | B7: Chitepo school if Ideology | C7: 1642 | D7: 0 | E7: =DATA_EXPENSES!$C7 - DATA_EXPENSES!$D7 -> 1642
A8: 45962 | B8: SGR company | C8: 170 | D8: 0 | E8: =DATA_EXPENSES!$C8 - DATA_EXPENSES!$D8 -> 170
A9: 45962 | B9: SGR committe meeting Food | C9: 76 | D9: 0 | E9: =DATA_EXPENSES!$C9 - DATA_EXPENSES!$D9 -> 76
A10: 45962 | B10: 2 x SGR 4m tear drops | C10: 200 | D10: 0 | E10: =DATA_EXPENSES!$C10 - DATA_EXPENSES!$D10 -> 200
A11: 45962 | B11: 2 x Roll up banners | C11: 170 | D11: 0 | E11: =DATA_EXPENSES!$C11 - DATA_EXPENSES!$D11 -> 170
A12: 45962 | B12: Chef Joy 1st meeting | C12: =952.5+9 -> 961.5 | D12: 0 | E12: =DATA_EXPENSES!$C12 - DATA_EXPENSES!$D12 -> 961.5
A13: 45962 | B13: Chef Joy 2nd event Permsec | C13: 470 | D13: 0 | E13: =DATA_EXPENSES!$C13 - DATA_EXPENSES!$D13 -> 470
A14: 45962 | B14: SHRM Strategy payment | C14: 1000 | D14: 0 | E14: =DATA_EXPENSES!$C14 - DATA_EXPENSES!$D14 -> 1000
A15: 45962 | B15: Food Reimbursement | C15: 0 | D15: 630 | E15: =DATA_EXPENSES!$C15 - DATA_EXPENSES!$D15 -> -630
A16: 45962 | B16: Chairman Reimbursement | C16: 0 | D16: 500 | E16: =DATA_EXPENSES!$C16 - DATA_EXPENSES!$D16 -> -500
A17: 45962 | B17: Mr Mugariri | C17: 0 | D17: 500 | E17: =DATA_EXPENSES!$C17 - DATA_EXPENSES!$D17 -> -500
A18: 45962 | B18: Balacing figure | C18: 80 | D18: 0 | E18: =DATA_EXPENSES!$C18 - DATA_EXPENSES!$D18 -> 80
A19: 46178 | B19: Rentals-June | C19: 500 | D19: 0 | E19: =DATA_EXPENSES!$C19 - DATA_EXPENSES!$D19 -> 500
A20: 46179 | B20: Salary-Allowance | C20: 800 | D20: 0 | E20: =DATA_EXPENSES!$C20 - DATA_EXPENSES!$D20 -> 800
A21: 46205 | B21: Transport -Banner | C21: 10 | D21: 0 | E21: =DATA_EXPENSES!$C21 - DATA_EXPENSES!$D21 -> 10
A22: 46207 | B22: Transport -Workshop | C22: 10 | D22: 0 | E22: =DATA_EXPENSES!$C22 - DATA_EXPENSES!$D22 -> 10
A23: 46207 | B23: Workshop Lunch | C23: 136 | D23: 0 | E23: =DATA_EXPENSES!$C23 - DATA_EXPENSES!$D23 -> 136
A24: 46207 | B24: Rentals-July | C24: 500 | D24: 0 | E24: =DATA_EXPENSES!$C24 - DATA_EXPENSES!$D24 -> 500
... A35: 46217 | B35: Airtime | C35: 15 | D35: 0 | E35: =DATA_EXPENSES!$C35 - DATA_EXPENSES!$D35 -> 15
A36: 46217 | B36: Association Registration -Transport | C36: 10 | E36: =DATA_EXPENSES!$C36 - DATA_EXPENSES!$D36 -> 10
A37: 46217 | B37: Transport Bank card | C37: 10 | D37: 0 | E37: =DATA_EXPENSES!$C37 - DATA_EXPENSES!$D37 -> 10
A38: 46227 | B38: indrive transport | C38: 10 | D38: 0 | E38: =DATA_EXPENSES!$C38 - DATA_EXPENSES!$D38 -> 10
A39: 46234 | B39: Salary -allowance | C39: 100 | D39: 0 | E39: =DATA_EXPENSES!$C39 - DATA_EXPENSES!$D39 -> 100
A40: 46220 | B40: Card charge | C40: 4 | D40: 0 | E40: =DATA_EXPENSES!$C40 - DATA_EXPENSES!$D40 -> 4
A41: 46234 | B41: golf club | C41: 36.5 | D41: 0 | E41: =DATA_EXPENSES!$C41 - DATA_EXPENSES!$D41 -> 36.5
A42: 46234 | B42: bank charge | C42: 20.75 | D42: 0 | E42: =DATA_EXPENSES!$C42 - DATA_EXPENSES!$D42 -> 20.75
A43: 46224 | B43: IMT charge | C43: 0.73 | D43: 0 | E43: =DATA_EXPENSES!$C43 - DATA_EXPENSES!$D43 -> 0.73
A44: 46234 | B44: Airtime | C44: 15 | D44: 0 | E44: =DATA_EXPENSES!$C44 - DATA_EXPENSES!$D44 -> 15
A45: 46237 | B45: victory farm lunch (571) | C45: 0 | D45: 0 | E45: =DATA_EXPENSES!$C45 - DATA_EXPENSES!$D45 -> 0
A46: 46238 | B46: SGR dinner with nbs bank | C46: 33.6 | D46: 0 | E46: =DATA_EXPENSES!$C46 - DATA_EXPENSES!$D46 -> 33.6
A47: 46238 | B47: SGR Drinks with nbs executives | C47: 29.5 | D47: 0 | E47: =DATA_EXPENSES!$C47 - DATA_EXPENSES!$D47 -> 29.5
A48: 46238 | B48: Mutibura -naison balance | C48: 150 | D48: 0 | E48: =DATA_EXPENSES!$C48 - DATA_EXPENSES!$D48 -> 150
A49: 46238 | B49: Mutibura reinbursment balance (500) | C49: 500 | D49: 500 | E49: =DATA_EXPENSES!$C49 - DATA_EXPENSES!$D49 -> 0
A50: 46238 | B50: Rent | C50: 500 | E50: =DATA_EXPENSES!$C50 - DATA_EXPENSES!$D50 -> 500
A51: 46238 | B51: Nhema | C51: 0 | D51: 500 | E51: =DATA_EXPENSES!$C51 - DATA_EXPENSES!$D51 -> -500
A52: 46242 | B52: Diner with Namibian delegation | C52: 47.25 | D52: 0 | E52: =DATA_EXPENSES!$C52 - DATA_EXPENSES!$D52 -> 47.25
A53: 46249 | B53: SGR committe meeting Food | C53: 50.21 | D53: 0 | E53: =DATA_EXPENSES!$C53 - DATA_EXPENSES!$D53 -> 50.21
A54: 46255 | B54: New company phones | C54: 200 | D54: 0 | E54: =DATA_EXPENSES!$C54 - DATA_EXPENSES!$D54 -> 200
A55: 46255 | B55: Addition of New Member | C55: 80 | D55: 0 | E55: =DATA_EXPENSES!$C55 - DATA_EXPENSES!$D55 -> 80
A56: 46255 | B56: airtime and lines | C56: 20 | D56: 0 | E56: =DATA_EXPENSES!$C56 - DATA_EXPENSES!$D56 -> 20 | I56: =33.6+29.5 -> 63.1
A57: 46265 | B57: stationery | C57: =69.1+4.06 -> 73.16 | E57: =DATA_EXPENSES!$C57 - DATA_EXPENSES!$D57 -> 73.16
A58: 46265 | B58: office laptop | C58: 390 | D58: 0 | E58: =DATA_EXPENSES!$C58 - DATA_EXPENSES!$D58 -> 390
A59: 46265 | B59: office chairs | C59: 380 | E59: =DATA_EXPENSES!$C59 - DATA_EXPENSES!$D59 -> 380
A60: 46265 | B60: naison-salary (150) from Mr Mutibura | C60: 850 | E60: =DATA_EXPENSES!$C60 - DATA_EXPENSES!$D60 -> 850
A61: 46265 | B61: Indrive -Stationary-Transport | C61: 17 | E61: =DATA_EXPENSES!$C61 - DATA_EXPENSES!$D61 -> 17
A62: 46265 | B62: tanaka-salary | C62: 100 | E62: =DATA_EXPENSES!$C62 - DATA_EXPENSES!$D62 -> 100
A63: 46265 | B63: Bank charge+withdrawall | C63: 70.59 | E63: =DATA_EXPENSES!$C63 - DATA_EXPENSES!$D63 -> 70.59
A64: 46266 | B64: Rent | C64: 500 | E64: =DATA_EXPENSES!$C64 - DATA_EXPENSES!$D64 -> 500
A65: 46266 | B65: Chakuchichi | C65: 40 | D65: 500 | E65: =DATA_EXPENSES!$C65 - DATA_EXPENSES!$D65 -> -460
A66: 46267 | B66: Chinhoyi Workshop-Lunch | C66: 142 | E66: =DATA_EXPENSES!$C66 - DATA_EXPENSES!$D66 -> 142
A67: 46269 | B67: Office Power Adpter | C67: 45 | E67: =DATA_EXPENSES!$C67 - DATA_EXPENSES!$D67 -> 45
A68: 46269 | B68: office Phone Lines | C68: 2 | E68: =DATA_EXPENSES!$C68 - DATA_EXPENSES!$D68 -> 2
A69: 46270 | B69: Boardroom webcamera | C69: 40 | E69: =DATA_EXPENSES!$C69 - DATA_EXPENSES!$D69 -> 40
A70: 46270 | B70: DP -HDMI cable | C70: 10 | E70: =DATA_EXPENSES!$C70 - DATA_EXPENSES!$D70 -> 10
A71: 46270 | B71: Indrive-Transport | C71: 20 | E71: =DATA_EXPENSES!$C71 - DATA_EXPENSES!$D71 -> 20
A72: 46270 | B72: Airtime | C72: 20 | E72: =DATA_EXPENSES!$C72 - DATA_EXPENSES!$D72 -> 20
A73: 46275 | B73: Great wall dinner with Engineer from Ministry of Agric | C73: 98 | E73: =DATA_EXPENSES!$C73 - DATA_EXPENSES!$D73 -> 98
E74: =DATA_EXPENSES!$C74 - DATA_EXPENSES!$D74 -> 0
E75: =DATA_EXPENSES!$C75 - DATA_EXPENSES!$D75 -> 0
E76: =DATA_EXPENSES!$C76 - DATA_EXPENSES!$D76 -> 0
E77: =DATA_EXPENSES!$C77 - DATA_EXPENSES!$D77 -> 0
E78: =DATA_EXPENSES!$C78 - DATA_EXPENSES!$D78 -> 0
E79: =DATA_EXPENSES!$C79 - DATA_EXPENSES!$D79 -> 0
E80: =DATA_EXPENSES!$C80 - DATA_EXPENSES!$D80 -> 0
A81: 46295 | B81: Bank charge+withdrawall | C81: =45.46+3.63 -> 49.09 | E81: =DATA_EXPENSES!$C81 - DATA_EXPENSES!$D81 -> 49.09
E82: =DATA_EXPENSES!$C82 - DATA_EXPENSES!$D82 -> 0
E83: =DATA_EXPENSES!$C83 - DATA_EXPENSES!$D83 -> 0
E84: =DATA_EXPENSES!$C84 - DATA_EXPENSES!$D84 -> 0
E85: =DATA_EXPENSES!$C85 - DATA_EXPENSES!$D85 -> 0
E86: =DATA_EXPENSES!$C86 - DATA_EXPENSES!$D86 -> 0
E87: =DATA_EXPENSES!$C87 - DATA_EXPENSES!$D87 -> 0
E88: =DATA_EXPENSES!$C88 - DATA_EXPENSES!$D88 -> 0
E89: =DATA_EXPENSES!$C89 - DATA_EXPENSES!$D89 -> 0

Sheet PROFIT & LOSS
A1: SGR PROFIT & LOSS ACCOUNT
A2: Management P&L for June, July and August 2026, with cumulative June-August totals. Figures are linked to receipts and expense records.
A4: =HYPERLINK("#'HOME'!A1","HOME") -> HOME | B4: =HYPERLINK("#'FINANCE'!A1","FINANCE") -> FINANCE | C4: =HYPERLINK("#'REPORTS'!A1","REPORTS") -> REPORTS | D4: =HYPERLINK("#'MONTHLY SALARY'!A1","MONTHLY SALARY") -> MONTHLY SALARY | I4: =HYPERLINK("#'PROFIT & LOSS'!A1","PROFIT & LOSS") -> PROFIT & LOSS | J4: =HYPERLINK("#'BALANCE SHEET'!A1","BALANCE SHEET") -> BALANCE SHEET
A6: Particulars | B6: June 2026 | C6: July 2026 | D6: 46235 | E6: 46266 | F6: 46296 | G6: 46327 | H6: 46357 | I6: Jun-Aug Total
A7: INCOME
A8: Subscription / Farmer Receipts | B8: =SUMIFS(DATA_RECEIPTS!$E:$E,DATA_RECEIPTS!$B:$B,">="&DATE(2026,6,1),DATA_RECEIPTS!$B:$B,"<"&DATE(2026,7,1)) -> 700 | C8: =SUMIFS(DATA_RECEIPTS!$E:$E,DATA_RECEIPTS!$B:$B,">="&DATE(2026,7,1),DATA_RECEIPTS!$B:$B,"<"&DATE(2026,8,1)) -> 1600 | D8: =SUMIFS(DATA_RECEIPTS!$E:$E,DATA_RECEIPTS!$B:$B,">="&DATE(2026,8,1),DATA_RECEIPTS!$B:$B,"<"&DATE(2026,9,1)) -> 4850 | E8: =SUMIFS(DATA_RECEIPTS!$E:$E,DATA_RECEIPTS!$B:$B,">="&DATE(2026,9,1),DATA_RECEIPTS!$B:$B,"<"&DATE(2026,10,1)) -> 2725 | I8: =SUM(B8:D8) -> 7150
A9: TOTAL INCOME | B9: =B8 -> 700 | C9: =C8 -> 1600 | D9: =D8 -> 4850 | E9: =E8 -> 2725 | I9: =SUM(B9:D9) -> 7150
A11: OPERATING EXPENSES
A12: Salaries & Wages | B12: =SUMIFS(DATA_EXPENSES!$E:$E,DATA_EXPENSES!$A:$A,">="&DATE(2026,6,1),DATA_EXPENSES!$A:$A,"<"&DATE(2026,7,1),DATA_EXPENSES!$B:$B,"*salary*") -> 800 | C12: =SUMIFS(DATA_EXPENSES!$E:$E,DATA_EXPENSES!$A:$A,">="&DATE(2026,7,1),DATA_EXPENSES!$A:$A,"<"&DATE(2026,8,1),DATA_EXPENSES!$B:$B,"*salary*") -> 850 | D12: =SUMIFS(DATA_EXPENSES!$E:$E,DATA_EXPENSES!$A:$A,">="&DATE(2026,8,1),DATA_EXPENSES!$A:$A,"<"&DATE(2026,9,1),DATA_EXPENSES!$B:$B,"*salary*") -> 950 | E12: =SUMIFS(DATA_EXPENSES!$E:$E,DATA_EXPENSES!$A:$A,">="&DATE(2026,9,1),DATA_EXPENSES!$A:$A,"<"&DATE(2026,10,1),DATA_EXPENSES!$B:$B,"*salary*") -> 0 | I12: =SUM(B12:D12) -> 2600
A13: Rentals | B13: =SUMIFS(DATA_EXPENSES!$E:$E,DATA_EXPENSES!$A:$A,">="&DATE(2026,6,1),DATA_EXPENSES!$A:$A,"<"&DATE(2026,7,1),DATA_EXPENSES!$B:$B,"*rent*") -> 500 | C13: =SUMIFS(DATA_EXPENSES!$E:$E,DATA_EXPENSES!$A:$A,">="&DATE(2026,7,1),DATA_EXPENSES!$A:$A,"<"&DATE(2026,8,1),DATA_EXPENSES!$B:$B,"*rent*") -> 500 | D13: =SUMIFS(DATA_EXPENSES!$E:$E,DATA_EXPENSES!$A:$A,">="&DATE(2026,8,1),DATA_EXPENSES!$A:$A,"<"&DATE(2026,9,1),DATA_EXPENSES!$B:$B,"*rent*") -> 500 | E13: =SUMIFS(DATA_EXPENSES!$E:$E,DATA_EXPENSES!$A:$A,">="&DATE(2026,9,1),DATA_EXPENSES!$A:$A,"<"&DATE(2026,10,1),DATA_EXPENSES!$B:$B,"*rent*") -> 500 | I13: =SUM(B13:D13) -> 1500
A14: Transport | B14: =SUMIFS(DATA_EXPENSES!$E:$E,DATA_EXPENSES!$A:$A,">="&DATE(2026,6,1),DATA_EXPENSES!$A:$A,"<"&DATE(2026,7,1),DATA_EXPENSES!$B:$B,"*transport*") -> 0 | C14: =SUMIFS(DATA_EXPENSES!$E:$E,DATA_EXPENSES!$A:$A,">="&DATE(2026,7,1),DATA_EXPENSES!$A:$A,"<"&DATE(2026,8,1),DATA_EXPENSES!$B:$B,"*transport*") -> 60 | D14: =SUMIFS(DATA_EXPENSES!$E:$E,DATA_EXPENSES!$A:$A,">="&DATE(2026,8,1),DATA_EXPENSES!$A:$A,"<"&DATE(2026,9,1),DATA_EXPENSES!$B:$B,"*transport*") -> 17 | E14: =SUMIFS(DATA_EXPENSES!$E:$E,DATA_EXPENSES!$A:$A,">="&DATE(2026,9,1),DATA_EXPENSES!$A:$A,"<"&DATE(2026,10,1),DATA_EXPENSES!$B:$B,"*transport*") -> 20 | I14: =SUM(B14:D14) -> 77
A15: Meals / Entertainment | B15: =SUMIFS(DATA_EXPENSES!$E:$E,DATA_EXPENSES!$A:$A,">="&DATE(2026,6,1),DATA_EXPENSES!$A:$A,"<"&DATE(2026,7,1),DATA_EXPENSES!$B:$B,"*lunch*")+SUMIFS(DATA_EXPENSES!$E:$E,DATA_EXPENSES!$A:$A,">="&DATE(2026,6,1),DATA_EXPENSES!$A:$A,"<"&DATE(2026,7,1),DATA_EXPENSES!$B:$B,"*food*")+SUMIFS(DATA_EXPENSES!$E:$E,DATA_EXPENSES!$A:$A,">="&DATE(2026,6,1),DATA_EXPENSES!$A:$A,"<"&DATE(2026,7,1),DATA_EXPENSES!$B:$B,"*diner*")+SUMIFS(DATA_EXPENSES!$E:$E,DATA_EXPENSES!$A:$A,">="&DATE(2026,6,1),DATA_EXPENSES!$A:$A,"<"&DATE(2026,7,1),DATA_EXPENSES!$B:$B,"*meeting*") -> 0 | C15: =SUMIFS(DATA_EXPENSES!$E:$E,DATA_EXPENSES!$A:$A,">="&DATE(2026,7,1),DATA_EXPENSES!$A:$A,"<"&DATE(2026,8,1),DATA_EXPENSES!$B:$B,"*lunch*")+SUMIFS(DATA_EXPENSES!$E:$E,DATA_EXPENSES!$A:$A,">="&DATE(2026,7,1),DATA_EXPENSES!$A:$A,"<"&DATE(2026,8,1),DATA_EXPENSES!$B:$B,"*food*")+SUMIFS(DATA_EXPENSES!$E:$E,DATA_EXPENSES!$A:$A,">="&DATE(2026,7,1),DATA_EXPENSES!$A:$A,"<"&DATE(2026,8,1),DATA_EXPENSES!$B:$B,"*diner*")+SUMIFS(DATA_EXPENSES!$E:$E,DATA_EXPENSES!$A:$A,">="&DATE(2026,7,1),DATA_EXPENSES!$A:$A,"<"&DATE(2026,8,1),DATA_EXPENSES!$B:$B,"*meeting*") -> 136 | D15: =SUMIFS(DATA_EXPENSES!$E:$E,DATA_EXPENSES!$A:$A,">="&DATE(2026,8,1),DATA_EXPENSES!$A:$A,"<"&DATE(2026,9,1),DATA_EXPENSES!$B:$B,"*lunch*")+SUMIFS(DATA_EXPENSES!$E:$E,DATA_EXPENSES!$A:$A,">="&DATE(2026,8,1),DATA_EXPENSES!$A:$A,"<"&DATE(2026,9,1),DATA_EXPENSES!$B:$B,"*food*")+SUMIFS(DATA_EXPENSES!$E:$E,DATA_EXPENSES!$A:$A,">="&DATE(2026,8,1),DATA_EXPENSES!$A:$A,"<"&DATE(2026,9,1),DATA_EXPENSES!$B:$B,"*diner*")+SUMIFS(DATA_EXPENSES!$E:$E,DATA_EXPENSES!$A:$A,">="&DATE(2026,8,1),DATA_EXPENSES!$A:$A,"<"&DATE(2026,9,1),DATA_EXPENSES!$B:$B,"*meeting*") -> 147.67 | E15: =SUMIFS(DATA_EXPENSES!$E:$E,DATA_EXPENSES!$A:$A,">="&DATE(2026,9,1),DATA_EXPENSES!$A:$A,"<"&DATE(2026,10,1),DATA_EXPENSES!$B:$B,"*lunch*")+SUMIFS(DATA_EXPENSES!$E:$E,DATA_EXPENSES!$A:$A,">="&DATE(2026,9,1),DATA_EXPENSES!$A:$A,"<"&DATE(2026,10,1),DATA_EXPENSES!$B:$B,"*food*")+SUMIFS(DATA_EXPENSES!$E:$E,DATA_EXPENSES!$A:$A,">="&DATE(2026,9,1),DATA_EXPENSES!$A:$A,"<"&DATE(2026,10,1),DATA_EXPENSES!$B:$B,"*diner*")+SUMIFS(DATA_EXPENSES!$E:$E,DATA_EXPENSES!$A:$A,">="&DATE(2026,9,1),DATA_EXPENSES!$A:$A,"<"&DATE(2026,10,1),DATA_EXPENSES!$B:$B,"*meeting*") -> 142 | I15: =SUM(B15:D15) -> 283.67
A16: Bank & Transaction Charges | B16: =SUMIFS(DATA_EXPENSES!$E:$E,DATA_EXPENSES!$A:$A,">="&DATE(2026,6,1),DATA_EXPENSES!$A:$A,"<"&DATE(2026,7,1),DATA_EXPENSES!$B:$B,"*bank charge*")+SUMIFS(DATA_EXPENSES!$E:$E,DATA_EXPENSES!$A:$A,">="&DATE(2026,6,1),DATA_EXPENSES!$A:$A,"<"&DATE(2026,7,1),DATA_EXPENSES!$B:$B,"*IMT charge*") -> 0 | C16: =SUMIFS(DATA_EXPENSES!$E:$E,DATA_EXPENSES!$A:$A,">="&DATE(2026,7,1),DATA_EXPENSES!$A:$A,"<"&DATE(2026,8,1),DATA_EXPENSES!$B:$B,"*bank charge*")+SUMIFS(DATA_EXPENSES!$E:$E,DATA_EXPENSES!$A:$A,">="&DATE(2026,7,1),DATA_EXPENSES!$A:$A,"<"&DATE(2026,8,1),DATA_EXPENSES!$B:$B,"*IMT charge*") -> 21.48 | D16: =SUMIFS(DATA_EXPENSES!$E:$E,DATA_EXPENSES!$A:$A,">="&DATE(2026,8,1),DATA_EXPENSES!$A:$A,"<"&DATE(2026,9,1),DATA_EXPENSES!$B:$B,"*bank charge*")+SUMIFS(DATA_EXPENSES!$E:$E,DATA_EXPENSES!$A:$A,">="&DATE(2026,8,1),DATA_EXPENSES!$A:$A,"<"&DATE(2026,9,1),DATA_EXPENSES!$B:$B,"*IMT charge*") -> 70.59 | E16: =SUMIFS(DATA_EXPENSES!$E:$E,DATA_EXPENSES!$A:$A,">="&DATE(2026,9,1),DATA_EXPENSES!$A:$A,"<"&DATE(2026,10,1),DATA_EXPENSES!$B:$B,"*bank charge*")+SUMIFS(DATA_EXPENSES!$E:$E,DATA_EXPENSES!$A:$A,">="&DATE(2026,9,1),DATA_EXPENSES!$A:$A,"<"&DATE(2026,10,1),DATA_EXPENSES!$B:$B,"*IMT charge*") -> 49.09 | I16: =SUM(B16:D16) -> 92.07
A17: Office Equipment & Furniture | B17: =SUMIFS(DATA_EXPENSES!$E:$E,DATA_EXPENSES!$A:$A,">="&DATE(2026,6,1),DATA_EXPENSES!$A:$A,"<"&DATE(2026,7,1),DATA_EXPENSES!$B:$B,"*laptop*")+SUMIFS(DATA_EXPENSES!$E:$E,DATA_EXPENSES!$A:$A,">="&DATE(2026,6,1),DATA_EXPENSES!$A:$A,"<"&DATE(2026,7,1),DATA_EXPENSES!$B:$B,"*chair*")+SUMIFS(DATA_EXPENSES!$E:$E,DATA_EXPENSES!$A:$A,">="&DATE(2026,6,1),DATA_EXPENSES!$A:$A,"<"&DATE(2026,7,1),DATA_EXPENSES!$B:$B,"*phone*") -> 0 | C17: =SUMIFS(DATA_EXPENSES!$E:$E,DATA_EXPENSES!$A:$A,">="&DATE(2026,7,1),DATA_EXPENSES!$A:$A,"<"&DATE(2026,8,1),DATA_EXPENSES!$B:$B,"*laptop*")+SUMIFS(DATA_EXPENSES!$E:$E,DATA_EXPENSES!$A:$A,">="&DATE(2026,7,1),DATA_EXPENSES!$A:$A,"<"&DATE(2026,8,1),DATA_EXPENSES!$B:$B,"*chair*")+SUMIFS(DATA_EXPENSES!$E:$E,DATA_EXPENSES!$A:$A,">="&DATE(2026,7,1),DATA_EXPENSES!$A:$A,"<"&DATE(2026,8,1),DATA_EXPENSES!$B:$B,"*phone*") -> 0 | D17: =SUMIFS(DATA_EXPENSES!$E:$E,DATA_EXPENSES!$A:$A,">="&DATE(2026,8,1),DATA_EXPENSES!$A:$A,"<"&DATE(2026,9,1),DATA_EXPENSES!$B:$B,"*laptop*")+SUMIFS(DATA_EXPENSES!$E:$E,DATA_EXPENSES!$A:$A,">="&DATE(2026,8,1),DATA_EXPENSES!$A:$A,"<"&DATE(2026,9,1),DATA_EXPENSES!$B:$B,"*chair*")+SUMIFS(DATA_EXPENSES!$E:$E,DATA_EXPENSES!$A:$A,">="&DATE(2026,8,1),DATA_EXPENSES!$A:$A,"<"&DATE(2026,9,1),DATA_EXPENSES!$B:$B,"*phone*") -> 970 | E17: =SUMIFS(DATA_EXPENSES!$E:$E,DATA_EXPENSES!$A:$A,">="&DATE(2026,9,1),DATA_EXPENSES!$A:$A,"<"&DATE(2026,10,1),DATA_EXPENSES!$B:$B,"*laptop*")+SUMIFS(DATA_EXPENSES!$E:$E,DATA_EXPENSES!$A:$A,">="&DATE(2026,9,1),DATA_EXPENSES!$A:$A,"<"&DATE(2026,10,1),DATA_EXPENSES!$B:$B,"*chair*")+SUMIFS(DATA_EXPENSES!$E:$E,DATA_EXPENSES!$A:$A,">="&DATE(2026,9,1),DATA_EXPENSES!$A:$A,"<"&DATE(2026,10,1),DATA_EXPENSES!$B:$B,"*phone*") -> 2 | I17: =SUM(B17:D17) -> 970
A18: Other Operating Expenses | B18: =SUMIFS(DATA_EXPENSES!$E:$E,DATA_EXPENSES!$A:$A,">="&DATE(2026,6,1),DATA_EXPENSES!$A:$A,"<"&DATE(2026,7,1))-SUM(B12:B17) -> 0 | C18: =SUMIFS(DATA_EXPENSES!$E:$E,DATA_EXPENSES!$A:$A,">="&DATE(2026,7,1),DATA_EXPENSES!$A:$A,"<"&DATE(2026,8,1))-SUM(C12:C17) -> 265.5 | D18: =SUMIFS(DATA_EXPENSES!$E:$E,DATA_EXPENSES!$A:$A,">="&DATE(2026,8,1),DATA_EXPENSES!$A:$A,"<"&DATE(2026,9,1))-SUM(D12:D17) -> -163.95 | E18: =SUMIFS(DATA_EXPENSES!$E:$E,DATA_EXPENSES!$A:$A,">="&DATE(2026,9,1),DATA_EXPENSES!$A:$A,"<"&DATE(2026,10,1))-SUM(E12:E17) -> -247 | I18: =SUM(B18:D18) -> 101.55
A19: TOTAL OPERATING EXPENSES | B19: =SUM(B12:B18) -> 1300 | C19: =SUM(C12:C18) -> 1832.98 | D19: =SUM(D12:D18) -> 2491.31 | E19: =SUM(E12:E18) -> 466.09 | I19: =SUM(B19:D19) -> 5624.29
A21: NET PROFIT / (LOSS) | B21: =B9-B19 -> -600 | C21: =C9-C19 -> -232.98 | D21: =D9-D19 -> 2358.69 | E21: =E9-E19 -> 2258.91 | I21: =SUM(B21:D21) -> 1525.71
A24: Accounting note:
A25: This management P&L uses recorded cash receipts as income and recorded net expenses as costs. Expense categories are keyword-based from DATA_EXPENSES and should be reviewed for final statutory accounts.
A28: JUNE-DECEMBER 2026 MANAGEMENT PLANNING
A29: Period | B29: June | C29: July | D29: August | I29: September | J29: October | K29: November | L29: December
A30: Salary Expense | B30: ='MONTHLY SALARY'!B5 | C30: ='MONTHLY SALARY'!B6 | D30: ='MONTHLY SALARY'!B7 | I30: ='MONTHLY SALARY'!B8 -> 0 | J30: ='MONTHLY SALARY'!B9 -> 0 | K30: ='MONTHLY SALARY'!B10 -> 0 | L30: ='MONTHLY SALARY'!B11 -> 0
A31: Note | B31: September-December are planning figures; replace with actuals as incurred.

Sheet BALANCE SHEET
A1: SGR BALANCE SHEET
A3: =HYPERLINK("#'HOME'!A1","HOME") -> HOME | B3: =HYPERLINK("#'FINANCE'!A1","FINANCE") -> FINANCE
A5: Particulars | B5: USD
A6: ASSETS
A7: Cash at Bank | B7: =DATA_BANK!E10 -> 4125.12
A8: Accounts Receivable – Outstanding Farmer/Subscription Amounts | B8: =SUMIFS(DATA_RECEIPTS!$D:$D,DATA_RECEIPTS!$B:$B,"<"&DATE(2026,10,1))-SUMIFS(DATA_RECEIPTS!$E:$E,DATA_RECEIPTS!$B:$B,"<"&DATE(2026,10,1)) -> 14125
A9: Property, Plant & Equipment – Office Equipment | B9: =SUMIFS(DATA_EXPENSES!$E:$E,DATA_EXPENSES!$A:$A,"<"&DATE(2026,10,1),DATA_EXPENSES!$B:$B,"*laptop*")+SUMIFS(DATA_EXPENSES!$E:$E,DATA_EXPENSES!$A:$A,"<"&DATE(2026,10,1),DATA_EXPENSES!$B:$B,"*chair*")+SUMIFS(DATA_EXPENSES!$E:$E,DATA_EXPENSES!$A:$A,"<"&DATE(2026,10,1),DATA_EXPENSES!$B:$B,"*phone*") -> 472
A10: TOTAL ASSETS | B10: =SUM(B7:B9) -> 18722.12
A12: LIABILITIES
A13: Accounts Payable / Other Liabilities (input) | B13: 0
A14: TOTAL LIABILITIES | B14: =B13 -> 0
A16: EQUITY
A17: Retained Earnings – Cumulative Profit/(Loss) to 31 Aug 2026 | B17: ='PROFIT & LOSS'!I21 -> 1525.71
A18: Opening / Contributed Capital (derived) | B18: =B10-B14-B17 -> 17196.41
A19: TOTAL EQUITY | B19: =SUM(B17:B18) -> 18722.12
A21: TOTAL LIABILITIES + EQUITY | B21: =B14+B19 -> 18722.12
A22: BALANCE CHECK | B22: =B10-B21 -> 0
A25: Important:
A26: Accounts payable/liabilities are currently set to USD 0 because no separate payable ledger is present in the workbook. Replace B14 with confirmed liabilities when available. Opening/contributed capital in B19 is a derived balancing figure and should be replaced with the verified capital/shareholder balance once available.

Sheet INPUT DEBT
A1: INPUT DEBT RECOVERY
A2: Imported source snapshot — update this table when source workbooks change.
A3: =HYPERLINK("#'HOME'!A1","HOME") -> HOME | B3: =HYPERLINK("#'FARMERS'!A1","FARMERS") -> FARMERS | C3: =HYPERLINK("#'SUBSCRIPTIONS'!A1","SUBSCRIPTIONS") -> SUBSCRIPTIONS | D3: =HYPERLINK("#'PRODUCTION'!A1","PRODUCTION") -> PRODUCTION | E3: =HYPERLINK("#'DELIVERIES'!A1","DELIVERIES") -> DELIVERIES | F3: =HYPERLINK("#'REPORTS'!A1","REPORTS") -> REPORTS
A5: SEQ | B5: PROVINCE | C5: FARM NAME | D5: FARMER NAME | E5: FARMER ID | F5: CROP | G5: CONTRACTED HA | H5: ARDA GRAND TOTAL | I5: ARDA Balance Claimed | J5: ARDA BAL | K5: SGR Balance Recorded | L5: SGR vs ARDA Difference | M5: GRAIN RECOVERY TONNES | N5: GRAIN DELIVERED TONNES | O5: OUTSTANDING TONNES | P5: STATUS
A6: 1 | B6: MASHWEST | C6: NK | D6: BEHANE FLORENCE | E6: 63-676409-M-39 | F6: SORGHUM | G6: 50 | H6: 9878.15 | I6: - | J6: 10273 | K6: - | L6: 10273 | M6: 30.22 | N6: 0.82 | O6: ='INPUT DEBT'!$M6-'INPUT DEBT'!$N6 -> 29.4 | P6: =IF(N6=0, "NOT DELIVERED", IF(O6=0, "CLEARED", "PARTIALLY DELIVERED")) -> PARTIALLY DELIVERED
A7: 2 | B7: MASHWEST | C7: DAIZY FARM | D7: TAKAVADA KELVIN | E7: 86-053962-P-22 | F7: SORGHUM | G7: 20 | H7: 8630 | I7: - | J7: 8630 | K7: ='INPUT DEBT'!$J7+1277.64 -> 9907.64 | L7: 8630 | M7: 25.38 | N7: 0 | O7: ='INPUT DEBT'!$M7-'INPUT DEBT'!$N7 -> 25.38 | P7: =IF(N7=0, "NOT DELIVERED", IF(O7=0, "CLEARED", "PARTIALLY DELIVERED")) -> NOT DELIVERED
A8: 3 | B8: MASHWEST | C8: UNIT 40 COBEN ESTATES | D8: ZINYOWERA DONALD | E8: 63-259741-M-24 | F8: SORGHUM | G8: 35 | H8: 6467 | I8: - | J8: 6467 | L8: 6467 | M8: 19.02 | N8: 3.61 | O8: ='INPUT DEBT'!$M8-'INPUT DEBT'!$N8 -> 15.41 | P8: =IF(N8=0, "NOT DELIVERED", IF(O8=0, "CLEARED", "PARTIALLY DELIVERED")) -> PARTIALLY DELIVERED
A9: 4 | B9: MASHWEST | C9: AVOG 8 A COBURN ESTSTES | D9: MUNEMO MOSES | E9: 63-431627-V-25 | F9: SORGHUM | G9: 40 | H9: 7596 | I9: - | J9: 7596 | L9: 7596 | M9: 22.34 | N9: 2.52 | O9: ='INPUT DEBT'!$M9-'INPUT DEBT'!$N9 -> 19.82 | P9: =IF(N9=0, "NOT DELIVERED", IF(O9=0, "CLEARED", "PARTIALLY DELIVERED")) -> PARTIALLY DELIVERED
A10: 5 | B10: MASHWEST | C10: COBEAN STATES | D10: GORORO HARROED | E10: 63-202346-B-25 | F10: SORGHUM | G10: 30 | H10: 6008 | I10: - | J10: 6008 | L10: 6008 | M10: 17.67 | N10: 5.38 | O10: ='INPUT DEBT'!$M10-'INPUT DEBT'!$N10 -> 12.29 | P10: =IF(N10=0, "NOT DELIVERED", IF(O10=0, "CLEARED", "PARTIALLY DELIVERED")) -> PARTIALLY DELIVERED
A11: 6 | B11: MASHWEST | C11: COBEAN ESTATE | D11: MATHUTHU FUNNY | E11: 29-075854-N-21 | F11: SORGHUM | G11: 20 | H11: 4415 | I11: 1557 | J11: 2858 | L11: 2858 | M11: 12.99 | N11: 4.27 | O11: ='INPUT DEBT'!$M11-'INPUT DEBT'!$N11 -> 8.72 | P11: =IF(N11=0, "NOT DELIVERED", IF(O11=0, "CLEARED", "PARTIALLY DELIVERED")) -> PARTIALLY DELIVERED
A12: 7 | B12: MASHEAST | C12: 43 COBEAN ESTATE | D12: MKWENA CAUL | E12: 70-2000429-T-04 | F12: SORGHUM | G12: 20 | H12: 4415 | I12: - | J12: 4415 | L12: 4415 | M12: 12.99 | N12: 2.28 | O12: ='INPUT DEBT'!$M12-'INPUT DEBT'!$N12 -> 10.71 | P12: =IF(N12=0, "NOT DELIVERED", IF(O12=0, "CLEARED", "PARTIALLY DELIVERED")) -> PARTIALLY DELIVERED
A13: 8 | B13: MASHWEST | C13: CHIKAGO FARM | D13: JANDELES VALERIE | E13: 63-708750-Q-00 | F13: SORGHUM | G13: 25 | H13: 5317 | I13: - | J13: 5317 | L13: 5317 | M13: 15.64 | N13: 4.81 | O13: ='INPUT DEBT'!$M13-'INPUT DEBT'!$N13 -> 10.83 | P13: =IF(N13=0, "NOT DELIVERED", IF(O13=0, "CLEARED", "PARTIALLY DELIVERED")) -> PARTIALLY DELIVERED
A14: 9 | B14: MASHWEST | C14: 25 COBEAN ESTATE | D14: MOYO CHARLES | E14: 29-062067-C-21 | F14: SORGHUM | G14: 20 | H14: 4415 | I14: - | J14: 4415 | L14: 4415 | M14: 12.99 | N14: 3.07 | O14: ='INPUT DEBT'!$M14-'INPUT DEBT'!$N14 -> 9.92 | P14: =IF(N14=0, "NOT DELIVERED", IF(O14=0, "CLEARED", "PARTIALLY DELIVERED")) -> PARTIALLY DELIVERED
A15: 10 | B15: MASHWEST | C15: FAUN FARM PLOT 1 | D15: CHIKOMWE SHINE | E15: 38-047571-E-38 | F15: SORGHUM | G15: 80 | H15: 12655 | I15: - | J15: 12655 | L15: 12655 | M15: 37.22 | N15: 0 | O15: ='INPUT DEBT'!$M15-'INPUT DEBT'!$N15 -> 37.22 | P15: =IF(N15=0, "NOT DELIVERED", IF(O15=0, "CLEARED", "PARTIALLY DELIVERED")) -> NOT DELIVERED
A16: 11 | B16: MASHWEST | C16: BURNBANK FARM | D16: MUSWEHAURARI CHIPO | E16: 42-144968-X-42 | F16: SORGHUM | G16: 20 | H16: 8301 | I16: 1773 | J16: 6528 | L16: 6528 | M16: 24.41 | N16: 4.86 | O16: ='INPUT DEBT'!$M16-'INPUT DEBT'!$N16 -> 19.55 | P16: =IF(N16=0, "NOT DELIVERED", IF(O16=0, "CLEARED", "PARTIALLY DELIVERED")) -> PARTIALLY DELIVERED
A17: 12 | B17: MASHWEST | C17: MUDAVANHU FARM CHEGUTU | D17: MUDAVANHU D | E17: 27-165809-C-03 | F17: SORGHUM | G17: 100 | H17: 27965 | I17: 2860 | J17: 25105 | L17: 25105 | M17: 82.25 | N17: 7.84 | O17: ='INPUT DEBT'!$M17-'INPUT DEBT'!$N17 -> 74.41 | P17: =IF(N17=0, "NOT DELIVERED", IF(O17=0, "CLEARED", "PARTIALLY DELIVERED")) -> PARTIALLY DELIVERED
A18: 13 | B18: MASHWEST | C18: SIVUNDAZI FAM | D18: MUJURU D | E18: 63-948959-M-80 | F18: SORGHUM | G18: 180 | H18: 27779 | I18: - | J18: 27779 | L18: 27779 | M18: 81.7 | N18: 0 | O18: ='INPUT DEBT'!$M18-'INPUT DEBT'!$N18 -> 81.7 | P18: =IF(N18=0, "NOT DELIVERED", IF(O18=0, "CLEARED", "PARTIALLY DELIVERED")) -> NOT DELIVERED
A19: 14 | B19: MASHWEST | C19: PLOT 4 JAMAICA FARM | D19: GORA DOCAS | E19: 32-188882-P-26 | F19: SORGHUM | G19: 15 | H19: 2808 | I19: - | J19: 2808 | L19: 2808 | M19: 8.26 | N19: 0 | O19: ='INPUT DEBT'!$M19-'INPUT DEBT'!$N19 -> 8.26 | P19: =IF(N19=0, "NOT DELIVERED", IF(O19=0, "CLEARED", "PARTIALLY DELIVERED")) -> NOT DELIVERED
A20: 15 | B20: MASHWEST | C20: DAIZY FARM | D20: MANYAWU E.T | E20: 63-817650-K-50 | F20: SORGHUM | G20: 12 | H20: 4565 | I20: - | J20: 4565 | L20: 4565 | M20: 13.43 | N20: 0 | O20: ='INPUT DEBT'!$M20-'INPUT DEBT'!$N20 -> 13.43 | P20: =IF(N20=0, "NOT DELIVERED", IF(O20=0, "CLEARED", "PARTIALLY DELIVERED")) -> NOT DELIVERED
A21: 16 | B21: MASHWEST | C21: HIPPOVALE FARM PLOT 5 | D21: MAVUNGA COMBOSI S | E21: 08-285801-E-32 | F21: SORGHUM | G21: 10 | H21: 4433 | I21: - | J21: 4433 | L21: 4433 | M21: 13.04 | N21: 0 | O21: ='INPUT DEBT'!$M21-'INPUT DEBT'!$N21 -> 13.04 | P21: =IF(N21=0, "NOT DELIVERED", IF(O21=0, "CLEARED", "PARTIALLY DELIVERED")) -> NOT DELIVERED
A22: 17 | B22: MASHWEST | C22: THE GROOVE FARM 1 | D22: CHIGUNDU BABRA | E22: 63736189-Q-80 | F22: SORGHUM | G22: 20 | H22: - | I22: - | J22: - | L22: - | M22: 0 | N22: 0 | O22: ='INPUT DEBT'!$M22-'INPUT DEBT'!$N22 -> 0 | P22: CLEARED
A23: 18 | B23: MASHWEST | C23: 2 AQUARUS FARM GADZEMA | D23: MWAMLOWE OLIVIA | E23: 24066249-Q-85 | F23: SORGHUM | G23: 20 | H23: 4744 | I23: - | J23: 4744 | L23: 4744 | M23: 13.95 | N23: 4.23 | O23: ='INPUT DEBT'!$M23-'INPUT DEBT'!$N23 -> 9.72 | P23: =IF(N23=0, "NOT DELIVERED", IF(O23=0, "CLEARED", "PARTIALLY DELIVERED")) -> PARTIALLY DELIVERED
A24: 19 | B24: MASHWEST | C24: PLOT 3 HUNYANI ETSTATE NORTON | D24: MUTIWASEKWA ITAI | E24: 32088464-P-44 | F24: SORGHUM | G24: 40 | H24: 11006 | I24: - | J24: 11006 | L24: 11006 | M24: 32.37 | N24: 0 | O24: ='INPUT DEBT'!$M24-'INPUT DEBT'!$N24 -> 32.37 | P24: =IF(N24=0, "NOT DELIVERED", IF(O24=0, "CLEARED", "PARTIALLY DELIVERED")) -> NOT DELIVERED
A25: 20 | B25: MASHWEST | C25: THE GROOVE FARM 1 | D25: KADZOMBE TRUST | E25: 32-123646-F-71 | F25: SORGHUM | G25: 10 | H25: 273 | I25: - | J25: 273 | L25: 273 | M25: 0.8 | N25: 0 | O25: ='INPUT DEBT'!$M25-'INPUT DEBT'!$N25 -> 0.8 | P25: CLEARED
A26: 21 | B26: MASHWEST | C26: BULLFIELD FARM | D26: MDADADADA A | E26: 29-114199-S-66 | F26: SORGHUM | G26: 13 | H26: - | I26: - | J26: - | L26: - | M26: 0 | N26: 0 | O26: ='INPUT DEBT'!$M26-'INPUT DEBT'!$N26 -> 0 | P26: CLEARED
A27: 22 | B27: MASHWEST | C27: COBUN ESTATE | D27: MUBWANDARIKWA K | E27: 18-064080-T-27 | F27: SORGHUM | G27: 30 | H27: 7215 | I27: - | J27: 7215 | L27: 7215 | M27: 21.22 | N27: 0 | O27: ='INPUT DEBT'!$M27-'INPUT DEBT'!$N27 -> 21.22 | P27: =IF(N27=0, "NOT DELIVERED", IF(O27=0, "CLEARED", "PARTIALLY DELIVERED")) -> NOT DELIVERED
A28: 23 | B28: MASHEAST | C28: RUDOLPHIA | D28: BIKA FARAYI WILFRED | E28: 63-701839-D-25 | F28: SORGHUM | G28: 20 | H28: 7265 | I28: - | J28: 7265 | L28: 7265 | M28: 21.37 | N28: 4.21 | O28: ='INPUT DEBT'!$M28-'INPUT DEBT'!$N28 -> 17.16 | P28: =IF(N28=0, "NOT DELIVERED", IF(O28=0, "CLEARED", "PARTIALLY DELIVERED")) -> PARTIALLY DELIVERED
A29: 24 | B29: MASHEAST | C29: SPRINGS FARM | D29: CHIKOMO UNICO | E29: 63-1438243-Q-75 | F29: SORGHUM | G29: 20 | H29: 8948 | I29: - | J29: 8948 | L29: 8948 | M29: 26.32 | N29: 0 | O29: ='INPUT DEBT'!$M29-'INPUT DEBT'!$N29 -> 26.32 | P29: =IF(N29=0, "NOT DELIVERED", IF(O29=0, "CLEARED", "PARTIALLY DELIVERED")) -> NOT DELIVERED
A30: 25 | B30: MASHWEST | C30: ZPCS FARM | D30: KAROI PRISONS | E30: 71-051668-Y-71 | F30: SORGHUM | G30: 30 | H30: 15099 | I30: - | J30: 15099 | L30: 15099 | M30: 44.41 | N30: 0 | O30: ='INPUT DEBT'!$M30-'INPUT DEBT'!$N30 -> 44.41 | P30: =IF(N30=0, "NOT DELIVERED", IF(O30=0, "CLEARED", "PARTIALLY DELIVERED")) -> NOT DELIVERED
A31: 26 | B31: MASHWEST | C31: SENCEGAL , TENGWE | D31: CHIREMBA S TAFADZWA | E31: 63-1563144-C-07 | F31: SORGHUM | G31: 100 | H31: 31207 | I31: - | J31: 31207 | L31: 31207 | M31: 91.79 | N31: 0 | O31: ='INPUT DEBT'!$M31-'INPUT DEBT'!$N31 -> 91.79 | P31: =IF(N31=0, "NOT DELIVERED", IF(O31=0, "CLEARED", "PARTIALLY DELIVERED")) -> NOT DELIVERED
A32: 27 | B32: MASHWEST | C32: RAUUNMADE | D32: MUDZVITI TECLA | E32: 83-116229-B-83 | F32: SORGHUM | G32: 20 | H32: 8096 | I32: - | J32: 8096 | L32: 8096 | M32: 23.81 | N32: 0 | O32: ='INPUT DEBT'!$M32-'INPUT DEBT'!$N32 -> 23.81 | P32: =IF(N32=0, "NOT DELIVERED", IF(O32=0, "CLEARED", "PARTIALLY DELIVERED")) -> NOT DELIVERED
A33: 28 | B33: MASHWEST | C33: PUMULA FARM MAGUNJE | D33: CHAERUKA ANOLD | E33: 75-157910-E-75 | F33: SORGHUM | G33: 400 | H33: 76796 | I33: 10359 | J33: 66438 | L33: 66438 | M33: 225.87 | N33: 28.4 | O33: ='INPUT DEBT'!$M33-'INPUT DEBT'!$N33 -> 197.47 | P33: =IF(N33=0, "NOT DELIVERED", IF(O33=0, "CLEARED", "PARTIALLY DELIVERED")) -> PARTIALLY DELIVERED
A34: 29 | B34: MASHWEST | C34: PELELE FARM PLOT 11 | D34: GOMBE TENDAI | E34: 38-218039-W-70 | F34: SORGHUM | G34: 20 | H34: 7384 | I34: - | J34: 7384 | L34: 7384 | M34: 21.72 | N34: 0 | O34: ='INPUT DEBT'!$M34-'INPUT DEBT'!$N34 -> 21.72 | P34: =IF(N34=0, "NOT DELIVERED", IF(O34=0, "CLEARED", "PARTIALLY DELIVERED")) -> NOT DELIVERED
A35: 30 | B35: MASHWEST | C35: CHOYAMBA | D35: MUJENGE TONGAI | E35: 71-072373-D-38 | F35: SORGHUM | G35: 20 | H35: 4850 | I35: - | J35: 4850 | L35: 4850 | M35: 14.27 | N35: 0 | O35: ='INPUT DEBT'!$M35-'INPUT DEBT'!$N35 -> 14.27 | P35: =IF(N35=0, "NOT DELIVERED", IF(O35=0, "CLEARED", "PARTIALLY DELIVERED")) -> NOT DELIVERED
A36: 31 | B36: MASHWEST | C36: MARNI MULICHI | D36: GATSI MARIAN | E36: 66-025163-F-12 | F36: SORGHUM | G36: 10 | H36: 2807 | I36: - | J36: 2807 | K36: ='INPUT DEBT'!$J36-911.3 -> 1895.7 | L36: 2807 | M36: 8.26 | N36: 0 | O36: ='INPUT DEBT'!$M36-'INPUT DEBT'!$N36 -> 8.26 | P36: =IF(N36=0, "NOT DELIVERED", IF(O36=0, "CLEARED", "PARTIALLY DELIVERED")) -> NOT DELIVERED
A37: 32 | B37: MASHWEST | C37: PLOT 10 BALLANEETTY FARM NYABIRA | D37: JINYA JEFFREY | E37: 70-135325-Y-71 | F37: SORGHUM | G37: 10 | H37: 2382 | I37: - | J37: 2382 | L37: 2382 | M37: 7 | N37: 0 | O37: ='INPUT DEBT'!$M37-'INPUT DEBT'!$N37 -> 7 | P37: =IF(N37=0, "NOT DELIVERED", IF(O37=0, "CLEARED", "PARTIALLY DELIVERED")) -> NOT DELIVERED
A38: 33 | B38: MASHWEST | C38: PLOT KIPPOCK FARM KAROI | D38: NJOVANA TANAKA WONDER | E38: 38-251446-H-66 | F38: SORGHUM | G38: 10 | H38: 3462 | I38: - | J38: 3462 | L38: 3462 | M38: 10.18 | N38: 0 | O38: ='INPUT DEBT'!$M38-'INPUT DEBT'!$N38 -> 10.18 | P38: =IF(N38=0, "NOT DELIVERED", IF(O38=0, "CLEARED", "PARTIALLY DELIVERED")) -> NOT DELIVERED
A39: 34 | B39: MASHWEST | C39: NEBO FARM | D39: ISAH RABEEAH M | E39: 63-3216103-X-70 | F39: SORGHUM | G39: 30 | H39: 7612 | I39: - | J39: 7612 | K39: ='INPUT DEBT'!$J39-1822.6 -> 5789.4 | L39: 7612 | M39: 22.39 | N39: 0 | O39: ='INPUT DEBT'!$M39-'INPUT DEBT'!$N39 -> 22.39 | P39: =IF(N39=0, "NOT DELIVERED", IF(O39=0, "CLEARED", "PARTIALLY DELIVERED")) -> NOT DELIVERED
A40: 35 | B40: MASHWEST | C40: PLOT 1 RIDGES EASTER PARADE | D40: MUSIIWA ALEXIS | E40: 02-2000881-A-05 | F40: SORGHUM | G40: 20 | H40: 5199 | I40: - | J40: 5199 | K40: ='INPUT DEBT'!$J40-911.3 -> 4287.7 | L40: 5199 | M40: 15.29 | N40: 3.66 | O40: ='INPUT DEBT'!$M40-'INPUT DEBT'!$N40 -> 11.63 | P40: =IF(N40=0, "NOT DELIVERED", IF(O40=0, "CLEARED", "PARTIALLY DELIVERED")) -> PARTIALLY DELIVERED
A41: 36 | B41: MASHWEST | C41: GOOD HOPE PLOT 27 | D41: HURUNGWE FARMERS ASSOCIA | E41: 38-115839-J-38 | F41: SORGHUM | G41: 122 | H41: 30217 | I41: 2378 | J41: 27839 | L41: 27839 | M41: 88.87 | N41: 7.35 | O41: ='INPUT DEBT'!$M41-'INPUT DEBT'!$N41 -> 81.52 | P41: =IF(N41=0, "NOT DELIVERED", IF(O41=0, "CLEARED", "PARTIALLY DELIVERED")) -> PARTIALLY DELIVERED
A42: 37 | B42: MASHWEST | C42: COMSTON PLOT 5 KAROI | D42: BURANDA MOSES | E42: 18045704B18 | F42: SORGHUM | G42: 15 | H42: 4812 | I42: - | J42: 4812 | L42: 4812 | M42: 14.15 | N42: 0 | O42: ='INPUT DEBT'!$M42-'INPUT DEBT'!$N42 -> 14.15 | P42: =IF(N42=0, "NOT DELIVERED", IF(O42=0, "CLEARED", "PARTIALLY DELIVERED")) -> NOT DELIVERED
A43: 38 | B43: MASHWEST | C43: Cornstone Farm Subdivision 5 | D43: MWANDITANI PATRICIA | E43: 38140258B66 | F43: SORGHUM | G43: 15 | H43: 4797 | I43: - | J43: 4797 | L43: 4797 | M43: 14.11 | N43: 0.34 | O43: ='INPUT DEBT'!$M43-'INPUT DEBT'!$N43 -> 13.77 | P43: =IF(N43=0, "NOT DELIVERED", IF(O43=0, "CLEARED", "PARTIALLY DELIVERED")) -> PARTIALLY DELIVERED
A44: 39 | B44: MASHWEST | C44: Naba Estate(A2) Plot 2 | D44: IMBAYAGO NYARADZO | E44: 24043532R12 | F44: SORGHUM | G44: 20 | H44: 12436 | I44: - | J44: 12436 | L44: 12436 | M44: 36.58 | N44: 3.32 | O44: ='INPUT DEBT'!$M44-'INPUT DEBT'!$N44 -> 33.26 | P44: =IF(N44=0, "NOT DELIVERED", IF(O44=0, "CLEARED", "PARTIALLY DELIVERED")) -> PARTIALLY DELIVERED
A45: 40 | B45: MASHWEST | C45: Cornstone Farm Plot 7 Karoi | D45: MILONDE ADAM | E45: 38-095779-E-38 | F45: SORGHUM | G45: 25 | H45: 7356 | I45: - | J45: 7356 | L45: 7356 | M45: 21.63 | N45: 0 | O45: ='INPUT DEBT'!$M45-'INPUT DEBT'!$N45 -> 21.63 | P45: =IF(N45=0, "NOT DELIVERED", IF(O45=0, "CLEARED", "PARTIALLY DELIVERED")) -> NOT DELIVERED
A46: 41 | B46: MASHWEST | C46: MYLERN FARM , Karoi | D46: MASHORE LENON | E46: 38-140239-F-70 | F46: SORGHUM | G46: 40 | H46: 10904 | I46: - | J46: 10904 | L46: 10904 | M46: 32.07 | N46: 0 | O46: ='INPUT DEBT'!$M46-'INPUT DEBT'!$N46 -> 32.07 | P46: =IF(N46=0, "NOT DELIVERED", IF(O46=0, "CLEARED", "PARTIALLY DELIVERED")) -> NOT DELIVERED
A47: 42 | B47: MASHWEST | C47: MYLERN FARM , Karoi | D47: MUZEZEWA SHEPARD | E47: 38-059005-H-38 | F47: SORGHUM | G47: 50 | H47: 14075 | I47: - | J47: 14075 | L47: 14075 | M47: 41.4 | N47: 0 | O47: ='INPUT DEBT'!$M47-'INPUT DEBT'!$N47 -> 41.4 | P47: =IF(N47=0, "NOT DELIVERED", IF(O47=0, "CLEARED", "PARTIALLY DELIVERED")) -> NOT DELIVERED
A48: 43 | B48: MASHWEST | C48: MYLERN FARM , Karoi | D48: MARIMO DENNY TAPIWA | E48: 38-175475-F-38 | F48: SORGHUM | G48: 50 | H48: 16984 | I48: - | J48: 16984 | L48: 16984 | M48: 49.95 | N48: 0 | O48: ='INPUT DEBT'!$M48-'INPUT DEBT'!$N48 -> 49.95 | P48: =IF(N48=0, "NOT DELIVERED", IF(O48=0, "CLEARED", "PARTIALLY DELIVERED")) -> NOT DELIVERED
A49: 44 | B49: MASHWEST | C49: MAKOROKOTO | D49: MASENDA TAPIWA | E49: 63-2080208-D-80 | F49: SORGHUM | G49: 60 | H49: 14815 | I49: - | J49: 14815 | L49: 14815 | M49: 43.57 | N49: 0 | O49: ='INPUT DEBT'!$M49-'INPUT DEBT'!$N49 -> 43.57 | P49: =IF(N49=0, "NOT DELIVERED", IF(O49=0, "CLEARED", "PARTIALLY DELIVERED")) -> NOT DELIVERED
A50: 45 | B50: MASHWEST | C50: NYAMANDA FARM, KAROI | D50: NHEMA TAKUNDA | E50: 29-198307-P-66 | F50: SORGHUM | G50: 500 | H50: 103060 | I50: - | J50: 103060 | K50: ='INPUT DEBT'!$J50+3645 -> 106705 | L50: 103060 | M50: 303.12 | N50: 87.82 | O50: ='INPUT DEBT'!$M50-'INPUT DEBT'!$N50 -> 215.3 | P50: =IF(N50=0, "NOT DELIVERED", IF(O50=0, "CLEARED", "PARTIALLY DELIVERED")) -> PARTIALLY DELIVERED
A51: 46 | B51: MASHEAST | C51: DOUNE FARM, Marondera | D51: KANETA NACY | E51: 58-057835-R-44 | F51: SORGHUM | G51: 10 | H51: 2522 | I51: - | J51: 2522 | L51: 2522 | M51: 7.42 | N51: 0 | O51: ='INPUT DEBT'!$M51-'INPUT DEBT'!$N51 -> 7.42 | P51: =IF(N51=0, "NOT DELIVERED", IF(O51=0, "CLEARED", "PARTIALLY DELIVERED")) -> NOT DELIVERED
A52: 47 | B52: MASHWEST | C52: ITAFA FARM , CTC | D52: CHIWERA BLESSING | E52: 18-088449-G-18 | F52: SORGHUM | G52: 60 | H52: 20225 | I52: 11351 | J52: 8874 | L52: 8874 | M52: 59.48 | N52: 31.12 | O52: ='INPUT DEBT'!$M52-'INPUT DEBT'!$N52 -> 28.36 | P52: =IF(N52=0, "NOT DELIVERED", IF(O52=0, "CLEARED", "PARTIALLY DELIVERED")) -> PARTIALLY DELIVERED
A53: 48 | B53: MASHWEST | C53: PLOT 14 RAILWAY FARM | D53: MACHIYA TAKUNDA | E53: 24-181927-C22 | F53: SORGHUM | G53: 25 | H53: 6640 | I53: 2576 | J53: 4064 | L53: 4064 | M53: 19.53 | N53: 7.06 | O53: ='INPUT DEBT'!$M53-'INPUT DEBT'!$N53 -> 12.47 | P53: =IF(N53=0, "NOT DELIVERED", IF(O53=0, "CLEARED", "PARTIALLY DELIVERED")) -> PARTIALLY DELIVERED
A54: 49 | B54: MASHWEST | C54: COMBE FARM KADOMA | D54: JAMELA BEATRICE | E54: 24-097588-E-24 | F54: SORGHUM | G54: 50 | H54: 9778 | I54: - | J54: 9778 | L54: 9778 | M54: 28.76 | N54: 0 | O54: ='INPUT DEBT'!$M54-'INPUT DEBT'!$N54 -> 28.76 | P54: =IF(N54=0, "NOT DELIVERED", IF(O54=0, "CLEARED", "PARTIALLY DELIVERED")) -> NOT DELIVERED
A55: 50 | B55: MASHWEST | C55: NK | D55: ZHARARE MARTIN | E55: 32-090877-M-24 | F55: SORGHUM | G55: 10 | H55: - | I55: - | J55: - | L55: - | M55: 0 | N55: 0 | O55: ='INPUT DEBT'!$M55-'INPUT DEBT'!$N55 -> 0 | P55: CLEARED
A56: 51 | B56: MASHWEST | C56: KADOMA PRISON FARM | D56: KADOMA PRISSONS | E56: 32-065804-J-26 | F56: SORGHUM | G56: 20 | H56: 2555 | I56: - | J56: 2555 | L56: 2555 | M56: 7.52 | N56: 0 | O56: ='INPUT DEBT'!$M56-'INPUT DEBT'!$N56 -> 7.52 | P56: =IF(N56=0, "NOT DELIVERED", IF(O56=0, "CLEARED", "PARTIALLY DELIVERED")) -> NOT DELIVERED
A57: 52 | B57: MASHWEST | C57: CHIMUSENGA FARM | D57: MUTARA COMMENT T | E57: 24-162440-W-07 | F57: SORGHUM | G57: 150 | H57: 37209 | I57: - | J57: 37209 | L57: 37209 | M57: 109.44 | N57: 0 | O57: ='INPUT DEBT'!$M57-'INPUT DEBT'!$N57 -> 109.44 | P57: =IF(N57=0, "NOT DELIVERED", IF(O57=0, "CLEARED", "PARTIALLY DELIVERED")) -> NOT DELIVERED
A58: 53 | B58: MASHWEST | C58: GUMA FARM | D58: NYAMAYARO FARAI | E58: 25-046225-G-25 | F58: SORGHUM | G58: 40 | H58: 17014 | I58: - | J58: 17014 | L58: 17014 | M58: 50.04 | N58: 5.13 | O58: ='INPUT DEBT'!$M58-'INPUT DEBT'!$N58 -> 44.91 | P58: =IF(N58=0, "NOT DELIVERED", IF(O58=0, "CLEARED", "PARTIALLY DELIVERED")) -> PARTIALLY DELIVERED
A59: 54 | B59: MASHWEST | C59: TEVERED PLOT 14 | D59: MUSHAYAVANHU PRETTY | E59: 63-1186544-E-38 | F59: SORGHUM | G59: 40 | H59: 15568 | I59: - | J59: 15568 | L59: 15568 | M59: 45.79 | N59: 3.17 | O59: ='INPUT DEBT'!$M59-'INPUT DEBT'!$N59 -> 42.62 | P59: =IF(N59=0, "NOT DELIVERED", IF(O59=0, "CLEARED", "PARTIALLY DELIVERED")) -> PARTIALLY DELIVERED
A60: 55 | B60: MASHWEST | C60: DEVIDE PLOT 3 | D60: MUSIYIWA TAFADZWA | E60: 70-217393-C-70 | F60: SORGHUM | G60: 20 | H60: 5510 | I60: - | J60: 5510 | L60: 5510 | M60: 16.21 | N60: 3.57 | O60: ='INPUT DEBT'!$M60-'INPUT DEBT'!$N60 -> 12.64 | P60: =IF(N60=0, "NOT DELIVERED", IF(O60=0, "CLEARED", "PARTIALLY DELIVERED")) -> PARTIALLY DELIVERED
A61: 56 | B61: MASHWEST | C61: PETROUSWILE PLOT 14, DOMA | D61: MASHAVAVE SIMBARASHE | E61: 63-722130-J-66 | F61: SORGHUM | G61: 50 | H61: 15945 | I61: - | J61: 15945 | L61: 15945 | M61: 46.9 | N61: 0 | O61: ='INPUT DEBT'!$M61-'INPUT DEBT'!$N61 -> 46.9 | P61: =IF(N61=0, "NOT DELIVERED", IF(O61=0, "CLEARED", "PARTIALLY DELIVERED")) -> NOT DELIVERED
A62: 57 | B62: MASHWEST | C62: OLD CITRUS FARM | D62: MAGAYA WEBSTER | E62: 86-2003688-E-70 | F62: SORGHUM | G62: 20 | H62: 6601 | I62: - | J62: 6601 | L62: 6601 | M62: 19.41 | N62: 0 | O62: ='INPUT DEBT'!$M62-'INPUT DEBT'!$N62 -> 19.41 | P62: =IF(N62=0, "NOT DELIVERED", IF(O62=0, "CLEARED", "PARTIALLY DELIVERED")) -> NOT DELIVERED
A63: 58 | B63: MASHWEST | C63: ROSSETA FARM 16 , DOMA | D63: CHIKONDOWA TINASHE | E63: 29-156984-Y-07 | F63: SORGHUM | G63: 70 | H63: 24850 | I63: - | J63: 24850 | K63: 25791 | L63: -941 | M63: 73.09 | N63: 0 | O63: ='INPUT DEBT'!$M63-'INPUT DEBT'!$N63 -> 73.09 | P63: =IF(N63=0, "NOT DELIVERED", IF(O63=0, "CLEARED", "PARTIALLY DELIVERED")) -> NOT DELIVERED
A64: 59 | B64: MASHWEST | C64: LEADHILLS FARM , LIONS DEN | D64: PIRIRAI CHIPO BLESSING | E64: 59-055920-R-38 | F64: SORGHUM | G64: 30 | H64: 11572 | I64: - | J64: 11572 | L64: 11572 | M64: 34.03 | N64: 0 | O64: ='INPUT DEBT'!$M64-'INPUT DEBT'!$N64 -> 34.03 | P64: =IF(N64=0, "NOT DELIVERED", IF(O64=0, "CLEARED", "PARTIALLY DELIVERED")) -> NOT DELIVERED
A65: 60 | B65: MASHWEST | C65: LIONDEN FARM , ALASKA | D65: HINZE KORNELL | E65: 70-089062-M-00 | F65: SORGHUM | G65: 140 | H65: 47808 | I65: 30070 | J65: 17738 | K65: 17820 | L65: -82 | M65: 140.61 | N65: 82.44 | O65: ='INPUT DEBT'!$M65-'INPUT DEBT'!$N65 -> 58.17 | P65: =IF(N65=0, "NOT DELIVERED", IF(O65=0, "CLEARED", "PARTIALLY DELIVERED")) -> PARTIALLY DELIVERED
A66: 61 | B66: MASHWEST | C66: HIGHBERRY FARM | D66: DENHERE SHONHAYI | E66: 63-576825T-77 | F66: SORGHUM | G66: 200 | H66: 26297 | I66: - | J66: 26297 | L66: 26297 | M66: 77.34 | N66: 0 | O66: ='INPUT DEBT'!$M66-'INPUT DEBT'!$N66 -> 77.34 | P66: =IF(N66=0, "NOT DELIVERED", IF(O66=0, "CLEARED", "PARTIALLY DELIVERED")) -> NOT DELIVERED
A67: 62 | B67: MASHWEST | C67: HIGHBERRY FARM | D67: MUREFU LAHLIWE | E67: 08-506842-R-43 | F67: SORGHUM | G67: 20 | H67: 5038 | I67: - | J67: 5038 | L67: 5038 | M67: 14.82 | N67: 0 | O67: ='INPUT DEBT'!$M67-'INPUT DEBT'!$N67 -> 14.82 | P67: =IF(N67=0, "NOT DELIVERED", IF(O67=0, "CLEARED", "PARTIALLY DELIVERED")) -> NOT DELIVERED
A68: 63 | B68: MASHWEST | C68: PLATEAU FARM PLOT 64 | D68: MATURA HERALD | E68: 08-567298-E-48 | F68: SORGHUM | G68: 20 | H68: 6587 | I68: 1164 | J68: 5422 | L68: 5422 | M68: 19.37 | N68: 3.19 | O68: ='INPUT DEBT'!$M68-'INPUT DEBT'!$N68 -> 16.18 | P68: =IF(N68=0, "NOT DELIVERED", IF(O68=0, "CLEARED", "PARTIALLY DELIVERED")) -> PARTIALLY DELIVERED
A69: 64 | B69: MASHWEST | C69: OLD CITRUS FARM | D69: CHIYANGWA BRUCE | E69: 63-2063267-P-70 | F69: SORGHUM | G69: 100 | H69: 33784 | I69: 3754 | J69: 30030 | L69: 30030 | M69: 99.36 | N69: 10.29 | O69: ='INPUT DEBT'!$M69-'INPUT DEBT'!$N69 -> 89.07 | P69: =IF(N69=0, "NOT DELIVERED", IF(O69=0, "CLEARED", "PARTIALLY DELIVERED")) -> PARTIALLY DELIVERED
A70: 65 | B70: MASHWEST | C70: ROSSETA FARM 22, Doma | D70: CHIKONDOWA TINEVIMBO | E70: 70-216775-V-07 | F70: SORGHUM | G70: 20 | H70: 6682 | I70: - | J70: 6682 | K70: 6863 | L70: -181 | M70: 19.65 | N70: 0 | O70: ='INPUT DEBT'!$M70-'INPUT DEBT'!$N70 -> 19.65 | P70: =IF(N70=0, "NOT DELIVERED", IF(O70=0, "CLEARED", "PARTIALLY DELIVERED")) -> NOT DELIVERED
A71: 66 | B71: MASHWEST | C71: CLENT FARM, PORTLET | D71: GURAMATUNHU OBEY | E71: 38-136292-Q-38 | F71: SORGHUM | G71: 30 | H71: 4376 | I71: - | J71: 4376 | L71: 4376 | M71: 12.87 | N71: 0 | O71: ='INPUT DEBT'!$M71-'INPUT DEBT'!$N71 -> 12.87 | P71: =IF(N71=0, "NOT DELIVERED", IF(O71=0, "CLEARED", "PARTIALLY DELIVERED")) -> NOT DELIVERED
A72: 67 | B72: MASHWEST | C72: MUCHERENGI FARM 13 , Mhangura | D72: SEFU MOFFAT | E72: 63-1215791-Y-38 | F72: SORGHUM | G72: 300 | H72: 110156 | I72: - | J72: 110156 | L72: 110156 | M72: 323.99 | N72: 0 | O72: ='INPUT DEBT'!$M72-'INPUT DEBT'!$N72 -> 323.99 | P72: =IF(N72=0, "NOT DELIVERED", IF(O72=0, "CLEARED", "PARTIALLY DELIVERED")) -> NOT DELIVERED
A73: 68 | B73: MASHWEST | C73: PIRINGANI FARM , Mangura | D73: ZVOBGO DAN MAGWENZI | E73: 63-748865-T-22 | F73: SORGHUM | G73: 60 | H73: 24457 | I73: 12037 | J73: 12420 | L73: 12420 | M73: 71.93 | N73: 33 | O73: ='INPUT DEBT'!$M73-'INPUT DEBT'!$N73 -> 38.93 | P73: =IF(N73=0, "NOT DELIVERED", IF(O73=0, "CLEARED", "PARTIALLY DELIVERED")) -> PARTIALLY DELIVERED
A74: 69 | B74: MASHWEST | C74: UMVUMI FARM , Doma | D74: MASHURA LIBERTY | E74: 14-197494-H-54 | F74: SORGHUM | G74: 500 | H74: 115647 | I74: - | J74: 115647 | L74: 115647 | M74: 340.14 | N74: 0 | O74: ='INPUT DEBT'!$M74-'INPUT DEBT'!$N74 -> 340.14 | P74: =IF(N74=0, "NOT DELIVERED", IF(O74=0, "CLEARED", "PARTIALLY DELIVERED")) -> NOT DELIVERED
A75: 70 | B75: MASHWEST | C75: STAILINGVALE , Mhangura | D75: FOBS MAODZWA | E75: 15-139390-h-15 | F75: SORGHUM | G75: 100 | H75: 25315 | I75: - | J75: 25315 | L75: 25315 | M75: 74.46 | N75: 0 | O75: ='INPUT DEBT'!$M75-'INPUT DEBT'!$N75 -> 74.46 | P75: =IF(N75=0, "NOT DELIVERED", IF(O75=0, "CLEARED", "PARTIALLY DELIVERED")) -> NOT DELIVERED
A76: 71 | B76: MASHWEST | C76: SHEEPRIDGE FARM , | D76: CHIDARIKIRE GAMUCHIRAI | E76: 70-248534-B-32 | F76: SORGHUM | G76: 45 | H76: 16046 | I76: - | J76: 16046 | L76: 16046 | M76: 47.19 | N76: 0 | O76: ='INPUT DEBT'!$M76-'INPUT DEBT'!$N76 -> 47.19 | P76: =IF(N76=0, "NOT DELIVERED", IF(O76=0, "CLEARED", "PARTIALLY DELIVERED")) -> NOT DELIVERED
A77: 72 | B77: MASHWEST | C77: SCAFFEL | D77: MUNYEBA PARADZAI | E77: 70-125696-J-70 | F77: SORGHUM | G77: 10 | H77: 3745 | I77: - | J77: 3745 | L77: 3745 | M77: 11.01 | N77: 0 | O77: ='INPUT DEBT'!$M77-'INPUT DEBT'!$N77 -> 11.01 | P77: =IF(N77=0, "NOT DELIVERED", IF(O77=0, "CLEARED", "PARTIALLY DELIVERED")) -> NOT DELIVERED
A78: 73 | B78: MASHWEST | C78: KANAMI ALASKA | D78: SHIKITA B TENDAI | E78: 63-1111302-V-75 | F78: SORGHUM | G78: 50 | H78: 12979 | I78: - | J78: 12979 | L78: 12979 | M78: 38.17 | N78: 0 | O78: ='INPUT DEBT'!$M78-'INPUT DEBT'!$N78 -> 38.17 | P78: =IF(N78=0, "NOT DELIVERED", IF(O78=0, "CLEARED", "PARTIALLY DELIVERED")) -> NOT DELIVERED
A79: 74 | B79: MASHWEST | C79: SHEEPRIDGE FARM | D79: MADA PRINCE | E79: 70-224430-B-04 | F79: SORGHUM | G79: 40 | H79: 25533 | I79: - | J79: 25533 | L79: 25533 | M79: 75.1 | N79: 0 | O79: ='INPUT DEBT'!$M79-'INPUT DEBT'!$N79 -> 75.1 | P79: =IF(N79=0, "NOT DELIVERED", IF(O79=0, "CLEARED", "PARTIALLY DELIVERED")) -> NOT DELIVERED
A80: 75 | B80: MASHWEST | C80: SHEEPRIDGE FARM | D80: MATARUTSE PETER | E80: 22-029770-B-83 | F80: SORGHUM | G80: 60 | H80: 24614 | I80: - | J80: 24614 | L80: 24614 | M80: 72.39 | N80: 0 | O80: ='INPUT DEBT'!$M80-'INPUT DEBT'!$N80 -> 72.39 | P80: =IF(N80=0, "NOT DELIVERED", IF(O80=0, "CLEARED", "PARTIALLY DELIVERED")) -> NOT DELIVERED
A81: 76 | B81: MASHWEST | C81: WOELWEHOEK | D81: BENHURA CHANDAIDA DIDMUS | E81: 68-034449-M-42 | F81: SORGHUM | G81: 40 | H81: 14152 | I81: 3026 | J81: 11125 | L81: 11125 | M81: 41.62 | N81: 8.3 | O81: ='INPUT DEBT'!$M81-'INPUT DEBT'!$N81 -> 33.32 | P81: =IF(N81=0, "NOT DELIVERED", IF(O81=0, "CLEARED", "PARTIALLY DELIVERED")) -> PARTIALLY DELIVERED
A82: 77 | B82: MASHWEST | C82: SPRING FARM | D82: MLISWA THEMBA | E82: 63-821381-Q-66 | F82: SORGHUM | G82: 120 | H82: 31501 | I82: 2590 | J82: 28911 | L82: 28911 | M82: 92.65 | N82: 7.1 | O82: ='INPUT DEBT'!$M82-'INPUT DEBT'!$N82 -> 85.55 | P82: =IF(N82=0, "NOT DELIVERED", IF(O82=0, "CLEARED", "PARTIALLY DELIVERED")) -> PARTIALLY DELIVERED
A83: 78 | B83: MASHWEST | C83: MHANGURA | D83: KUNODZIYA GALANT | E83: 04-131844-J-83 | F83: SORGHUM | G83: 20 | H83: - | I83: - | J83: - | L83: - | M83: 0 | N83: 0 | O83: ='INPUT DEBT'!$M83-'INPUT DEBT'!$N83 -> 0 | P83: CLEARED
A84: 79 | B84: MASHWEST | C84: MSINA FARM , MTUNZI | D84: DZARAMBA TATENDA | E84: 70-2033630-G-70 | F84: SORGHUM | G84: 30 | H84: 7605 | I84: - | J84: 7605 | L84: 7605 | M84: 22.37 | N84: 0 | O84: ='INPUT DEBT'!$M84-'INPUT DEBT'!$N84 -> 22.37 | P84: =IF(N84=0, "NOT DELIVERED", IF(O84=0, "CLEARED", "PARTIALLY DELIVERED")) -> NOT DELIVERED
A85: 80 | B85: MASHWEST | C85: TSWANDAZWA FARM | D85: MUZAMBINDO DANIEL | E85: 29-032540-H18 | F85: SORGHUM | G85: 30 | H85: 6589 | I85: 2432 | J85: 4157 | L85: 4157 | M85: 19.38 | N85: 6.67 | O85: ='INPUT DEBT'!$M85-'INPUT DEBT'!$N85 -> 12.71 | P85: =IF(N85=0, "NOT DELIVERED", IF(O85=0, "CLEARED", "PARTIALLY DELIVERED")) -> PARTIALLY DELIVERED
A86: 81 | B86: MASHWEST | C86: PORTLET ESTATE , CHITOMBORWIZI | D86: MAGWADA PENIKATI | E86: 15-007643-E-15 | F86: SORGHUM | G86: 50 | H86: 10322 | I86: 13884 | J86: -3562 | L86: -3562 | M86: 30.36 | N86: 38.07 | O86: ='INPUT DEBT'!$M86-'INPUT DEBT'!$N86 -> -7.71 | P86: CLEARED
A87: 82 | B87: MASHWEST | C87: TREELANDS FARM , MHANGURA | D87: GWESHE WONDER | E87: 63-470729-X-26 | F87: SORGHUM | G87: 40 | H87: 15302 | I87: 13178 | J87: 2124 | L87: 2124 | M87: 45.01 | N87: 36.13 | O87: ='INPUT DEBT'!$M87-'INPUT DEBT'!$N87 -> 8.88 | P87: =IF(N87=0, "NOT DELIVERED", IF(O87=0, "CLEARED", "PARTIALLY DELIVERED")) -> PARTIALLY DELIVERED
A88: 83 | B88: MASHWEST | C88: CHIRIDZA FARM | D88: NGIRAZI OBERT | E88: 07-071953-E-07 | F88: SORGHUM | G88: 40 | H88: 8472 | I88: - | J88: 8472 | L88: 8472 | M88: 24.92 | N88: 2.04 | O88: ='INPUT DEBT'!$M88-'INPUT DEBT'!$N88 -> 22.88 | P88: =IF(N88=0, "NOT DELIVERED", IF(O88=0, "CLEARED", "PARTIALLY DELIVERED")) -> PARTIALLY DELIVERED
A89: 84 | B89: MASHWEST | C89: TASA FARM , CHIMUSENGA | D89: WATAMA TAWANDA | E89: 70-084715-M-70 | F89: SORGHUM | G89: 20 | H89: - | I89: - | J89: - | L89: - | M89: 0 | N89: 0 | O89: ='INPUT DEBT'!$M89-'INPUT DEBT'!$N89 -> 0 | P89: CLEARED
A90: 85 | B90: MASHWEST | C90: LONGWOOD FARM , DARWENDALE | D90: ZIYAMBI ZIYAMBI | E90: 32-084159-K-70 | F90: SORGHUM | G90: 40 | H90: 7129 | I90: - | J90: 7129 | L90: 7129 | M90: 20.97 | N90: 0 | O90: ='INPUT DEBT'!$M90-'INPUT DEBT'!$N90 -> 20.97 | P90: =IF(N90=0, "NOT DELIVERED", IF(O90=0, "CLEARED", "PARTIALLY DELIVERED")) -> NOT DELIVERED
A91: 86 | B91: MASHWEST | C91: CHIMUSENGA FARM , Victory | D91: KAFINYA SIMBARASHE | E91: 70-244486-B-70 | F91: SORGHUM | G91: 80 | H91: 26057 | I91: 20462 | J91: 5594 | L91: 5594 | M91: 76.64 | N91: 56.1 | O91: ='INPUT DEBT'!$M91-'INPUT DEBT'!$N91 -> 20.54 | P91: =IF(N91=0, "NOT DELIVERED", IF(O91=0, "CLEARED", "PARTIALLY DELIVERED")) -> PARTIALLY DELIVERED
A92: 87 | B92: MASHWEST | C92: GLEN VIEW FARM , MHANGURA | D92: MATIYENGA MUNYARADZI | E92: 70-108906-G-70 | F92: SORGHUM | G92: 10 | H92: 3944 | I92: - | J92: 3944 | K92: 4505 | L92: -561 | M92: 11.6 | N92: 0 | O92: ='INPUT DEBT'!$M92-'INPUT DEBT'!$N92 -> 11.6 | P92: =IF(N92=0, "NOT DELIVERED", IF(O92=0, "CLEARED", "PARTIALLY DELIVERED")) -> NOT DELIVERED
A93: 88 | B93: MASHWEST | C93: MUCHERENGI FARM | D93: MUTANGA NYARADZAI DOREEN | E93: 70-211203-Z-86 | F93: SORGHUM | G93: 30 | H93: 11846 | I93: 7944 | J93: 3902 | L93: 3902 | M93: 34.84 | N93: 21.78 | O93: ='INPUT DEBT'!$M93-'INPUT DEBT'!$N93 -> 13.06 | P93: =IF(N93=0, "NOT DELIVERED", IF(O93=0, "CLEARED", "PARTIALLY DELIVERED")) -> PARTIALLY DELIVERED
A94: 89 | B94: MASHWEST | C94: ENDEAVOR FARM , Mucherengi | D94: MANGOMBE FARAI | E94: 63-442750-K-38 | F94: SORGHUM | G94: 30 | H94: 3099 | I94: - | J94: 3099 | L94: 3099 | M94: 9.11 | N94: 0 | O94: ='INPUT DEBT'!$M94-'INPUT DEBT'!$N94 -> 9.11 | P94: =IF(N94=0, "NOT DELIVERED", IF(O94=0, "CLEARED", "PARTIALLY DELIVERED")) -> NOT DELIVERED
A95: 90 | B95: MASHWEST | C95: NASSAU FARM , Lions Den | D95: GWANZURA MUBAIRO SHASHA | E95: 38-049719-P-38 | F95: SORGHUM | G95: 30 | H95: 8219 | I95: - | J95: 8219 | L95: 8219 | M95: 24.17 | N95: 0 | O95: ='INPUT DEBT'!$M95-'INPUT DEBT'!$N95 -> 24.17 | P95: =IF(N95=0, "NOT DELIVERED", IF(O95=0, "CLEARED", "PARTIALLY DELIVERED")) -> NOT DELIVERED
A96: 91 | B96: MASHWEST | C96: RIXON RANGE FARM , MHANGURA | D96: CHIWADE BETTY | E96: 70-082150-Z-70 | F96: SORGHUM | G96: 10 | H96: 3812 | I96: - | J96: 3812 | L96: 3812 | M96: 11.21 | N96: 5.04 | O96: ='INPUT DEBT'!$M96-'INPUT DEBT'!$N96 -> 6.17 | P96: =IF(N96=0, "NOT DELIVERED", IF(O96=0, "CLEARED", "PARTIALLY DELIVERED")) -> PARTIALLY DELIVERED
A97: 92 | B97: MASHWEST | C97: GYPPSLANDER FARM | D97: MAREGERE TIMOTHY | E97: 12-001446-Z-22 | F97: SORGHUM | G97: 100 | H97: 17219 | I97: 20069 | J97: -2849 | L97: -2849 | M97: 50.64 | N97: 55.02 | O97: ='INPUT DEBT'!$M97-'INPUT DEBT'!$N97 -> -4.38 | P97: CLEARED
A98: 93 | B98: MASHWEST | C98: KOSSANA FARM , | D98: CHIMBANGU CHAMUNORWA | E98: 70-125085-S-71 | F98: SORGHUM | G98: 20 | H98: 4569 | I98: - | J98: 4569 | L98: 4569 | M98: 13.44 | N98: 0 | O98: ='INPUT DEBT'!$M98-'INPUT DEBT'!$N98 -> 13.44 | P98: =IF(N98=0, "NOT DELIVERED", IF(O98=0, "CLEARED", "PARTIALLY DELIVERED")) -> NOT DELIVERED
A99: 94 | B99: MASHWEST | C99: GUMA FARM | D99: MWANASA TAKESURE | E99: 70-153293-D-44 | F99: SORGHUM | G99: 20 | H99: 5852 | I99: - | J99: 5852 | L99: 5852 | M99: 17.21 | N99: 0 | O99: ='INPUT DEBT'!$M99-'INPUT DEBT'!$N99 -> 17.21 | P99: =IF(N99=0, "NOT DELIVERED", IF(O99=0, "CLEARED", "PARTIALLY DELIVERED")) -> NOT DELIVERED
A100: 95 | B100: MASHWEST | C100: RUKUTE FARM | D100: CHISHAMISO OBERT | E100: 70-145824-K-70 | F100: SORGHUM | G100: 20 | H100: 5877 | I100: - | J100: 5877 | L100: 5877 | M100: 17.28 | N100: 0 | O100: ='INPUT DEBT'!$M100-'INPUT DEBT'!$N100 -> 17.28 | P100: =IF(N100=0, "NOT DELIVERED", IF(O100=0, "CLEARED", "PARTIALLY DELIVERED")) -> NOT DELIVERED
A101: 96 | B101: MASHWEST | C101: AVONDALE FARM , LIONS DEN | D101: MHLANGA JOSIAH | E101: 58015120-M-23 | F101: SORGHUM | G101: 40 | H101: 17906 | I101: 15057 | J101: 2850 | L101: 2850 | M101: 52.67 | N101: 41.28 | O101: ='INPUT DEBT'!$M101-'INPUT DEBT'!$N101 -> 11.39 | P101: =IF(N101=0, "NOT DELIVERED", IF(O101=0, "CLEARED", "PARTIALLY DELIVERED")) -> PARTIALLY DELIVERED
...

Sheet PRODUCTION
A1: SUMMER 2026/2027 PRODUCTION
A2: Target vs contracted hectares
A3: =HYPERLINK("#'HOME'!A1","HOME") -> HOME | B3: =HYPERLINK("#'FARMERS'!A1","FARMERS") -> FARMERS | C3: =HYPERLINK("#'SUBSCRIPTIONS'!A1","SUBSCRIPTIONS") -> SUBSCRIPTIONS | D3: =HYPERLINK("#'PRODUCTION'!A1","PRODUCTION") -> PRODUCTION | E3: =HYPERLINK("#'RECOVERY'!A1","RECOVERY") -> RECOVERY | F3: =HYPERLINK("#'DELIVERIES'!A1","DELIVERIES") -> DELIVERIES | G3: =HYPERLINK("#'FINANCE'!A1","FINANCE") -> FINANCE | H3: =HYPERLINK("#'REPORTS'!A1","REPORTS") -> REPORTS
A5: MAIZE TARGET (HA) | C5: MAIZE ACTUAL (HA) | E5: MAIZE ACHIEVEMENT | G5: SORGHUM TARGET (HA) | I5: SORGHUM ACTUAL (HA) | K5: SORGHUM ACHIEVEMENT
A6: 20000 | C6: =SUM(DATA_PIPELINE!$M$6:$M$601) -> 20840 | E6: =C6/A6 -> 1.042 | G6: 20000 | I6: =SUM(DATA_PIPELINE!$N$6:$N$601) -> 40932 | K6: =I6/G6 -> 2.0466
A10: Crop | B10: Target HA | C10: Actual HA | D10: Variance | E10: Achievement | F10: Remaining
A11: Maize | B11: 20000 | C11: =SUM(DATA_PIPELINE!$M$6:$M$601) -> 20840 | D11: =C11-B11 -> 840 | E11: =C11/B11 -> 1.042 | F11: =MAX(0,B11-C11) -> 0
A12: Sorghum | B12: 20000 | C12: =SUM(DATA_PIPELINE!$N$6:$N$601) -> 40932 | D12: =C12-B12 -> 20932 | E12: =C12/B12 -> 2.0466 | F12: =MAX(0,B12-C12) -> 0
A16: District performance
A17: District | B17: Maize HA | C17: Sorghum HA | D17: Total HA
A18: BEATRICE | B18: =SUMIF(DATA_PIPELINE!$G$6:$G$601,A18,DATA_PIPELINE!$M$6:$M$601) -> 0 | C18: =SUMIF(DATA_PIPELINE!$G$6:$G$601,A18,DATA_PIPELINE!$N$6:$N$601) -> 0 | D18: =B18+C18 -> 0
A19: BINDURA | B19: =SUMIF(DATA_PIPELINE!$G$6:$G$601,A19,DATA_PIPELINE!$M$6:$M$601) -> 0 | C19: =SUMIF(DATA_PIPELINE!$G$6:$G$601,A19,DATA_PIPELINE!$N$6:$N$601) -> 0 | D19: =B19+C19 -> 0
A20: CHEGUTU | B20: =SUMIF(DATA_PIPELINE!$G$6:$G$601,A20,DATA_PIPELINE!$M$6:$M$601) -> 0 | C20: =SUMIF(DATA_PIPELINE!$G$6:$G$601,A20,DATA_PIPELINE!$N$6:$N$601) -> 0 | D20: =B20+C20 -> 0
A21: GOROMONZI | B21: =SUMIF(DATA_PIPELINE!$G$6:$G$601,A21,DATA_PIPELINE!$M$6:$M$601) -> 6 | C21: =SUMIF(DATA_PIPELINE!$G$6:$G$601,A21,DATA_PIPELINE!$N$6:$N$601) -> 0 | D21: =B21+C21 -> 6
A22: HURUNGWE | B22: =SUMIF(DATA_PIPELINE!$G$6:$G$601,A22,DATA_PIPELINE!$M$6:$M$601) -> 0 | C22: =SUMIF(DATA_PIPELINE!$G$6:$G$601,A22,DATA_PIPELINE!$N$6:$N$601) -> 0 | D22: =B22+C22 -> 0
A23: KADOMA | B23: =SUMIF(DATA_PIPELINE!$G$6:$G$601,A23,DATA_PIPELINE!$M$6:$M$601) -> 0 | C23: =SUMIF(DATA_PIPELINE!$G$6:$G$601,A23,DATA_PIPELINE!$N$6:$N$601) -> 0 | D23: =B23+C23 -> 0
A24: MACHEKE | B24: =SUMIF(DATA_PIPELINE!$G$6:$G$601,A24,DATA_PIPELINE!$M$6:$M$601) -> 0 | C24: =SUMIF(DATA_PIPELINE!$G$6:$G$601,A24,DATA_PIPELINE!$N$6:$N$601) -> 0 | D24: =B24+C24 -> 0
A25: MAKONDE | B25: =SUMIF(DATA_PIPELINE!$G$6:$G$601,A25,DATA_PIPELINE!$M$6:$M$601) -> 0 | C25: =SUMIF(DATA_PIPELINE!$G$6:$G$601,A25,DATA_PIPELINE!$N$6:$N$601) -> 20 | D25: =B25+C25 -> 20
A26: MAKONE | B26: =SUMIF(DATA_PIPELINE!$G$6:$G$601,A26,DATA_PIPELINE!$M$6:$M$601) -> 0 | C26: =SUMIF(DATA_PIPELINE!$G$6:$G$601,A26,DATA_PIPELINE!$N$6:$N$601) -> 0 | D26: =B26+C26 -> 0
A27: MARONDERA | B27: =SUMIF(DATA_PIPELINE!$G$6:$G$601,A27,DATA_PIPELINE!$M$6:$M$601) -> 0 | C27: =SUMIF(DATA_PIPELINE!$G$6:$G$601,A27,DATA_PIPELINE!$N$6:$N$601) -> 0 | D27: =B27+C27 -> 0
A28: MAZOWE | B28: =SUMIF(DATA_PIPELINE!$G$6:$G$601,A28,DATA_PIPELINE!$M$6:$M$601) -> 0 | C28: =SUMIF(DATA_PIPELINE!$G$6:$G$601,A28,DATA_PIPELINE!$N$6:$N$601) -> 0 | D28: =B28+C28 -> 0
A29: MHONDORO NGEZI | B29: =SUMIF(DATA_PIPELINE!$G$6:$G$601,A29,DATA_PIPELINE!$M$6:$M$601) -> 0 | C29: =SUMIF(DATA_PIPELINE!$G$6:$G$601,A29,DATA_PIPELINE!$N$6:$N$601) -> 0 | D29: =B29+C29 -> 0
... A33: ZVIMBA | B33: =SUMIF(DATA_PIPELINE!$G$6:$G$601,A33,DATA_PIPELINE!$M$6:$M$601) -> 0 | C33: =SUMIF(DATA_PIPELINE!$G$6:$G$601,A33,DATA_PIPELINE!$N$6:$N$601) -> 0 | D33: =B33+C33 -> 0

Sheet RECOVERY
A1: RECOVERY PROGRAMME | 2025/2026
A2: ARDA input recovery and outstanding tonnage
A3: =HYPERLINK("#'HOME'!A1","HOME") -> HOME | B3: =HYPERLINK("#'FARMERS'!A1","FARMERS") -> FARMERS | C3: =HYPERLINK("#'SUBSCRIPTIONS'!A1","SUBSCRIPTIONS") -> SUBSCRIPTIONS | D3: =HYPERLINK("#'PRODUCTION'!A1","PRODUCTION") -> PRODUCTION | E3: =HYPERLINK("#'RECOVERY'!A1","RECOVERY") -> RECOVERY | F3: =HYPERLINK("#'DELIVERIES'!A1","DELIVERIES") -> DELIVERIES | G3: =HYPERLINK("#'FINANCE'!A1","FINANCE") -> FINANCE | H3: =HYPERLINK("#'REPORTS'!A1","REPORTS") -> REPORTS
A5: FARMERS IN RECOVERY | C5: ARDA AMOUNT OWED | E5: GRAIN DELIVERED (T) | G5: OUTSTANDING (T) | I5: RECOVERY % | K5: OUTSTANDING VALUE
A6: =COUNTA('INPUT DEBT'!$E$6:$E$569) -> 563 | C6: =SUM('INPUT DEBT'!$H$6:$H$569) -> 3841770.1 | E6: =SUM('INPUT DEBT'!$N$6:$N$569) -> 2173.12 | G6: =SUM('INPUT DEBT'!$O$6:$O$569) -> 9104.35 | I6: =IFERROR(SUM('INPUT DEBT'!$N$6:$N$569)/SUM('INPUT DEBT'!$M$6:$M$569),0) -> 0.1926957 | K6: =SUM('INPUT DEBT'!$O$6:$O$569)*340 -> 3095479
A9: Recovery by province
A10: Province | B10: ARDA Owed | C10: Delivered T | D10: Outstanding T
A11: MANICALAND | B11: =SUMIF('INPUT DEBT'!$B$6:$B$569,A11,'INPUT DEBT'!$H$6:$H$569) -> 12235 | C11: =SUMIF('INPUT DEBT'!$B$6:$B$569,A11,'INPUT DEBT'!$N$6:$N$569) -> 0 | D11: =SUMIF('INPUT DEBT'!$B$6:$B$569,A11,'INPUT DEBT'!$O$6:$O$569) -> 35.99
A12: MASHCENTRAL | B12: =SUMIF('INPUT DEBT'!$B$6:$B$569,A12,'INPUT DEBT'!$H$6:$H$569) -> 205060 | C12: =SUMIF('INPUT DEBT'!$B$6:$B$569,A12,'INPUT DEBT'!$N$6:$N$569) -> 543.36 | D12: =SUMIF('INPUT DEBT'!$B$6:$B$569,A12,'INPUT DEBT'!$O$6:$O$569) -> 59.77
A13: MASHEAST | B13: =SUMIF('INPUT DEBT'!$B$6:$B$569,A13,'INPUT DEBT'!$H$6:$H$569) -> 48616 | C13: =SUMIF('INPUT DEBT'!$B$6:$B$569,A13,'INPUT DEBT'!$N$6:$N$569) -> 6.49 | D13: =SUMIF('INPUT DEBT'!$B$6:$B$569,A13,'INPUT DEBT'!$O$6:$O$569) -> 136.51
A14: MASHWEST | B14: =SUMIF('INPUT DEBT'!$B$6:$B$569,A14,'INPUT DEBT'!$H$6:$H$569) -> 3561280.1 | C14: =SUMIF('INPUT DEBT'!$B$6:$B$569,A14,'INPUT DEBT'!$N$6:$N$569) -> 1611.78 | D14: =SUMIF('INPUT DEBT'!$B$6:$B$569,A14,'INPUT DEBT'!$O$6:$O$569) -> 8840.68
A15: NK | B15: =SUMIF('INPUT DEBT'!$B$6:$B$569,A15,'INPUT DEBT'!$H$6:$H$569) -> 14578.91 | C15: =SUMIF('INPUT DEBT'!$B$6:$B$569,A15,'INPUT DEBT'!$N$6:$N$569) -> 11.49 | D15: =SUMIF('INPUT DEBT'!$B$6:$B$569,A15,'INPUT DEBT'!$O$6:$O$569) -> 31.4
A16: MATABELELAND SOUTH | B16: =SUMIF('INPUT DEBT'!$B$6:$B$569,A16,'INPUT DEBT'!$H$6:$H$569) -> 0 | C16: =SUMIF('INPUT DEBT'!$B$6:$B$569,A16,'INPUT DEBT'!$N$6:$N$569) -> 0 | D16: =SUMIF('INPUT DEBT'!$B$6:$B$569,A16,'INPUT DEBT'!$O$6:$O$569) -> 0
A20: Delivered | B20: Outstanding | C20: Total
A21: =SUM('INPUT DEBT'!$N$6:$N$569) -> 2173.12 | B21: =SUM('INPUT DEBT'!$O$6:$O$569) -> 9104.35 | C21: =A21+B21 -> 11277.47

Sheet MAIZE BUDGET
A1: =HYPERLINK("#'HOME'!A1","HOME") -> HOME | B1: =HYPERLINK("#'MAIZE BUDGET'!A1","MAIZE BUDGET") -> MAIZE BUDGET | D1: =HYPERLINK("#'PRODUCTION'!A1","PRODUCTION") -> PRODUCTION | E1: =HYPERLINK("#'SUBSCRIPTIONS'!A1","SUBSCRIPTIONS") -> SUBSCRIPTIONS
A2: SGR MAIZE BUDGET 2026/27
A3: MAIZE 20,000 HA | EXECUTIVE BUDGET MODEL
A5: SOURCE BUDGET INPUT
A7: ITEM | B7: QUANTITY | C7: COST | D7: TOTAL 1HA | E7: TOTAL FOR 20,000 HA
A8: TILLAGE AND FARM MACHINERY | D8: =IFERROR(B8*C8,0) -> 0 | E8: =D8*20000 -> 0
A9: DISCING(HIRING) | B9: 1 | C9: 80 | D9: =IFERROR(B9*C9,0) -> 80 | E9: =D9*20000 -> 1600000
A10: PLANTING(HIRING) | B10: 1 | C10: 80 | D10: =IFERROR(B10*C10,0) -> 80 | E10: =D10*20000 -> 1600000
A11: SPRAYING/FERTILISATION(HIRING) | B11: 5 | C11: 30 | D11: =IFERROR(B11*C11,0) -> 150 | E11: =D11*20000 -> 3000000
D12: =IFERROR(B12*C12,0) -> 0 | E12: =D12*20000 -> 0
A13: SEED AND FERTILISERS | D13: =IFERROR(B13*C13,0) -> 0 | E13: =D13*20000 -> 0
A14: SEED(SC659) | B14: 25 | C14: 4.5 | D14: =IFERROR(B14*C14,0) -> 112.5 | E14: =D14*20000 -> 2250000
A15: COMP D | B15: 6 | C15: 31 | D15: =IFERROR(B15*C15,0) -> 186 | E15: =D15*20000 -> 3720000
A16: AN | B16: 6 | C16: 36 | D16: =IFERROR(B16*C16,0) -> 216 | E16: =D16*20000 -> 4320000
D17: =IFERROR(B17*C17,0) -> 0 | E17: =D17*20000 -> 0
A18: CHEMICALS | D18: =IFERROR(B18*C18,0) -> 0 | E18: =D18*20000 -> 0
A19: GLYPHOSATE(GRANULES) | B19: 3 | C19: 8 | D19: =IFERROR(B19*C19,0) -> 24 | E19: =D19*20000 -> 480000
A20: ATRAZINE | B20: 3 | C20: 5 | D20: =IFERROR(B20*C20,0) -> 15 | E20: =D20*20000 -> 300000
A21: METOLACHLOR | B21: 2 | C21: 12 | D21: =IFERROR(B21*C21,0) -> 24 | E21: =D21*20000 -> 480000
A22: MUTSVAIRO/NATO | B22: 2 | C22: 12 | D22: =IFERROR(B22*C22,0) -> 24 | E22: =D22*20000 -> 480000
A23: EMMAMECTIN BENSOATE | B23: 0.5 | C23: 50 | D23: =IFERROR(B23*C23,0) -> 25 | E23: =D23*20000 -> 500000
D24: =IFERROR(B24*C24,0) -> 0 | E24: =D24*20000 -> 0
A25: HARVESTING | B25: 1 | C25: 80 | D25: =IFERROR(B25*C25,0) -> 80 | E25: =D25*20000 -> 1600000
A26: LABOUR | B26: 1 | C26: 50 | D26: =IFERROR(B26*C26,0) -> 50 | E26: =D26*20000 -> 1000000
A27: SUBTOTAL | D27: =IFERROR(B27*C27,0) -> 0 | E27: =D27*20000 -> 0
A28: MISCELLENIOUS | B28: 1 | D28: =IFERROR(B28*C28,0) -> 0 | E28: =D28*20000 -> 0
A29: TOTAL VARIABLE COST | D29: =IFERROR(B29*C29,0) -> 0 | E29: =D29*20000 -> 0
A30: TOTAL VARIABLE COST | D30: =SUM(D8:D29) -> 1066.5 | E30: =SUM(E8:E29) -> 21330000
A33: EXECUTIVE COST GROUP DETAIL | HIRING RATES
A34: Group | B34: Item | C34: Rate/Ha | D34: Unit | E34: Cost/Ha | F34: Cost @20,000 HA | G34: Cost @ Funded HA | H34: Source Row
A35: Tillage & Farm Machinery | B35: DISCING (HIRING) | C35: =C9 -> 80 | D35: per ha | E35: =D9 -> 80 | F35: =E35*20000 -> 1600000 | G35: =E35*HOME!$G$53 -> 156000 | H35: 9
A36: Tillage & Farm Machinery | B36: PLANTING (HIRING) | C36: =C10 -> 80 | D36: per ha | E36: =D10 -> 80 | F36: =E36*20000 -> 1600000 | G36: =E36*HOME!$G$53 -> 156000 | H36: 10
A37: Tillage & Farm Machinery | B37: SPRAYING/FERTILISATION (HIRING) | C37: =C11 -> 30 | D37: per ha | E37: =D11 -> 150 | F37: =E37*20000 -> 3000000 | G37: =E37*HOME!$G$53 -> 292500 | H37: 11
A38: Seed & Fertilisers | B38: SEED (SC659) | C38: =C14 -> 4.5 | D38: per ha | E38: =D14 -> 112.5 | F38: =E38*20000 -> 2250000 | G38: =E38*HOME!$G$53 -> 219375 | H38: 14
A39: Seed & Fertilisers | B39: COMP D | C39: =C15 -> 31 | D39: per ha | E39: =D15 -> 186 | F39: =E39*20000 -> 3720000 | G39: =E39*HOME!$G$53 -> 362700 | H39: 15
A40: Seed & Fertilisers | B40: AN | C40: =C16 -> 36 | D40: per ha | E40: =D16 -> 216 | F40: =E40*20000 -> 4320000 | G40: =E40*HOME!$G$53 -> 421200 | H40: 16
A41: Chemicals | B41: GLYPHOSATE (GRANULES) | C41: =C19 -> 8 | D41: per ha | E41: =D19 -> 24 | F41: =E41*20000 -> 480000 | G41: =E41*HOME!$G$53 -> 46800 | H41: 19
A42: Chemicals | B42: ATRAZINE | C42: =C20 -> 5 | D42: per ha | E42: =D20 -> 15 | F42: =E42*20000 -> 300000 | G42: =E42*HOME!$G$53 -> 29250 | H42: 20
A43: Chemicals | B43: METOLACHLOR | C43: =C21 -> 12 | D43: per ha | E43: =D21 -> 24 | F43: =E43*20000 -> 480000 | G43: =E43*HOME!$G$53 -> 46800 | H43: 21
A44: Chemicals | B44: MUTSVAIRO/NATO | C44: =C22 -> 12 | D44: per ha | E44: =D22 -> 24 | F44: =E44*20000 -> 480000 | G44: =E44*HOME!$G$53 -> 46800 | H44: 22
A45: Chemicals | B45: EMMAMECTIN BENSOATE | C45: =C23 -> 50 | D45: per ha | E45: =D23 -> 25 | F45: =E45*20000 -> 500000 | G45: =E45*HOME!$G$53 -> 48750 | H45: 23
A46: Harvesting | B46: HARVESTING | C46: =C25 -> 80 | D46: per ha | E46: =D25 -> 80 | F46: =E46*20000 -> 1600000 | G46: =E46*HOME!$G$53 -> 156000 | H46: 25
A47: Labour | B47: LABOUR | C47: =C26 -> 50 | D47: per ha | E47: =D26 -> 50 | F47: =E47*20000 -> 1000000 | G47: =E47*HOME!$G$53 -> 97500 | H47: 26
A48: Miscellaneous | B48: Miscellaneous (5% of subtotal) | C48: =0.05*SUM(E35:E47) -> 53.325 | D48: per ha | E48: =C48 -> 53.325 | F48: =E48*20000 -> 1066500 | G48: =E48*HOME!$G$53 -> 103983.75 | H48: 25
A49: TOTAL | E49: =SUM(E35:E48) -> 1119.825 | F49: =SUM(F35:F48) -> 22396500 | G49: =SUM(G35:G48) -> 2183658.8
A51: MODEL: Funded maize hectares come from DATA_PIPELINE MAIZE (HA) for farmers with CALCULATED PAYMENT STATUS = Paid or Partly Paid. Funded hectares are capped at the 20,000 HA target.

Sheet MONTHLY SALARY
A1: SGR - MONTHLY SALARY PLAN
A2: Actuals for June-August 2026 and salary planning through December 2026
A4: Month | B4: Planned Salary | C4: Actual Salary | D4: Variance | E4: Status
A5: June 2026 | B5: =IF(C5="","",C5) | D5: =IF(OR(B5="",C5=""),"",C5-B5) | E5: =IF(C5="","Planned",IF(D5=0,"On Plan",IF(D5>0,"Over Budget","Under Budget"))) -> Planned
A6: July 2026 | B6: =IF(C6="","",C6) | D6: =IF(OR(B6="",C6=""),"",C6-B6) | E6: =IF(C6="","Planned",IF(D6=0,"On Plan",IF(D6>0,"Over Budget","Under Budget"))) -> Planned
A7: August 2026 | B7: =IF(C7="","",C7) | D7: =IF(OR(B7="",C7=""),"",C7-B7) | E7: =IF(C7="","Planned",IF(D7=0,"On Plan",IF(D7>0,"Over Budget","Under Budget"))) -> Planned
A8: September 2026 | B8: =IF(C7<>"",C7,0) -> 0 | D8: =IF(OR(B8="",C8=""),"",C8-B8) | E8: =IF(C8="","Planned",IF(D8=0,"On Plan",IF(D8>0,"Over Budget","Under Budget"))) -> Planned
A9: October 2026 | B9: =IF(C7<>"",C7,0) -> 0 | D9: =IF(OR(B9="",C9=""),"",C9-B9) | E9: =IF(C9="","Planned",IF(D9=0,"On Plan",IF(D9>0,"Over Budget","Under Budget"))) -> Planned
A10: November 2026 | B10: =IF(C7<>"",C7,0) -> 0 | D10: =IF(OR(B10="",C10=""),"",C10-B10) | E10: =IF(C10="","Planned",IF(D10=0,"On Plan",IF(D10>0,"Over Budget","Under Budget"))) -> Planned
A11: December 2026 | B11: =IF(C7<>"",C7,0) -> 0 | D11: =IF(OR(B11="",C11=""),"",C11-B11) | E11: =IF(C11="","Planned",IF(D11=0,"On Plan",IF(D11>0,"Over Budget","Under Budget"))) -> Planned
A13: June-December 2026 Summary
A14: Total Planned Salary | B14: =SUM(B5:B11) -> 0
A15: Total Actual Salary | B15: =SUM(C5:C11) -> 0
A16: Total Variance | B16: =SUM(D5:D11) -> 0
